Workbook
Name SegmentaciónDeDatos_AñoMes: #N/A
Name SegmentaciónDeDatos_Categoría1: #N/A
Name TBL_REND_TARGET: REND_TARGET[]

Sheet DQO
B2: DIA | C2: TURNO | D2: HORA | E2: OPERARIO | F2: SALIDA DAF DQO <1000 (mg O2/l) | G2: DAF pH PORTATIL (5,5 - 9,5) (upH) | H2: SALIDA DAF Tª 40 (ºC) | I2: SALIDA DAF CE FIJA <5000 (µS/cm) | K2: DIA_INC | L2: TIPO | M2: PARÁMETRO | N2: VALOR_MUESTRA | O2: VALOR_REFERENCIA | P2: GRAVEDAD_EXP | Q2: COSTE | R2: VENCIMIENTO
B3: 45659 | C3: mañana | D3: 0.32638889 | E3: elena | F3: 53 | G3: 7.44 | I3: 0.95 | K3: 45659 | L3: Desviación | M3: Nitrógeno | N3: 70 | O3: 40 | P3: Grave y Recurrente | Q3: 100 | R3: 46082
B4: 45660 | C4: mañana | D4: 0.33333333 | E4: elena | F4: 43 | G4: 7.56 | I4: 0.94
B5: 45664 | C5: mañana | D5: 0.35416667 | E5: elena | F5: 29 | G5: 7.77 | I5: 0.77
B6: 45665 | C6: mañana | D6: 0.47916667 | E6: elena | F6: 33 | G6: 7.84 | I6: 0.85
B7: 45666 | C7: mañana | D7: 0.55208333 | E7: elena | F7: 56 | G7: 7.39 | I7: 0.7
B8: 45667 | C8: mañana | D8: 0.56944444 | E8: elena | F8: 40 | G8: 7.8 | I8: 1.18
B9: 45673 | C9: mañana | D9: 0.41666667 | E9: elena | F9: 90 | G9: 7.5 | I9: 0.89
B10: 45674 | C10: mañana | D10: 0.375 | E10: elena | F10: 140 | G10: 7.62 | I10: 0.94
B11: 45677 | C11: mañana | D11: 0.51041667 | E11: elena | F11: 94 | G11: 7.5 | I11: 0.91
B12: 45678 | C12: mañana | D12: 0.47916667 | E12: elena | F12: 174 | G12: 7.3 | I12: 0.98
B13: 45679 | C13: mañana | D13: 0.4375 | E13: elena | F13: 126 | G13: 7.47 | I13: 1.22
B14: 45681 | C14: mañana | D14: 0.65972222 | E14: elena | F14: 150 | G14: 7.85 | I14: 1.16
B15: 45692 | C15: mañana | D15: 0.39583333 | E15: elena | F15: 84 | G15: 7.64 | I15: 0.85
... B39: 45754 | C39: mañana | D39: 0.36111111 | E39: DIANA | F39: 13 | G39: 8 | I39: 0.92
B40: =+B39+1 -> 45755 | C40: mañana | D40: 0.33333333 | E40: LAYNER | F40: 123 | G40: 7.67 | I40: 1.04
B41: =+B40+1 -> 45756 | C41: mañana | D41: 0.36805556 | E41: DIANA | F41: 40 | G41: 7.71 | I41: 0.98
B42: =+B41+1 -> 45757 | C42: mañana | D42: 0.58333333 | E42: LAYNER | F42: 34 | G42: 7.83 | I42: 0.95
B43: =+B42+1 -> 45758 | C43: mañana | D43: 0.55555556 | E43: DIANA | F43: 45 | G43: 7.15 | I43: 1.34
B44: =+B43+3 -> 45761 | C44: mañana | D44: 0.30208333 | E44: TAMARA | F44: 44 | G44: 7.6 | I44: 1.21
B45: =+B44+1 -> 45762 | C45: mañana | D45: 0.27083333 | E45: TAMARA | F45: 183 | G45: 7.53 | I45: 1.34
B46: =+B45+1 -> 45763 | C46: mañana | D46: 0.29166667 | E46: TAMARA | F46: 171 | G46: 7.56 | I46: 1.21
B47: 45768 | C47: MAÑANA | D47: 0.36111111 | E47: LAYNER | F47: 115 | G47: 7.53 | I47: 0.9
B48: 45769 | C48: MAÑANA | D48: 0.35069444 | E48: LAYNER | F48: 256 | G48: 7.72 | I48: 0.99
B49: 45771 | C49: MAÑANA | D49: 0.47222222 | E49: DIANA | F49: 264 | G49: 7.32 | I49: 0.91
B50: 45772 | C50: MAÑANA | D50: 0.4375 | E50: LAYNER | F50: 179 | G50: 7.44 | I50: 0.91
B51: 45775 | C51: MAÑANA | D51: 0.35416667 | E51: DIANA | F51: 119 | G51: 7.73 | I51: 0.87
B52: 45776 | C52: MAÑANA | D52: 0.41666667 | E52: TAMARA | F52: 358 | G52: 4.59 | I52: 1.04
B53: 45777 | C53: MAÑANA | D53: 0.33333333 | E53: DIANA | F53: 602 | G53: 7.47 | I53: 1.26
B54: 45778 | C54: MAÑANA | D54: 0.36111111 | E54: LAYNER | F54: 405 | G54: 7.62 | I54: 1.18
B55: 45779 | C55: MAÑANA | D55: 0.34375 | E55: TAMARA | F55: 245 | G55: 7.71 | I55: 1.1
B56: 45782 | C56: MAÑANA | D56: 0.44444444 | E56: DIANA Y LAYNER | F56: 367 | G56: 7.74 | I56: 1.13
B57: 45783 | C57: MAÑANA | D57: 0.50347222 | E57: DIANA Y LAYNER | F57: 636 | G57: 7.56 | I57: 1.07
B58: 45784 | C58: MAÑANA | D58: 0.48958333 | E58: DIANA Y LAYNER | F58: 868 | G58: 7.01 | I58: 1.37
... B68: 45798 | C68: MAÑANA | D68: 0.53472222 | E68: DIANA Y LAYNER | F68: 248 | G68: 7.64 | I68: 1.05
B69: 45799 | C69: MAÑANA | E69: DIANA Y LAYNER | F69: 221 | G69: 7.52 | I69: 0.94
B70: 45800 | C70: MAÑANA | D70: 0.45833333 | E70: DIANA Y LAYNER | F70: 203 | G70: 7.4 | I70: 0.88
B71: 45803 | C71: MAÑANA | D71: 0.375 | E71: DIANA Y ABY | F71: 180 | G71: 7.87 | I71: 0.98
B72: 45804 | C72: MAÑANA | D72: 0.34722222 | E72: DIANA Y MARTA | F72: 350 | G72: 7.51 | I72: 1.06
B73: 45805 | C73: MAÑANA | D73: 0.43055556 | E73: DIANA Y MARTA | F73: 457 | G73: 7.16 | I73: 0.99
B74: 45810 | C74: MAÑANA | D74: 0.32638889 | E74: LAYNER | F74: 321 | G74: 7.87 | I74: 1.17
B75: 45812 | C75: MAÑANA | D75: 0.39583333 | E75: LAYNER | F75: 1500 | G75: 7 | I75: 1.23
B76: 45813 | C76: MAÑANA | D76: 0.40625 | E76: LAYNER | F76: 461 | G76: 6.84 | I76: 1.02
B77: 45814 | C77: MAÑANA | D77: 0.45833333 | E77: LAYNER | F77: 873 | G77: 7.42 | I77: 1.22
B78: 45817 | C78: MAÑANA | D78: 0.38194444 | E78: MARTA | F78: 264 | G78: 8.09 | I78: 1.08
B79: 45818 | C79: MAÑANA | D79: 0.43055556 | E79: MARTA | F79: 360 | G79: 7.6 | I79: 0.98
B80: 45819 | C80: MAÑANA | D80: 10;50 | E80: DIANA | F80: 338 | G80: 7.55 | I80: 0.88
B81: 45820 | C81: MAÑANA | D81: 9,:31 | E81: MARTA | F81: 451 | G81: 7.48 | I81: 0.93
B82: 45821 | C82: MAÑANA | D82: 0.39375 | E82: DIANA | F82: 386 | G82: 7.38 | I82: 1.01
B83: 45824 | C83: MAÑANA | D83: 0.45833333 | F83: 328 | G83: 7.91 | I83: 1.32
B84: 45825 | C84: MAÑANA | D84: 08;30 | F84: 111 | G84: 7.67 | I84: 1.17
B85: 45827 | C85: MAÑANA | D85: 11,:30 | F85: 234 | G85: 7.61 | I85: 0.98
B86: 45841 | C86: MAÑANA | D86: 0.34722222 | E86: LAYNER | F86: 142 | G86: 7.26 | I86: 3
B87: 45842 | C87: MAÑANA | D87: 0.36805556 | E87: LAYNER | F87: 154 | G87: 7.94 | I87: 2.27
B88: 45845 | C88: MAÑANA | D88: 0.32291667 | E88: DIANA | F88: 59 | G88: 8.32 | I88: 2.04
B89: 45846 | C89: MAÑANA | D89: 0.4375 | E89: DIANA | F89: 174 | G89: 7.52 | I89: 1.59
B90: 45847 | C90: MAÑANA | D90: 0.40625 | E90: ELENA | F90: 80 | G90: 7.58 | I90: 1.4
B91: 45848 | C91: MAÑANA | D91: 0.39583333 | E91: DIANA | F91: 123 | G91: 7.75 | I91: 1.72
B92: 45849 | C92: MAÑANA | D92: 0.47916667 | E92: DIANA | F92: 74 | G92: 8.15 | I92: 1.56
B93: 45852 | C93: MAÑANA | D93: 0.38888889 | E93: LAYNER | F93: 67 | G93: 8.07 | I93: 1.62
B94: 45853 | C94: MAÑANA | D94: 0.375 | E94: LAYNER | F94: 187 | G94: 7.98 | I94: 1.77
B95: 45854 | C95: MAÑANA | D95: 0.41666667 | E95: LAYNER | F95: 108 | G95: 7.97 | I95: 1.51
B96: 45855 | C96: MAÑANA | D96: 0.41666667 | E96: LAYNER | F96: 248 | G96: 7.72 | I96: 1.29
B97: 45856 | C97: MAÑANA | D97: 0.42708333 | E97: LAYNER | F97: 240 | G97: 7.92 | I97: 1.26
... B142: 45919 | C142: MAÑANA | D142: 0.45833333 | E142: ABBY/DIANA | F142: 33 | G142: 7.73 | I142: 1.65
B143: 45922 | C143: MAÑANA | D143: 0.42708333 | E143: DIANA/LAYNER | F143: 6 | G143: 8.4 | H143: - | I143: 1.46
B144: 45923 | C144: MAÑANA | D144: 0.38888889 | E144: LAYNER | F144: 44 | G144: 7.63 | H144: - | I144: 1.53
B145: 45924 | C145: MAÑANA | D145: 0.36111111 | E145: LAYNER | F145: 42 | G145: 8.01 | H145: - | I145: 1.41
B146: 45925 | C146: MAÑANA | D146: 0.43055556 | E146: LAYNER | F146: 96 | G146: 7.78 | H146: 17 | I146: 1.39
B147: 45926 | C147: MAÑANA | D147: 0.39583333 | E147: LAYNER | F147: 49 | G147: 8.14 | H147: 0 | I147: 1.25
B148: 45929 | C148: MAÑANA | D148: 0.39583333 | E148: DIANA/LAYNER | F148: 43 | G148: 7.91 | H148: 4 | I148: 1.28
B149: 45930 | C149: MAÑANA | D149: 0.40277778 | E149: DIANA/LAYNER | F149: 54 | G149: 7.51 | H149: 3 | I149: 1.57
B150: 45931 | C150: MAÑANA | D150: 0.39930556 | E150: DIANA/LAYNER | F150: 98 | G150: 8.05 | H150: 0 | I150: 1.49
B151: 45932 | C151: MAÑANA | D151: 0.38888889 | E151: DIANA/LAYNER | F151: 77 | G151: 7.97 | H151: 5 | I151: 1.55
B152: 45933 | C152: MAÑANA | D152: 0.47569444 | E152: DIANA/LAYNER | F152: 50 | G152: 7.87 | H152: 5 | I152: 1.44
B153: 45936 | C153: MAÑANA | D153: 0.41319444 | E153: ABBY | F153: 58 | G153: 7.91 | H153: 6 | I153: 1.38
B154: 45937 | C154: MAÑANA | D154: 0.35763889 | E154: ABBY | F154: 79 | G154: 7.6 | H154: 18 | I154: 1.15
B155: 45938 | C155: MAÑANA | D155: 0.375 | E155: MARTA/ABBY | F155: 42 | G155: 7.61 | H155: 11 | I155: 1.27
B156: 45939 | C156: MAÑANA | D156: 0.36805556 | E156: MARTA/ABBY | F156: 45 | G156: 8.01 | H156: 6 | I156: 1.38
B157: 45940 | C157: MAÑANA | D157: 0.41666667 | E157: MARTA/DIANA | F157: 67 | G157: 7.85 | H157: 13 | I157: 1.66
... B235: 46051 | C235: MAÑANA | D235: 0.41666667 | E235: LAYNER Y DIANA | F235: 75 | G235: 7.24 | H235: 14 | I235: 1.33
B236: 46052 | C236: MAÑANA | D236: 9.30 | E236: LAYNER Y DIANA | F236: 98 | G236: 7.41 | H236: 0 | I236: 1.17
B237: 46055 | C237: MAÑANA | D237: 0.35416667 | E237: LAYNER | F237: 36 | G237: 7.61 | H237: 6 | I237: 1.08
B238: 46056 | C238: MAÑANA | D238: 0.36805556 | E238: LAYNER | F238: 78 | G238: 7.67 | H238: 19 | I238: 1.2
B239: 46057 | C239: MAÑANA | D239: 0.375 | E239: LAYNER | F239: 64 | G239: 7.86 | H239: 26 | I239: 1.3
B240: 46058 | C240: MAÑANA | D240: 0.41666667 | E240: LAYNER | F240: 96 | G240: 7.71 | H240: 18 | I240: 1.22
B241: 46059 | C241: MAÑANA | D241: 0.39583333 | E241: LAYNER | F241: 577 | G241: 7.49 | H241: 36 | I241: 1.12
B242: 46062 | C242: MAÑANA | D242: 0.5 | E242: MARTA Y DIANA | F242: - | G242: - | H242: - | I242: -
B243: 46063 | C243: MAÑANA | D243: 0.51736111 | E243: MARTA Y DIANA | F243: - | G243: - | H243: - | I243: -
B244: 46064 | C244: MAÑANA | D244: 0.51388889 | E244: MARTA Y DIANA | F244: 66 | G244: 7.7 | H244: 19 | I244: 1.13
B245: 46065 | C245: MAÑANA | D245: 0.48611111 | E245: MARTA Y DIANA | F245: 68 | G245: 7.38 | H245: 15 | I245: 1.23
B246: 46066 | C246: MAÑANA | D246: 0.47916667 | E246: MARTA Y DIANA | F246: 49 | G246: 7.46 | H246: 9 | I246: 1.45
B247: 46069 | C247: MAÑANA | D247: 0.43055556 | E247: LAYNER Y DIANA | F247: - | G247: - | H247: - | I247: -
B248: 46070 | C248: MAÑANA | D248: 0.43055556 | E248: LAYNER Y DIANA | F248: 45 | G248: 7.51 | H248: 19 | I248: 2.43
B249: 46071 | C249: MAÑANA | D249: 9.5 | E249: LAYNER | F249: 76 | G249: 7.55 | H249: 20 | I249: 3.32
B250: 46072 | C250: MAÑANA | D250: 0.4375 | E250: LAYNER Y DIANA | F250: 44 | G250: 7.55 | H250: 17 | I250: 2.8
B251: 46073 | C251: MAÑANA | D251: 0.4375 | E251: LAYNER Y DIANA | F251: 38 | G251: 7.72 | H251: 3 | I251: 2.13
B252: 46076 | C252: MAÑANA | D252: 0.41666667 | E252: LAYNER Y DIANA | F252: - | G252: - | H252: - | I252: -
B253: 46077 | C253: MAÑANA | D253: 0.41666667 | E253: LAYNER Y DIANA | F253: 68 | G253: 7.36 | H253: 26 | I253: 2.38
B254: 46078 | C254: MAÑANA | D254: 0.4375 | E254: LAYNER Y DIANA | F254: 60 | G254: 7.22 | H254: 41 | I254: 2.46
...

Sheet Base_Rendimientos
A1: =3045*0.42 -> 1278.9 | G1: =+E1+A1 -> 1278.9 | I1: =SUBTOTAL(9,I2:I323) -> 47855848 | J1: =SUBTOTAL(9,J2:J323) -> 47263334 | O1: =SUBTOTAL(9,O2:O323) -> 554214 | R1: =SUBTOTAL(9,R2:R323)/J1 -> 0.022494372 | S1: =SUBTOTAL(9,S2:S323) -> 14008.66 | T1: =SUBTOTAL(9,T2:T323)/I1 -> 0.88617174 | U1: =+T1 -> 0.88617174 | V1: =SUMPRODUCT(Tabla_master_rend[MG_suero],Tabla_master_rend[L_suero Total]) -> 62427.917 | W1: =SUMPRODUCT(Tabla_master_rend[MP_suero],Tabla_master_rend[L_suero Total]) -> 372620.09 | X1: =SUBTOTAL(9,X2:X323) -> 33659758 | Y1: =SUBTOTAL(9,Y2:Y323) -> 11266351 | Z1: =+X1/Y1 -> 2.9876362 | AA1: =SUBTOTAL(9,AA2:AA323) -> 8748741.8 | AD1: =SUBTOTAL(9,AD2:AD323) -> 850930 | AE1: =SUBTOTAL(9,AE2:AE323) -> 0 | AH1: =+G1/15224 -> 0.084005518 | AI1: =SUBTOTAL(9,AI2:AI323) -> 5384399.1 | AJ1: =+I1/AI1 -> 8.8878717 | AK1: =+I1/(AI1-BR1) -> 9.1812137 | AM1: =SUBTOTAL(9,AM2:AM323) -> 3535676 | AR1: =SUBTOTAL(9,AR2:AR323) -> 425263.6 | AU1: =SUBTOTAL(9,AU2:AU323) -> 3189477 | AV1: =SUBTOTAL(9,AV2:AV323) -> 9391.84 | AW1: =SUBTOTAL(9,AW2:AW323) -> 21347.1 | AX1: =SUBTOTAL(9,AX2:AX323) -> 8546.9 | AY1: =SUBTOTAL(9,AY2:AY323) -> 39285.84 | AZ1: =+(AV1+AW1+AX1)/(AI1) -> 0.0072962348 | BA1: =SUBTOTAL(9,BA2:BA323) -> 59701 | BB1: =+BA1/(BA1+BK1) -> 0.011169268 | BC1: =SUBTOTAL(9,BC2:BC323) -> 742777 | BD1: =SUBTOTAL(9,BD2:BD323) -> 722503 | BE1: =SUBTOTAL(9,BE2:BE323) -> 5225397 | BF1: =SUBTOTAL(9,BF2:BF323) -> 41843 | BG1: =SUBTOTAL(9,BG2:BG323) -> 44643.1 | BH1: =SUBTOTAL(9,BH2:BH323) -> 6265.6 | BI1: =SUBTOTAL(9,BI2:BI323) -> 51996.2 | BJ1: =SUBTOTAL(9,BJ2:BJ323) -> 20660 | ... BN1: =SUBTOTAL(9,BN2:BN323) -> 4779.06 | BO1: =+BM1/BK1 -> 0.012868915 | BP1: =+BO1*(1-BZ1) -> 0.0083733744 | BQ1: =+BR1/AI1 -> 0.031950241 | BR1: =SUBTOTAL(9,BR2:BR323) -> 172032.85 | BS1: =SUBTOTAL(9,BS2:BS323) -> 2713819.7 | BT1: =SUBTOTAL(9,BT2:BT591) -> -24776.58 | BU1: =+BT1/BK1 -> -0.0046877289 | BW1: Precio Nata | BX1: =SUBTOTAL(9,BX2:BX323) -> 264394.74 | BY1: =SUBTOTAL(9,BY2:BY323) -> 92361.889 | BZ1: =+BY1/BX1 -> 0.34933331 | CA1: 0.0065 | CB1: 0.01 | CC1: 0.0105 | CD1: =SUBTOTAL(9,CD2:CD323) -> 109814.82 | CE1: =+CD1/AI1 -> 0.020395 | CF1: =+BR1/AI1 -> 0.031950241 | CG1: =SUBTOTAL(9,CG2:CG323) -> -62218.032 | CI1: =SUBTOTAL(9,CI2:CI323) -> -80883.441
A2: Fecha | B2: mes | C2: Mes_Nom | D2: Día | E2: Lote | F2: Tipo_Leche | G2: Producto | H2: Cubas_prod | I2: Litros_Leche_Total | J2: L_Leche_ent | K2: %MG_Leche | L2: %MP_Leche | M2: EST_% | N2: Desn_en_linea | O2: L_desn_ext | P2: L_cabra | Q2: L_oveja | R2: Litros_Nata | S2: L_nata_suero | T2: L_suero Total | U2: %Suero_vs_leche | V2: MG_suero | W2: MP_suero | X2: L_suero para con | Y2: L_suero_con | Z2: Rartio_sueroC | AA2: L_Suero_Sobrante | AB2: MG_sueroc | AC2: MP_sueroc | AD2: L_LPS_Gen | AE2: L_LPS_incor | AF2: gr_LPS | AG2: MG_LPS | AH2: MP_LPS | AI2: Kg_Queso_Blan | AJ2: RDTO_Blanco | AK2: RDTO_NETO | AL2: REND_TARGET | AM2: Kg_Solidos_leche | AN2: %MG_QUESO | AO2: %PT_QUESO | AP2: ES_QUESO | AQ2: Rendimiento_Solidos_% | AR2: Kg_MG_Nata | AS2: %RECUP_MG | AT2: %RECUP_PT | AU2: Valor_Nata_€ | AV2: Kg_Finos | AW2: Kg_Llenadora | AX2: Kg_Desmoldeo | AY2: Merma_fab | AZ2: % Merma_fab2 | BA2: L_Agua | BB2: % oreo | BC2: B_totales | BD2: B_OK_uni | BE2: B_OK_kg | BF2: B_altas | BG2: B_bajas | BH2: B_rotas | BI2: B_feas | BJ2: B_lab | BK2: Kg_SalidaSecadero | BL2: Kg_rebaba | BM2: Kg_mer_env_real | BN2: kg_mer_lab_real | BO2: %Merma_env | BP2: %Merma_env_corr | BQ2: % merma TOT | BR2: Merma_TOT | BS2: Kg_Env_Total | BT2: Diferencia_Env_vs_Sec_kg | BU2: Diferencia_Env_vs_Sec_% | BV2: Coste_Leche_€ | BW2: €/kg_MPQueso | BX2: Merma_inic | BY2: Recup_kg | BZ2: Recup_% | CA2: Merma_ppto fab | CB2: Merma_ppto oreo | CC2: Merma_ppto Env/Enc | CD2: Merma_T ppto | CE2: Merma_T ppto % | CF2: Merma_T real % | CG2: DIF R Vs PPTO | CH2: IMPACTO | CI2: IMPACTO_vs_PPTO | CK2: DATO MEDIA ENE | CM2: 1.3 | CO2: Precio Nata
A3: 45659 | B3: 1 | C3: =+UPPER(TEXT(Tabla_master_rend[[#This Row],[Fecha]],"MMM")) -> ENE | D3: =+UPPER(TEXT(Tabla_master_rend[[#This Row],[Fecha]],"ddd")) -> JU | E3: 020125726 | F3: VACA | G3: GOUDA_LIGHT | H3: 2 | I3: =+Tabla_master_rend[[#This Row],[L_Leche_ent]]+Tabla_master_rend[[#This Row],[L_desn_ext]]+Tabla_master_rend[[#This Row],[L_cabra]]+Tabla_master_rend[[#This Row],[L_oveja]] -> 31269 | J3: 31269 | K3: 0.0424 | L3: 0.0351 | M3: =0.93*K3+0.74*L3+0.048 -> 0.113406 | N3: NO | O3: 0 | P3: 0 | Q3: 0 | R3: 1953.3 | T3: 27600 | U3: =+Tabla_master_rend[[#This Row],[L_suero Total]]/Tabla_master_rend[[#This Row],[Litros_Leche_Total]] -> 0.88266334 | V3: 0.0023 | W3: 0.0099 | X3: =112998/(211440+27600)*27600 -> 13046.958 | Y3: =(8475+25405)/(211440+27600)*27600 -> 3911.8474 | Z3: =IF(Tabla_master_rend[[#This Row],[L_suero para con]]=0,0,+Tabla_master_rend[[#This Row],[L_suero para con]]/Tabla_master_rend[[#This Row],[L_suero_con]]) -> 3.335242 | AA3: =+Tabla_master_rend[[#This Row],[L_suero Total]]-Tabla_master_rend[[#This Row],[L_suero para con]] -> 14553.042 | AD3: 0 | AE3: 0 | AF3: 0 | AG3: 0 | AH3: 0 | AI3: =+Tabla_master_rend[[#This Row],[Kg_Finos]]+Tabla_master_rend[[#This Row],[Kg_Llenadora]]+Tabla_master_rend[[#This Row],[Kg_Desmoldeo]]+Tabla_master_rend[[#This Row],[L_Agua]]+Tabla_master_rend[[#This Row],[Kg_SalidaSecadero]] -> 2909.7116 | AJ3: =+Tabla_master_rend[[#This Row],[Litros_Leche_Total]]/Tabla_master_rend[[#This Row],[Kg_Queso_Blan]] -> 10.746426 | AK3: =+Tabla_master_rend[[#This Row],[Litros_Leche_Total]]/(Tabla_master_rend[[#This Row],[Kg_Queso_Blan]]-Tabla_master_rend[[#This Row],[Merma_TOT]]) -> 11.53744 | AL3: =VLOOKUP(G3,REND_TARGET[#All],8,FALSE) -> #N/A | AM3: =(I3*1.03*Tabla_master_rend[[#This Row],[%MG_Leche]])+(I3*1.03*Tabla_master_rend[[#This Row],[%MP_Leche]]) -> 2496.0479 | AN3: 0.1792 | AO3: 0.2809 | AP3: 0.5123 | AQ3: =+Tabla_master_rend[[#This Row],[Kg_Queso_Blan]]*Tabla_master_rend[[#This Row],[ES_QUESO]]/(Tabla_master_rend[[#This Row],[Kg_Solidos_leche]]) -> 0.59720217 | AR3: =R3*0.4 -> 781.32 | AS3: =+(Tabla_master_rend[[#This Row],[Kg_Queso_Blan]]*Tabla_master_rend[[#This Row],[%MG_QUESO]]+(Tabla_master_rend[[#This Row],[Kg_MG_Nata]]))/(Tabla_master_rend[[#This Row],[Litros_Leche_Total]]*1.03*Tabla_master_rend[[#This Row],[%MG_Leche]]) -> 0.95398332 | AT3: =+Tabla_master_rend[[#This Row],[Kg_Queso_Blan]]*Tabla_master_rend[[#This Row],[%PT_QUESO]]/(Tabla_master_rend[[#This Row],[Litros_Leche_Total]]*1.03*Tabla_master_rend[[#This Row],[%MP_Leche]]) -> 0.72300841 | AU3: =AR3*$CO$3 -> 5859.9 | AV3: 7.1115939 | AW3: 9.3 | AX3: 20.3 | AY3: =SUM(Tabla_master_rend[[#This Row],[Kg_Finos]:[Kg_Desmoldeo]]) -> 36.711594 | AZ3: =+(Tabla_master_rend[[#This Row],[Kg_Finos]]+Tabla_master_rend[[#This Row],[Kg_Llenadora]]+Tabla_master_rend[[#This Row],[Kg_Desmoldeo]])/(Tabla_master_rend[[#This Row],[Kg_Queso_Blan]]) -> 0.012616918 | BA3: 30 | BB3: =+Tabla_master_rend[[#This Row],[L_Agua]]/(Tabla_master_rend[[#This Row],[L_Agua]]+Tabla_master_rend[[#This Row],[Kg_SalidaSecadero]]) -> 0.010442047 | BC3: 423 | BD3: 385 | BE3: 2650 | BF3: 0 | BG3: 0 | BH3: =11*5.8 -> 63.8 | BI3: =22*5.8 -> 127.6 | BJ3: 30 | BK3: 2843 | BL3: 1.16 | BM3: 127.41 | BN3: 4.21 | BO3: =+SUM(Tabla_master_rend[[#This Row],[B_altas]:[B_lab]])/Tabla_master_rend[[#This Row],[Kg_SalidaSecadero]] -> 0.077875484 | BP3: =+(Tabla_master_rend[[#This Row],[Kg_mer_env_real]]+Tabla_master_rend[[#This Row],[kg_mer_lab_real]])/Tabla_master_rend[[#This Row],[Kg_SalidaSecadero]] -> 0.046296166 | BQ3: =+Tabla_master_rend[[#This Row],[Merma_TOT]]/Tabla_master_rend[[#This Row],[Kg_Queso_Blan]] -> 0.068560607 | BR3: =+Tabla_master_rend[[#This Row],[kg_mer_lab_real]]+Tabla_master_rend[[#This Row],[Kg_mer_env_real]]+Tabla_master_rend[[#This Row],[Kg_rebaba]]+Tabla_master_rend[[#This Row],[L_Agua]]+Tabla_master_rend[[#This Row],[Kg_Desmoldeo]]+Tabla_master_rend[[#This Row],[Kg_Llenadora]]+Tabla_master_rend[[#This Row],[Kg_Finos]] -> 199.49159 | BT3: =IF(+Tabla_master_rend[[#This Row],[Kg_Env_Total]]=0,0,Tabla_master_rend[[#This Row],[Kg_Env_Total]]-Tabla_master_rend[[#This Row],[Kg_SalidaSecadero]]) -> 0 | BU3: =+Tabla_master_rend[[#This Row],[Diferencia_Env_vs_Sec_kg]]/Tabla_master_rend[[#This Row],[Kg_SalidaSecadero]] -> 0 | BV3: =IFERROR(Tabla_master_rend[[#This Row],[Litros_Leche_Total]]*SUMIFS(tbl_PrecioLeche[PMV_eur_L],tbl_PrecioLeche[AñoMes],TEXT(Tabla_master_rend[[#This Row],[Fecha]],"yyyy-mm"),tbl_PrecioLeche[Tipo_Leche],Tabla_master_rend[[#This Row],[Tipo_Leche]]),"") -> 0 | BW3: =+(Tabla_master_rend[[#This Row],[Coste_Leche_€]]-Tabla_master_rend[[#This Row],[Kg_MG_Nata]]*$CO$3)/Tabla_master_rend[[#This Row],[Kg_Queso_Blan]] -> -2.0139109 | BX3: =SUM(Tabla_master_rend[[#This Row],[Kg_Finos]:[Kg_Desmoldeo]])+Tabla_master_rend[[#This Row],[L_Agua]]+SUM(Tabla_master_rend[[#This Row],[B_altas]:[B_lab]]) -> 288.11159 | BY3: =+BX3-Tabla_master_rend[[#This Row],[Merma_TOT]] -> 88.62 | BZ3: =+BY3/BX3 -> 0.30758915 | CA3: =+Tabla_master_rend[[#This Row],[Kg_Queso_Blan]]*$CA$1 -> 18.913125 | CB3: =+Tabla_master_rend[[#This Row],[Kg_Queso_Blan]]*($CB$1-$CA$1) -> 10.183991 | CC3: =+(Tabla_master_rend[[#This Row],[Kg_Queso_Blan]]-CA3-CB3)*$CC$1 -> 30.246452 | CD3: =+CA3+CB3+CC3 -> 59.343568 | CE3: =+CD3/Tabla_master_rend[[#This Row],[Kg_Queso_Blan]] -> 0.020395 | CF3: =+Tabla_master_rend[[#This Row],[Merma_TOT]]/Tabla_master_rend[[#This Row],[Kg_Queso_Blan]] -> 0.068560607 | CG3: =CD3-Tabla_master_rend[[#This Row],[Merma_TOT]] -> -140.14803 | CH3: {=-BR3 * IFERROR(INDEX('Precio Leche_EBITDA_Ventas'!$BD$87:$BD$110,MATCH(1,('Precio Leche_EBITDA_Ventas'!$AZ$87:$AZ$110=YEAR(A3))*('Precio Leche_EBITDA_Ventas'!$BB$87:$BB$110=C3),0)),1.3)} -> -698.22058 | CI3: =+CG3*$CM$2 -> -182.19243 | CK3: Venta Kg Q Ok | CM3: 4.775 | CO3: 7.5
A4: 45659 | B4: 1 | C4: =+UPPER(TEXT(Tabla_master_rend[[#This Row],[Fecha]],"MMM")) -> ENE | D4: =+UPPER(TEXT(Tabla_master_rend[[#This Row],[Fecha]],"ddd")) -> JU | E4: 020125226 | F4: VACA | G4: GOUDA | H4: 15 | I4: =+Tabla_master_rend[[#This Row],[L_Leche_ent]]+Tabla_master_rend[[#This Row],[L_desn_ext]]+Tabla_master_rend[[#This Row],[L_cabra]]+Tabla_master_rend[[#This Row],[L_oveja]] -> 229311 | J4: 229311 | K4: 0.0402 | L4: 0.0339 | M4: =0.93*K4+0.74*L4+0.048 -> 0.110472 | N4: NO | O4: 0 | P4: 0 | Q4: 0 | R4: 3791.7 | T4: 211440 | U4: =+Tabla_master_rend[[#This Row],[L_suero Total]]/Tabla_master_rend[[#This Row],[Litros_Leche_Total]] -> 0.92206654 | V4: 0.0023 | W4: 0.0099 | X4: =112998/(211440+27600)*211440 -> 99951.042 | Y4: =(8475+25405)/(211440+27600)*211440 -> 29968.153 | Z4: =IF(Tabla_master_rend[[#This Row],[L_suero para con]]=0,0,+Tabla_master_rend[[#This Row],[L_suero para con]]/Tabla_master_rend[[#This Row],[L_suero_con]]) -> 3.335242 | AA4: =+Tabla_master_rend[[#This Row],[L_suero Total]]-Tabla_master_rend[[#This Row],[L_suero para con]] -> 111488.96 | AD4: 5516 | AE4: 0 | AF4: 0 | AG4: 0.0117 | AH4: 0.058 | AI4: =+Tabla_master_rend[[#This Row],[Kg_Finos]]+Tabla_master_rend[[#This Row],[Kg_Llenadora]]+Tabla_master_rend[[#This Row],[Kg_Desmoldeo]]+Tabla_master_rend[[#This Row],[L_Agua]]+Tabla_master_rend[[#This Row],[Kg_SalidaSecadero]] -> 26762.988 | AJ4: =+Tabla_master_rend[[#This Row],[Litros_Leche_Total]]/Tabla_master_rend[[#This Row],[Kg_Queso_Blan]] -> 8.5682136 | AK4: =+Tabla_master_rend[[#This Row],[Litros_Leche_Total]]/(Tabla_master_rend[[#This Row],[Kg_Queso_Blan]]-Tabla_master_rend[[#This Row],[Merma_TOT]]) -> 8.8494834 | AL4: =VLOOKUP(G4,REND_TARGET[#All],8,FALSE) -> 8.494317 | AM4: =(I4*1.03*Tabla_master_rend[[#This Row],[%MG_Leche]])+(I4*1.03*Tabla_master_rend[[#This Row],[%MP_Leche]]) -> 17501.703 | AN4: 0.2846 | AO4: 0.2323 | AP4: 0.5668 | AQ4: =+Tabla_master_rend[[#This Row],[Kg_Queso_Blan]]*Tabla_master_rend[[#This Row],[ES_QUESO]]/(Tabla_master_rend[[#This Row],[Kg_Solidos_leche]]) -> 0.86673059 | AR4: =R4*0.4 -> 1516.68 | AS4: =+(Tabla_master_rend[[#This Row],[Kg_Queso_Blan]]*Tabla_master_rend[[#This Row],[%MG_QUESO]]+(Tabla_master_rend[[#This Row],[Kg_MG_Nata]]))/(Tabla_master_rend[[#This Row],[Litros_Leche_Total]]*1.03*Tabla_master_rend[[#This Row],[%MG_Leche]]) -> 0.96193466 | AT4: =+Tabla_master_rend[[#This Row],[Kg_Queso_Blan]]*Tabla_master_rend[[#This Row],[%PT_QUESO]]/(Tabla_master_rend[[#This Row],[Litros_Leche_Total]]*1.03*Tabla_master_rend[[#This Row],[%MP_Leche]]) -> 0.77646522 | AU4: =AR4*$CO$3 -> 11375.1 | AV4: 64.088406 | AW4: 99.9 | AX4: 6 | AY4: =SUM(Tabla_master_rend[[#This Row],[Kg_Finos]:[Kg_Desmoldeo]]) -> 169.98841 | AZ4: =+(Tabla_master_rend[[#This Row],[Kg_Finos]]+Tabla_master_rend[[#This Row],[Kg_Llenadora]]+Tabla_master_rend[[#This Row],[Kg_Desmoldeo]])/(Tabla_master_rend[[#This Row],[Kg_Queso_Blan]]) -> 0.0063516228 | BA4: 545 | BB4: =+Tabla_master_rend[[#This Row],[L_Agua]]/(Tabla_master_rend[[#This Row],[L_Agua]]+Tabla_master_rend[[#This Row],[Kg_SalidaSecadero]]) -> 0.020494115 | BC4: 3812 | BD4: 3773 | BE4: 26343 | BF4: 0 | BG4: 0 | BH4: =10*6.7 -> 67 | BI4: =14*6.7 -> 93.8 | BJ4: 90 | BK4: 26048 | BL4: 5 | BM4: 116.46 | BN4: 14.18 | BO4: =+SUM(Tabla_master_rend[[#This Row],[B_altas]:[B_lab]])/Tabla_master_rend[[#This Row],[Kg_SalidaSecadero]] -> 0.0096283784 | BP4: =+(Tabla_master_rend[[#This Row],[Kg_mer_env_real]]+Tabla_master_rend[[#This Row],[kg_mer_lab_real]])/Tabla_master_rend[[#This Row],[Kg_SalidaSecadero]] -> 0.0050153563 | BQ4: =+Tabla_master_rend[[#This Row],[Merma_TOT]]/Tabla_master_rend[[#This Row],[Kg_Queso_Blan]] -> 0.03178376 | BR4: =+Tabla_master_rend[[#This Row],[kg_mer_lab_real]]+Tabla_master_rend[[#This Row],[Kg_mer_env_real]]+Tabla_master_rend[[#This Row],[Kg_rebaba]]+Tabla_master_rend[[#This Row],[L_Agua]]+Tabla_master_rend[[#This Row],[Kg_Desmoldeo]]+Tabla_master_rend[[#This Row],[Kg_Llenadora]]+Tabla_master_rend[[#This Row],[Kg_Finos]] -> 850.62841 | BT4: =IF(+Tabla_master_rend[[#This Row],[Kg_Env_Total]]=0,0,Tabla_master_rend[[#This Row],[Kg_Env_Total]]-Tabla_master_rend[[#This Row],[Kg_SalidaSecadero]]) -> 0 | BU4: =+Tabla_master_rend[[#This Row],[Diferencia_Env_vs_Sec_kg]]/Tabla_master_rend[[#This Row],[Kg_SalidaSecadero]] -> 0 | BV4: =IFERROR(Tabla_master_rend[[#This Row],[Litros_Leche_Total]]*SUMIFS(tbl_PrecioLeche[PMV_eur_L],tbl_PrecioLeche[AñoMes],TEXT(Tabla_master_rend[[#This Row],[Fecha]],"yyyy-mm"),tbl_PrecioLeche[Tipo_Leche],Tabla_master_rend[[#This Row],[Tipo_Leche]]),"") -> 0 | BW4: =+(Tabla_master_rend[[#This Row],[Coste_Leche_€]]-Tabla_master_rend[[#This Row],[Kg_MG_Nata]]*$CO$3)/Tabla_master_rend[[#This Row],[Kg_Queso_Blan]] -> -0.42503101 | BX4: =SUM(Tabla_master_rend[[#This Row],[Kg_Finos]:[Kg_Desmoldeo]])+Tabla_master_rend[[#This Row],[L_Agua]]+SUM(Tabla_master_rend[[#This Row],[B_altas]:[B_lab]]) -> 965.78841 | BY4: =+BX4-Tabla_master_rend[[#This Row],[Merma_TOT]] -> 115.16 | BZ4: =+BY4/BX4 -> 0.11923937 | CA4: =+Tabla_master_rend[[#This Row],[Kg_Queso_Blan]]*$CA$1 -> 173.95942 | CB4: =+Tabla_master_rend[[#This Row],[Kg_Queso_Blan]]*($CB$1-$CA$1) -> 93.670459 | CC4: =+(Tabla_master_rend[[#This Row],[Kg_Queso_Blan]]-CA4-CB4)*$CC$1 -> 278.20126 | CD4: =+CA4+CB4+CC4 -> 545.83115 | CE4: =+CD4/Tabla_master_rend[[#This Row],[Kg_Queso_Blan]] -> 0.020395 | CF4: =+Tabla_master_rend[[#This Row],[Merma_TOT]]/Tabla_master_rend[[#This Row],[Kg_Queso_Blan]] -> 0.03178376 | CG4: =CD4-Tabla_master_rend[[#This Row],[Merma_TOT]] -> -304.79726 | CH4: {=-BR4 * IFERROR(INDEX('Precio Leche_EBITDA_Ventas'!$BD$87:$BD$110,MATCH(1,('Precio Leche_EBITDA_Ventas'!$AZ$87:$AZ$110=YEAR(A4))*('Precio Leche_EBITDA_Ventas'!$BB$87:$BB$110=C4),0)),1.3)} -> -2977.1994 | CI4: =+CG4*$CM$2 -> -396.23643 | CK4: Venta kg Merma | CM4: 3.475
A5: 45664 | B5: 1 | C5: =+UPPER(TEXT(Tabla_master_rend[[#This Row],[Fecha]],"MMM")) -> ENE | D5: =+UPPER(TEXT(Tabla_master_rend[[#This Row],[Fecha]],"ddd")) -> MA | E5: 070125216 | F5: VACA | G5: EDAM | H5: 17 | I5: =+Tabla_master_rend[[#This Row],[L_Leche_ent]]+Tabla_master_rend[[#This Row],[L_desn_ext]]+Tabla_master_rend[[#This Row],[L_cabra]]+Tabla_master_rend[[#This Row],[L_oveja]] -> 254077 | J5: 254077 | K5: 0.0391 | L5: 0.0338 | M5: =0.93*K5+0.74*L5+0.048 -> 0.109375 | N5: NO | O5: 0 | P5: 0 | Q5: 0 | R5: 7660 | T5: 235530 | U5: =+Tabla_master_rend[[#This Row],[L_suero Total]]/Tabla_master_rend[[#This Row],[Litros_Leche_Total]] -> 0.92700244 | V5: 0.0017 | W5: 0.01 | X5: 152821 | Y5: 49494 | Z5: =IF(Tabla_master_rend[[#This Row],[L_suero para con]]=0,0,+Tabla_master_rend[[#This Row],[L_suero para con]]/Tabla_master_rend[[#This Row],[L_suero_con]]) -> 3.0876672 | AA5: =+Tabla_master_rend[[#This Row],[L_suero Total]]-Tabla_master_rend[[#This Row],[L_suero para con]] -> 82709 | AD5: 0 | AE5: 0 | AF5: 0 | AG5: 0 | AH5: 0 | AI5: =+Tabla_master_rend[[#This Row],[Kg_Finos]]+Tabla_master_rend[[#This Row],[Kg_Llenadora]]+Tabla_master_rend[[#This Row],[Kg_Desmoldeo]]+Tabla_master_rend[[#This Row],[L_Agua]]+Tabla_master_rend[[#This Row],[Kg_SalidaSecadero]] -> 29718.7 | AJ5: =+Tabla_master_rend[[#This Row],[Litros_Leche_Total]]/Tabla_master_rend[[#This Row],[Kg_Queso_Blan]] -> 8.5493982 | AK5: =+Tabla_master_rend[[#This Row],[Litros_Leche_Total]]/(Tabla_master_rend[[#This Row],[Kg_Queso_Blan]]-Tabla_master_rend[[#This Row],[Merma_TOT]]) -> 9.0595862 | AL5: =VLOOKUP(G5,REND_TARGET[#All],8,FALSE) -> 9.195758 | AM5: =(I5*1.03*Tabla_master_rend[[#This Row],[%MG_Leche]])+(I5*1.03*Tabla_master_rend[[#This Row],[%MP_Leche]]) -> 19077.88 | AN5: 0.2329 | AO5: 0.2339 | AP5: 0.5199 | AQ5: =+Tabla_master_rend[[#This Row],[Kg_Queso_Blan]]*Tabla_master_rend[[#This Row],[ES_QUESO]]/(Tabla_master_rend[[#This Row],[Kg_Solidos_leche]]) -> 0.80987785 | AR5: =R5*0.4 -> 3064 | AS5: =+(Tabla_master_rend[[#This Row],[Kg_Queso_Blan]]*Tabla_master_rend[[#This Row],[%MG_QUESO]]+(Tabla_master_rend[[#This Row],[Kg_MG_Nata]]))/(Tabla_master_rend[[#This Row],[Litros_Leche_Total]]*1.03*Tabla_master_rend[[#This Row],[%MG_Leche]]) -> 0.97586522 | AT5: =+Tabla_master_rend[[#This Row],[Kg_Queso_Blan]]*Tabla_master_rend[[#This Row],[%PT_QUESO]]/(Tabla_master_rend[[#This Row],[Litros_Leche_Total]]*1.03*Tabla_master_rend[[#This Row],[%MP_Leche]]) -> 0.78585198 | AU5: =AR5*$CO$3 -> 22980 | AV5: 76.7 | AW5: 218 | AX5: 52 | AY5: =SUM(Tabla_master_rend[[#This Row],[Kg_Finos]:[Kg_Desmoldeo]]) -> 346.7 | AZ5: =+(Tabla_master_rend[[#This Row],[Kg_Finos]]+Tabla_master_rend[[#This Row],[Kg_Llenadora]]+Tabla_master_rend[[#This Row],[Kg_Desmoldeo]])/(Tabla_master_rend[[#This Row],[Kg_Queso_Blan]]) -> 0.011666055 | BA5: 570 | BB5: =+Tabla_master_rend[[#This Row],[L_Agua]]/(Tabla_master_rend[[#This Row],[L_Agua]]+Tabla_master_rend[[#This Row],[Kg_SalidaSecadero]]) -> 0.019406237 | BC5: 3994 | BD5: 3806 | BE5: 28079 | BF5: 0 | BG5: 0 | BH5: =6*6.9 -> 41.4 | BI5: =165*6.9 -> 1138.5 | BJ5: 111 | BK5: 28802 | BL5: 1.36 | BM5: 725.88 | BN5: 29.66 | BO5: =+SUM(Tabla_master_rend[[#This Row],[B_altas]:[B_lab]])/Tabla_master_rend[[#This Row],[Kg_SalidaSecadero]] -> 0.044819804 | BP5: =+(Tabla_master_rend[[#This Row],[Kg_mer_env_real]]+Tabla_master_rend[[#This Row],[kg_mer_lab_real]])/Tabla_master_rend[[#This Row],[Kg_SalidaSecadero]] -> 0.026232206 | BQ5: =+Tabla_master_rend[[#This Row],[Merma_TOT]]/Tabla_master_rend[[#This Row],[Kg_Queso_Blan]] -> 0.056314711 | BR5: =+Tabla_master_rend[[#This Row],[kg_mer_lab_real]]+Tabla_master_rend[[#This Row],[Kg_mer_env_real]]+Tabla_master_rend[[#This Row],[Kg_rebaba]]+Tabla_master_rend[[#This Row],[L_Agua]]+Tabla_master_rend[[#This Row],[Kg_Desmoldeo]]+Tabla_master_rend[[#This Row],[Kg_Llenadora]]+Tabla_master_rend[[#This Row],[Kg_Finos]] -> 1673.6 | BT5: =IF(+Tabla_master_rend[[#This Row],[Kg_Env_Total]]=0,0,Tabla_master_rend[[#This Row],[Kg_Env_Total]]-Tabla_master_rend[[#This Row],[Kg_SalidaSecadero]]) -> 0 | BU5: =+Tabla_master_rend[[#This Row],[Diferencia_Env_vs_Sec_kg]]/Tabla_master_rend[[#This Row],[Kg_SalidaSecadero]] -> 0 | BV5: =IFERROR(Tabla_master_rend[[#This Row],[Litros_Leche_Total]]*SUMIFS(tbl_PrecioLeche[PMV_eur_L],tbl_PrecioLeche[AñoMes],TEXT(Tabla_master_rend[[#This Row],[Fecha]],"yyyy-mm"),tbl_PrecioLeche[Tipo_Leche],Tabla_master_rend[[#This Row],[Tipo_Leche]]),"") -> 0 | BW5: =+(Tabla_master_rend[[#This Row],[Coste_Leche_€]]-Tabla_master_rend[[#This Row],[Kg_MG_Nata]]*$CO$3)/Tabla_master_rend[[#This Row],[Kg_Queso_Blan]] -> -0.77325051 | BX5: =SUM(Tabla_master_rend[[#This Row],[Kg_Finos]:[Kg_Desmoldeo]])+Tabla_master_rend[[#This Row],[L_Agua]]+SUM(Tabla_master_rend[[#This Row],[B_altas]:[B_lab]]) -> 2207.6 | BY5: =+BX5-Tabla_master_rend[[#This Row],[Merma_TOT]] -> 534 | BZ5: =+BY5/BX5 -> 0.24189165 | CA5: =+Tabla_master_rend[[#This Row],[Kg_Queso_Blan]]*$CA$1 -> 193.17155 | CB5: =+Tabla_master_rend[[#This Row],[Kg_Queso_Blan]]*($CB$1-$CA$1) -> 104.01545 | CC5: =+(Tabla_master_rend[[#This Row],[Kg_Queso_Blan]]-CA5-CB5)*$CC$1 -> 308.92589 | CD5: =+CA5+CB5+CC5 -> 606.11289 | CE5: =+CD5/Tabla_master_rend[[#This Row],[Kg_Queso_Blan]] -> 0.020395 | CF5: =+Tabla_master_rend[[#This Row],[Merma_TOT]]/Tabla_master_rend[[#This Row],[Kg_Queso_Blan]] -> 0.056314711 | CG5: =CD5-Tabla_master_rend[[#This Row],[Merma_TOT]] -> -1067.4871 | CH5: {=-BR5 * IFERROR(INDEX('Precio Leche_EBITDA_Ventas'!$BD$87:$BD$110,MATCH(1,('Precio Leche_EBITDA_Ventas'!$AZ$87:$AZ$110=YEAR(A5))*('Precio Leche_EBITDA_Ventas'!$BB$87:$BB$110=C5),0)),1.3)} -> -5857.6 | CI5: =+CG5*$CM$2 -> -1387.7332
A6: 45665 | B6: 1 | C6: =+UPPER(TEXT(Tabla_master_rend[[#This Row],[Fecha]],"MMM")) -> ENE | D6: =+UPPER(TEXT(Tabla_master_rend[[#This Row],[Fecha]],"ddd")) -> MI | E6: 080125216 | F6: VACA | G6: EDAM | H6: 15 | I6: =+Tabla_master_rend[[#This Row],[L_Leche_ent]]+Tabla_master_rend[[#This Row],[L_desn_ext]]+Tabla_master_rend[[#This Row],[L_cabra]]+Tabla_master_rend[[#This Row],[L_oveja]] -> 224034 | J6: 224034 | K6: 0.0386 | L6: 0.0338 | M6: =0.93*K6+0.74*L6+0.048 -> 0.10891 | N6: NO | O6: 0 | P6: 0 | Q6: 0 | R6: 6660 | T6: 208090 | U6: =+Tabla_master_rend[[#This Row],[L_suero Total]]/Tabla_master_rend[[#This Row],[Litros_Leche_Total]] -> 0.92883223 | V6: 0.0017 | W6: 0.0101 | X6: 160816 | Y6: 49678 | Z6: =IF(Tabla_master_rend[[#This Row],[L_suero para con]]=0,0,+Tabla_master_rend[[#This Row],[L_suero para con]]/Tabla_master_rend[[#This Row],[L_suero_con]]) -> 3.2371674 | AA6: =+Tabla_master_rend[[#This Row],[L_suero Total]]-Tabla_master_rend[[#This Row],[L_suero para con]] -> 47274 | AD6: 8862 | AE6: 0 | AF6: 0 | AI6: =+Tabla_master_rend[[#This Row],[Kg_Finos]]+Tabla_master_rend[[#This Row],[Kg_Llenadora]]+Tabla_master_rend[[#This Row],[Kg_Desmoldeo]]+Tabla_master_rend[[#This Row],[L_Agua]]+Tabla_master_rend[[#This Row],[Kg_SalidaSecadero]] -> 25124.08 | AJ6: =+Tabla_master_rend[[#This Row],[Litros_Leche_Total]]/Tabla_master_rend[[#This Row],[Kg_Queso_Blan]] -> 8.9171026 | AK6: =+Tabla_master_rend[[#This Row],[Litros_Leche_Total]]/(Tabla_master_rend[[#This Row],[Kg_Queso_Blan]]-Tabla_master_rend[[#This Row],[Merma_TOT]]) -> 9.5233844 | AL6: =VLOOKUP(G6,REND_TARGET[#All],8,FALSE) -> 9.195758 | AM6: =(I6*1.03*Tabla_master_rend[[#This Row],[%MG_Leche]])+(I6*1.03*Tabla_master_rend[[#This Row],[%MP_Leche]]) -> 16706.663 | AN6: 0.2404 | AO6: 0.2387 | AP6: 0.5299 | AQ6: =+Tabla_master_rend[[#This Row],[Kg_Queso_Blan]]*Tabla_master_rend[[#This Row],[ES_QUESO]]/(Tabla_master_rend[[#This Row],[Kg_Solidos_leche]]) -> 0.79688264 | AR6: =R6*0.4 -> 2664 | AS6: =+(Tabla_master_rend[[#This Row],[Kg_Queso_Blan]]*Tabla_master_rend[[#This Row],[%MG_QUESO]]+(Tabla_master_rend[[#This Row],[Kg_MG_Nata]]))/(Tabla_master_rend[[#This Row],[Litros_Leche_Total]]*1.03*Tabla_master_rend[[#This Row],[%MG_Leche]]) -> 0.97717395 | AT6: =+Tabla_master_rend[[#This Row],[Kg_Queso_Blan]]*Tabla_master_rend[[#This Row],[%PT_QUESO]]/(Tabla_master_rend[[#This Row],[Litros_Leche_Total]]*1.03*Tabla_master_rend[[#This Row],[%MP_Leche]]) -> 0.76890862 | AU6: =AR6*$CO$3 -> 19980 | AV6: 46.58 | AW6: 155 | AX6: 102.5 | AY6: =SUM(Tabla_master_rend[[#This Row],[Kg_Finos]:[Kg_Desmoldeo]]) -> 304.08 | AZ6: =+(Tabla_master_rend[[#This Row],[Kg_Finos]]+Tabla_master_rend[[#This Row],[Kg_Llenadora]]+Tabla_master_rend[[#This Row],[Kg_Desmoldeo]])/(Tabla_master_rend[[#This Row],[Kg_Queso_Blan]]) -> 0.01210313 | BA6: 520 | BB6: =+Tabla_master_rend[[#This Row],[L_Agua]]/(Tabla_master_rend[[#This Row],[L_Agua]]+Tabla_master_rend[[#This Row],[Kg_SalidaSecadero]]) -> 0.020950846 | BC6: 3417 | BD6: 3203 | BE6: 23386 | BF6: 0 | BG6: 0 | BH6: =16*6.7 -> 107.2 | BI6: =177*6.7 -> 1185.9 | BJ6: 96 | BK6: 24300 | BL6: 1.26 | BM6: 753.62 | BN6: 20.5 | BO6: =+SUM(Tabla_master_rend[[#This Row],[B_altas]:[B_lab]])/Tabla_master_rend[[#This Row],[Kg_SalidaSecadero]] -> 0.057164609 | BP6: =+(Tabla_master_rend[[#This Row],[Kg_mer_env_real]]+Tabla_master_rend[[#This Row],[kg_mer_lab_real]])/Tabla_master_rend[[#This Row],[Kg_SalidaSecadero]] -> 0.03185679 | BQ6: =+Tabla_master_rend[[#This Row],[Merma_TOT]]/Tabla_master_rend[[#This Row],[Kg_Queso_Blan]] -> 0.063662431 | BR6: =+Tabla_master_rend[[#This Row],[kg_mer_lab_real]]+Tabla_master_rend[[#This Row],[Kg_mer_env_real]]+Tabla_master_rend[[#This Row],[Kg_rebaba]]+Tabla_master_rend[[#This Row],[L_Agua]]+Tabla_master_rend[[#This Row],[Kg_Desmoldeo]]+Tabla_master_rend[[#This Row],[Kg_Llenadora]]+Tabla_master_rend[[#This Row],[Kg_Finos]] -> 1599.46 | BT6: =IF(+Tabla_master_rend[[#This Row],[Kg_Env_Total]]=0,0,Tabla_master_rend[[#This Row],[Kg_Env_Total]]-Tabla_master_rend[[#This Row],[Kg_SalidaSecadero]]) -> 0 | BU6: =+Tabla_master_rend[[#This Row],[Diferencia_Env_vs_Sec_kg]]/Tabla_master_rend[[#This Row],[Kg_SalidaSecadero]] -> 0 | BV6: =IFERROR(Tabla_master_rend[[#This Row],[Litros_Leche_Total]]*SUMIFS(tbl_PrecioLeche[PMV_eur_L],tbl_PrecioLeche[AñoMes],TEXT(Tabla_master_rend[[#This Row],[Fecha]],"yyyy-mm"),tbl_PrecioLeche[Tipo_Leche],Tabla_master_rend[[#This Row],[Tipo_Leche]]),"") -> 0 | BW6: =+(Tabla_master_rend[[#This Row],[Coste_Leche_€]]-Tabla_master_rend[[#This Row],[Kg_MG_Nata]]*$CO$3)/Tabla_master_rend[[#This Row],[Kg_Queso_Blan]] -> -0.795253 | BX6: =SUM(Tabla_master_rend[[#This Row],[Kg_Finos]:[Kg_Desmoldeo]])+Tabla_master_rend[[#This Row],[L_Agua]]+SUM(Tabla_master_rend[[#This Row],[B_altas]:[B_lab]]) -> 2213.18 | BY6: =+BX6-Tabla_master_rend[[#This Row],[Merma_TOT]] -> 613.72 | BZ6: =+BY6/BX6 -> 0.27730234 | CA6: =+Tabla_master_rend[[#This Row],[Kg_Queso_Blan]]*$CA$1 -> 163.30652 | CB6: =+Tabla_master_rend[[#This Row],[Kg_Queso_Blan]]*($CB$1-$CA$1) -> 87.93428 | CC6: =+(Tabla_master_rend[[#This Row],[Kg_Queso_Blan]]-CA6-CB6)*$CC$1 -> 261.16481 | CD6: =+CA6+CB6+CC6 -> 512.40561 | CE6: =+CD6/Tabla_master_rend[[#This Row],[Kg_Queso_Blan]] -> 0.020395 | CF6: =+Tabla_master_rend[[#This Row],[Merma_TOT]]/Tabla_master_rend[[#This Row],[Kg_Queso_Blan]] -> 0.063662431 | CG6: =CD6-Tabla_master_rend[[#This Row],[Merma_TOT]] -> -1087.0544 | CH6: {=-BR6 * IFERROR(INDEX('Precio Leche_EBITDA_Ventas'!$BD$87:$BD$110,MATCH(1,('Precio Leche_EBITDA_Ventas'!$AZ$87:$AZ$110=YEAR(A6))*('Precio Leche_EBITDA_Ventas'!$BB$87:$BB$110=C6),0)),1.3)} -> -5598.11 | CI6: =+CG6*$CM$2 -> -1413.1707
A7: 45667 | B7: 1 | C7: =+UPPER(TEXT(Tabla_master_rend[[#This Row],[Fecha]],"MMM")) -> ENE | D7: =+UPPER(TEXT(Tabla_master_rend[[#This Row],[Fecha]],"ddd")) -> VI | E7: 100125326 | F7: VACA | G7: GOUDA_F | H7: 13 | I7: =+Tabla_master_rend[[#This Row],[L_Leche_ent]]+Tabla_master_rend[[#This Row],[L_desn_ext]]+Tabla_master_rend[[#This Row],[L_cabra]]+Tabla_master_rend[[#This Row],[L_oveja]] -> 204429 | J7: 204429 | K7: 0.0388 | L7: 0.0335 | M7: =0.93*K7+0.74*L7+0.048 -> 0.108874 | N7: SI | O7: 0 | P7: 0 | Q7: 0 | R7: 3045 | T7: 182000 | U7: =+Tabla_master_rend[[#This Row],[L_suero Total]]/Tabla_master_rend[[#This Row],[Litros_Leche_Total]] -> 0.89028465 | V7: 0.0018 | W7: 0.009 | X7: 149545 | Y7: 49146 | Z7: =IF(Tabla_master_rend[[#This Row],[L_suero para con]]=0,0,+Tabla_master_rend[[#This Row],[L_suero para con]]/Tabla_master_rend[[#This Row],[L_suero_con]]) -> 3.0428723 | AA7: =+Tabla_master_rend[[#This Row],[L_suero Total]]-Tabla_master_rend[[#This Row],[L_suero para con]] -> 32455 | AD7: 0 | AE7: 0 | AF7: 0 | AG7: 0 | AH7: 0 | AI7: =+Tabla_master_rend[[#This Row],[Kg_Finos]]+Tabla_master_rend[[#This Row],[Kg_Llenadora]]+Tabla_master_rend[[#This Row],[Kg_Desmoldeo]]+Tabla_master_rend[[#This Row],[L_Agua]]+Tabla_master_rend[[#This Row],[Kg_SalidaSecadero]] -> 22880.11 | AJ7: =+Tabla_master_rend[[#This Row],[Litros_Leche_Total]]/Tabla_master_rend[[#This Row],[Kg_Queso_Blan]] -> 8.934791 | AK7: =+Tabla_master_rend[[#This Row],[Litros_Leche_Total]]/(Tabla_master_rend[[#This Row],[Kg_Queso_Blan]]-Tabla_master_rend[[#This Row],[Merma_TOT]]) -> 9.3994061 | AL7: =VLOOKUP(G7,REND_TARGET[#All],8,FALSE) -> 9.354943 | AM7: =(I7*1.03*Tabla_master_rend[[#This Row],[%MG_Leche]])+(I7*1.03*Tabla_master_rend[[#This Row],[%MP_Leche]]) -> 15223.623 | AN7: 0.2915 | AO7: 0.2383 | AP7: 0.5782 | AQ7: =+Tabla_master_rend[[#This Row],[Kg_Queso_Blan]]*Tabla_master_rend[[#This Row],[ES_QUESO]]/(Tabla_master_rend[[#This Row],[Kg_Solidos_leche]]) -> 0.86899678 | AR7: =R7*0.4 -> 1218 | AS7: =+(Tabla_master_rend[[#This Row],[Kg_Queso_Blan]]*Tabla_master_rend[[#This Row],[%MG_QUESO]]+(Tabla_master_rend[[#This Row],[Kg_MG_Nata]]))/(Tabla_master_rend[[#This Row],[Litros_Leche_Total]]*1.03*Tabla_master_rend[[#This Row],[%MG_Leche]]) -> 0.96545222 | AT7: =+Tabla_master_rend[[#This Row],[Kg_Queso_Blan]]*Tabla_master_rend[[#This Row],[%PT_QUESO]]/(Tabla_master_rend[[#This Row],[Litros_Leche_Total]]*1.03*Tabla_master_rend[[#This Row],[%MP_Leche]]) -> 0.77296106 | AU7: =AR7*$CO$3 -> 9135 | AV7: 44.11 | AW7: 85 | AX7: 44 | AY7: =SUM(Tabla_master_rend[[#This Row],[Kg_Finos]:[Kg_Desmoldeo]]) -> 173.11 | AZ7: =+(Tabla_master_rend[[#This Row],[Kg_Finos]]+Tabla_master_rend[[#This Row],[Kg_Llenadora]]+Tabla_master_rend[[#This Row],[Kg_Desmoldeo]])/(Tabla_master_rend[[#This Row],[Kg_Queso_Blan]]) -> 0.0075659601 | BA7: 450 | BB7: =+Tabla_master_rend[[#This Row],[L_Agua]]/(Tabla_master_rend[[#This Row],[L_Agua]]+Tabla_master_rend[[#This Row],[Kg_SalidaSecadero]]) -> 0.019817677 | BC7: 3084 | BD7: 2957 | BE7: 21824 | BF7: 0 | BG7: 0 | BH7: =4*6.9 -> 27.6 | BI7: =112*6.9 -> 772.8 | BJ7: 83 | BK7: 22257 | BL7: 3.89 | BM7: 497.26 | BN7: 6.71 | BO7: =+SUM(Tabla_master_rend[[#This Row],[B_altas]:[B_lab]])/Tabla_master_rend[[#This Row],[Kg_SalidaSecadero]] -> 0.039690884 | BP7: =+(Tabla_master_rend[[#This Row],[Kg_mer_env_real]]+Tabla_master_rend[[#This Row],[kg_mer_lab_real]])/Tabla_master_rend[[#This Row],[Kg_SalidaSecadero]] -> 0.022643213 | BQ7: =+Tabla_master_rend[[#This Row],[Merma_TOT]]/Tabla_master_rend[[#This Row],[Kg_Queso_Blan]] -> 0.049430269 | BR7: =+Tabla_master_rend[[#This Row],[kg_mer_lab_real]]+Tabla_master_rend[[#This Row],[Kg_mer_env_real]]+Tabla_master_rend[[#This Row],[Kg_rebaba]]+Tabla_master_rend[[#This Row],[L_Agua]]+Tabla_master_rend[[#This Row],[Kg_Desmoldeo]]+Tabla_master_rend[[#This Row],[Kg_Llenadora]]+Tabla_master_rend[[#This Row],[Kg_Finos]] -> 1130.97 | BT7: =IF(+Tabla_master_rend[[#This Row],[Kg_Env_Total]]=0,0,Tabla_master_rend[[#This Row],[Kg_Env_Total]]-Tabla_master_rend[[#This Row],[Kg_SalidaSecadero]]) -> 0 | BU7: =+Tabla_master_rend[[#This Row],[Diferencia_Env_vs_Sec_kg]]/Tabla_master_rend[[#This Row],[Kg_SalidaSecadero]] -> 0 | BV7: =IFERROR(Tabla_master_rend[[#This Row],[Litros_Leche_Total]]*SUMIFS(tbl_PrecioLeche[PMV_eur_L],tbl_PrecioLeche[AñoMes],TEXT(Tabla_master_rend[[#This Row],[Fecha]],"yyyy-mm"),tbl_PrecioLeche[Tipo_Leche],Tabla_master_rend[[#This Row],[Tipo_Leche]]),"") -> 0 | BW7: =+(Tabla_master_rend[[#This Row],[Coste_Leche_€]]-Tabla_master_rend[[#This Row],[Kg_MG_Nata]]*$CO$3)/Tabla_master_rend[[#This Row],[Kg_Queso_Blan]] -> -0.39925507 | BX7: =SUM(Tabla_master_rend[[#This Row],[Kg_Finos]:[Kg_Desmoldeo]])+Tabla_master_rend[[#This Row],[L_Agua]]+SUM(Tabla_master_rend[[#This Row],[B_altas]:[B_lab]]) -> 1506.51 | BY7: =+BX7-Tabla_master_rend[[#This Row],[Merma_TOT]] -> 375.54 | BZ7: =+BY7/BX7 -> 0.24927813 | CA7: =+Tabla_master_rend[[#This Row],[Kg_Queso_Blan]]*$CA$1 -> 148.72071 | CB7: =+Tabla_master_rend[[#This Row],[Kg_Queso_Blan]]*($CB$1-$CA$1) -> 80.080385 | CC7: =+(Tabla_master_rend[[#This Row],[Kg_Queso_Blan]]-CA7-CB7)*$CC$1 -> 237.83874 | CD7: =+CA7+CB7+CC7 -> 466.63984 | CE7: =+CD7/Tabla_master_rend[[#This Row],[Kg_Queso_Blan]] -> 0.020395 | CF7: =+Tabla_master_rend[[#This Row],[Merma_TOT]]/Tabla_master_rend[[#This Row],[Kg_Queso_Blan]] -> 0.049430269 | CG7: =CD7-Tabla_master_rend[[#This Row],[Merma_TOT]] -> -664.33016 | CH7: {=-BR7 * IFERROR(INDEX('Precio Leche_EBITDA_Ventas'!$BD$87:$BD$110,MATCH(1,('Precio Leche_EBITDA_Ventas'!$AZ$87:$AZ$110=YEAR(A7))*('Precio Leche_EBITDA_Ventas'!$BB$87:$BB$110=C7),0)),1.3)} -> -3958.395 | CI7: =+CG7*$CM$2 -> -863.6292
A8: 45670 | B8: 1 | C8: =+UPPER(TEXT(Tabla_master_rend[[#This Row],[Fecha]],"MMM")) -> ENE | D8: =+UPPER(TEXT(Tabla_master_rend[[#This Row],[Fecha]],"ddd")) -> LU | E8: 130125316 | F8: VACA | G8: EDAM_F | H8: 16 | I8: =+Tabla_master_rend[[#This Row],[L_Leche_ent]]+Tabla_master_rend[[#This Row],[L_desn_ext]]+Tabla_master_rend[[#This Row],[L_cabra]]+Tabla_master_rend[[#This Row],[L_oveja]] -> 259322 | J8: 259322 | K8: 0.0372 | L8: 0.0334 | M8: =0.93*K8+0.74*L8+0.048 -> 0.107312 | N8: NO | O8: 0 | P8: 0 | Q8: 0 | R8: 7727 | T8: 223450 | U8: =+Tabla_master_rend[[#This Row],[L_suero Total]]/Tabla_master_rend[[#This Row],[Litros_Leche_Total]] -> 0.86167005 | V8: 0.0011 | W8: 0.0091 | X8: 134124 | Y8: 38013 | Z8: =IF(Tabla_master_rend[[#This Row],[L_suero para con]]=0,0,+Tabla_master_rend[[#This Row],[L_suero para con]]/Tabla_master_rend[[#This Row],[L_suero_con]]) -> 3.5283719 | AA8: =+Tabla_master_rend[[#This Row],[L_suero Total]]-Tabla_master_rend[[#This Row],[L_suero para con]] -> 89326 | AD8: 0 | AE8: 0 | AF8: 0 | AG8: 0 | AH8: 0 | AI8: =+Tabla_master_rend[[#This Row],[Kg_Finos]]+Tabla_master_rend[[#This Row],[Kg_Llenadora]]+Tabla_master_rend[[#This Row],[Kg_Desmoldeo]]+Tabla_master_rend[[#This Row],[L_Agua]]+Tabla_master_rend[[#This Row],[Kg_SalidaSecadero]] -> 28427.92 | AJ8: =+Tabla_master_rend[[#This Row],[Litros_Leche_Total]]/Tabla_master_rend[[#This Row],[Kg_Queso_Blan]] -> 9.1220884 | AK8: =+Tabla_master_rend[[#This Row],[Litros_Leche_Total]]/(Tabla_master_rend[[#This Row],[Kg_Queso_Blan]]-Tabla_master_rend[[#This Row],[Merma_TOT]]) -> 10.262488 | AL8: =VLOOKUP(G8,REND_TARGET[#All],8,FALSE) -> 9.80785 | AM8: =(I8*1.03*Tabla_master_rend[[#This Row],[%MG_Leche]])+(I8*1.03*Tabla_master_rend[[#This Row],[%MP_Leche]]) -> 18857.377 | AN8: 0.2365 | AO8: 0.254 | AP8: 0.5423 | AQ8: =+Tabla_master_rend[[#This Row],[Kg_Queso_Blan]]*Tabla_master_rend[[#This Row],[ES_QUESO]]/(Tabla_master_rend[[#This Row],[Kg_Solidos_leche]]) -> 0.81752944 | AR8: =R8*0.4 -> 3090.8 | AS8: =+(Tabla_master_rend[[#This Row],[Kg_Queso_Blan]]*Tabla_master_rend[[#This Row],[%MG_QUESO]]+(Tabla_master_rend[[#This Row],[Kg_MG_Nata]]))/(Tabla_master_rend[[#This Row],[Litros_Leche_Total]]*1.03*Tabla_master_rend[[#This Row],[%MG_Leche]]) -> 0.98770366 | AT8: =+Tabla_master_rend[[#This Row],[Kg_Queso_Blan]]*Tabla_master_rend[[#This Row],[%PT_QUESO]]/(Tabla_master_rend[[#This Row],[Litros_Leche_Total]]*1.03*Tabla_master_rend[[#This Row],[%MP_Leche]]) -> 0.80938611 | AU8: =AR8*$CO$3 -> 23181 | AV8: 52.92 | AW8: 88.4 | AX8: 282.6 | AY8: =SUM(Tabla_master_rend[[#This Row],[Kg_Finos]:[Kg_Desmoldeo]]) -> 423.92 | AZ8: =+(Tabla_master_rend[[#This Row],[Kg_Finos]]+Tabla_master_rend[[#This Row],[Kg_Llenadora]]+Tabla_master_rend[[#This Row],[Kg_Desmoldeo]])/(Tabla_master_rend[[#This Row],[Kg_Queso_Blan]]) -> 0.0149121 | BA8: 575 | BB8: =+Tabla_master_rend[[#This Row],[L_Agua]]/(Tabla_master_rend[[#This Row],[L_Agua]]+Tabla_master_rend[[#This Row],[Kg_SalidaSecadero]]) -> 0.020532781 | BC8: 3973 | BD8: 3367 | BE8: 23363 | BF8: 0 | BG8: 0 | BH8: =4*7.7 -> 30.8 | BI8: =588*7.7 -> 4527.6 | BJ8: 86 | BK8: 27429 | BL8: 4.23 | BM8: 2137.88 | BN8: 17.97 | BO8: =+SUM(Tabla_master_rend[[#This Row],[B_altas]:[B_lab]])/Tabla_master_rend[[#This Row],[Kg_SalidaSecadero]] -> 0.16932444 | BP8: =+(Tabla_master_rend[[#This Row],[Kg_mer_env_real]]+Tabla_master_rend[[#This Row],[kg_mer_lab_real]])/Tabla_master_rend[[#This Row],[Kg_SalidaSecadero]] -> 0.07859747 | BQ8: =+Tabla_master_rend[[#This Row],[Merma_TOT]]/Tabla_master_rend[[#This Row],[Kg_Queso_Blan]] -> 0.11112315 | BR8: =+Tabla_master_rend[[#This Row],[kg_mer_lab_real]]+Tabla_master_rend[[#This Row],[Kg_mer_env_real]]+Tabla_master_rend[[#This Row],[Kg_rebaba]]+Tabla_master_rend[[#This Row],[L_Agua]]+Tabla_master_rend[[#This Row],[Kg_Desmoldeo]]+Tabla_master_rend[[#This Row],[Kg_Llenadora]]+Tabla_master_rend[[#This Row],[Kg_Finos]] -> 3159 | BT8: =IF(+Tabla_master_rend[[#This Row],[Kg_Env_Total]]=0,0,Tabla_master_rend[[#This Row],[Kg_Env_Total]]-Tabla_master_rend[[#This Row],[Kg_SalidaSecadero]]) -> 0 | BU8: =+Tabla_master_rend[[#This Row],[Diferencia_Env_vs_Sec_kg]]/Tabla_master_rend[[#This Row],[Kg_SalidaSecadero]] -> 0 | BV8: =IFERROR(Tabla_master_rend[[#This Row],[Litros_Leche_Total]]*SUMIFS(tbl_PrecioLeche[PMV_eur_L],tbl_PrecioLeche[AñoMes],TEXT(Tabla_master_rend[[#This Row],[Fecha]],"yyyy-mm"),tbl_PrecioLeche[Tipo_Leche],Tabla_master_rend[[#This Row],[Tipo_Leche]]),"") -> 0 | BW8: =+(Tabla_master_rend[[#This Row],[Coste_Leche_€]]-Tabla_master_rend[[#This Row],[Kg_MG_Nata]]*$CO$3)/Tabla_master_rend[[#This Row],[Kg_Queso_Blan]] -> -0.81543075 | BX8: =SUM(Tabla_master_rend[[#This Row],[Kg_Finos]:[Kg_Desmoldeo]])+Tabla_master_rend[[#This Row],[L_Agua]]+SUM(Tabla_master_rend[[#This Row],[B_altas]:[B_lab]]) -> 5643.32 | BY8: =+BX8-Tabla_master_rend[[#This Row],[Merma_TOT]] -> 2484.32 | BZ8: =+BY8/BX8 -> 0.44022313 | CA8: =+Tabla_master_rend[[#This Row],[Kg_Queso_Blan]]*$CA$1 -> 184.78148 | CB8: =+Tabla_master_rend[[#This Row],[Kg_Queso_Blan]]*($CB$1-$CA$1) -> 99.49772 | CC8: =+(Tabla_master_rend[[#This Row],[Kg_Queso_Blan]]-CA8-CB8)*$CC$1 -> 295.50823 | CD8: =+CA8+CB8+CC8 -> 579.78743 | CE8: =+CD8/Tabla_master_rend[[#This Row],[Kg_Queso_Blan]] -> 0.020395 | CF8: =+Tabla_master_rend[[#This Row],[Merma_TOT]]/Tabla_master_rend[[#This Row],[Kg_Queso_Blan]] -> 0.11112315 | CG8: =CD8-Tabla_master_rend[[#This Row],[Merma_TOT]] -> -2579.2126 | CH8: {=-BR8 * IFERROR(INDEX('Precio Leche_EBITDA_Ventas'!$BD$87:$BD$110,MATCH(1,('Precio Leche_EBITDA_Ventas'!$AZ$87:$AZ$110=YEAR(A8))*('Precio Leche_EBITDA_Ventas'!$BB$87:$BB$110=C8),0)),1.3)} -> -11056.5 | CI8: =+CG8*$CM$2 -> -3352.9763
A9: 45673 | B9: 1 | C9: =+UPPER(TEXT(Tabla_master_rend[[#This Row],[Fecha]],"MMM")) -> ENE | D9: =+UPPER(TEXT(Tabla_master_rend[[#This Row],[Fecha]],"ddd")) -> JU | E9: 160125026 | F9: VACA | G9: GOUDA | H9: 17 | I9: =+Tabla_master_rend[[#This Row],[L_Leche_ent]]+Tabla_master_rend[[#This Row],[L_desn_ext]]+Tabla_master_rend[[#This Row],[L_cabra]]+Tabla_master_rend[[#This Row],[L_oveja]] -> 242694 | J9: 242694 | K9: 0.0393 | L9: 0.0345 | M9: =0.93*K9+0.74*L9+0.048 -> 0.110079 | N9: SI | O9: 0 | P9: 0 | Q9: 0 | R9: 2715 | T9: 223400 | U9: =+Tabla_master_rend[[#This Row],[L_suero Total]]/Tabla_master_rend[[#This Row],[Litros_Leche_Total]] -> 0.92050071 | V9: 0.0026 | W9: 0.0101 | X9: 142428 | Y9: 43435 | Z9: =IF(Tabla_master_rend[[#This Row],[L_suero para con]]=0,0,+Tabla_master_rend[[#This Row],[L_suero para con]]/Tabla_master_rend[[#This Row],[L_suero_con]]) -> 3.2791067 | AA9: =+Tabla_master_rend[[#This Row],[L_suero Total]]-Tabla_master_rend[[#This Row],[L_suero para con]] -> 80972 | AD9: 0 | AE9: 0 | AF9: 0 | AG9: 0 | AH9: 0 | AI9: =+Tabla_master_rend[[#This Row],[Kg_Finos]]+Tabla_master_rend[[#This Row],[Kg_Llenadora]]+Tabla_master_rend[[#This Row],[Kg_Desmoldeo]]+Tabla_master_rend[[#This Row],[L_Agua]]+Tabla_master_rend[[#This Row],[Kg_SalidaSecadero]] -> 30210.38 | AJ9: =+Tabla_master_rend[[#This Row],[Litros_Leche_Total]]/Tabla_master_rend[[#This Row],[Kg_Queso_Blan]] -> 8.033464 | AK9: =+Tabla_master_rend[[#This Row],[Litros_Leche_Total]]/(Tabla_master_rend[[#This Row],[Kg_Queso_Blan]]-Tabla_master_rend[[#This Row],[Merma_TOT]]) -> 8.2873143 | AL9: =VLOOKUP(G9,REND_TARGET[#All],8,FALSE) -> 8.494317 | AM9: =(I9*1.03*Tabla_master_rend[[#This Row],[%MG_Leche]])+(I9*1.03*Tabla_master_rend[[#This Row],[%MP_Leche]]) -> 18448.142 | AN9: 0.2854 | AO9: 0.2265 | AP9: 0.5624 | AQ9: =+Tabla_master_rend[[#This Row],[Kg_Queso_Blan]]*Tabla_master_rend[[#This Row],[ES_QUESO]]/(Tabla_master_rend[[#This Row],[Kg_Solidos_leche]]) -> 0.92097719 | AR9: =R9*0.4 -> 1086 | AS9: =+(Tabla_master_rend[[#This Row],[Kg_Queso_Blan]]*Tabla_master_rend[[#This Row],[%MG_QUESO]]+(Tabla_master_rend[[#This Row],[Kg_MG_Nata]]))/(Tabla_master_rend[[#This Row],[Litros_Leche_Total]]*1.03*Tabla_master_rend[[#This Row],[%MG_Leche]]) -> 0.98819545 | AT9: =+Tabla_master_rend[[#This Row],[Kg_Queso_Blan]]*Tabla_master_rend[[#This Row],[%PT_QUESO]]/(Tabla_master_rend[[#This Row],[Litros_Leche_Total]]*1.03*Tabla_master_rend[[#This Row],[%MP_Leche]]) -> 0.79343076 | AU9: =AR9*$CO$3 -> 8145 | AV9: 88.28 | AW9: 133.9 | AX9: 17.2 | AY9: =SUM(Tabla_master_rend[[#This Row],[Kg_Finos]:[Kg_Desmoldeo]]) -> 239.38 | AZ9: =+(Tabla_master_rend[[#This Row],[Kg_Finos]]+Tabla_master_rend[[#This Row],[Kg_Llenadora]]+Tabla_master_rend[[#This Row],[Kg_Desmoldeo]])/(Tabla_master_rend[[#This Row],[Kg_Queso_Blan]]) -> 0.0079237666 | BA9: 580 | BB9: =+Tabla_master_rend[[#This Row],[L_Agua]]/(Tabla_master_rend[[#This Row],[L_Agua]]+Tabla_master_rend[[#This Row],[Kg_SalidaSecadero]]) -> 0.01935204 | BC9: 4022 | BD9: 3996 | BE9: 29803 | BF9: 0 | BG9: 0 | BH9: =2*6.4 -> 12.8 | BI9: =11*6.4 -> 70.4 | BJ9: 85 | BK9: 29391 | BL9: 1.8 | BM9: 82.13 | BN9: 22.07 | BO9: =+SUM(Tabla_master_rend[[#This Row],[B_altas]:[B_lab]])/Tabla_master_rend[[#This Row],[Kg_SalidaSecadero]] -> 0.0057228403 | BP9: =+(Tabla_master_rend[[#This Row],[Kg_mer_env_real]]+Tabla_master_rend[[#This Row],[kg_mer_lab_real]])/Tabla_master_rend[[#This Row],[Kg_SalidaSecadero]] -> 0.003545303 | BQ9: =+Tabla_master_rend[[#This Row],[Merma_TOT]]/Tabla_master_rend[[#This Row],[Kg_Queso_Blan]] -> 0.030631194 | BR9: =+Tabla_master_rend[[#This Row],[kg_mer_lab_real]]+Tabla_master_rend[[#This Row],[Kg_mer_env_real]]+Tabla_master_rend[[#This Row],[Kg_rebaba]]+Tabla_master_rend[[#This Row],[L_Agua]]+Tabla_master_rend[[#This Row],[Kg_Desmoldeo]]+Tabla_master_rend[[#This Row],[Kg_Llenadora]]+Tabla_master_rend[[#This Row],[Kg_Finos]] -> 925.38 | BT9: =IF(+Tabla_master_rend[[#This Row],[Kg_Env_Total]]=0,0,Tabla_master_rend[[#This Row],[Kg_Env_Total]]-Tabla_master_rend[[#This Row],[Kg_SalidaSecadero]]) -> 0 | BU9: =+Tabla_master_rend[[#This Row],[Diferencia_Env_vs_Sec_kg]]/Tabla_master_rend[[#This Row],[Kg_SalidaSecadero]] -> 0 | BV9: =IFERROR(Tabla_master_rend[[#This Row],[Litros_Leche_Total]]*SUMIFS(tbl_PrecioLeche[PMV_eur_L],tbl_PrecioLeche[AñoMes],TEXT(Tabla_master_rend[[#This Row],[Fecha]],"yyyy-mm"),tbl_PrecioLeche[Tipo_Leche],Tabla_master_rend[[#This Row],[Tipo_Leche]]),"") -> 0 | BW9: =+(Tabla_master_rend[[#This Row],[Coste_Leche_€]]-Tabla_master_rend[[#This Row],[Kg_MG_Nata]]*$CO$3)/Tabla_master_rend[[#This Row],[Kg_Queso_Blan]] -> -0.26960932 | BX9: =SUM(Tabla_master_rend[[#This Row],[Kg_Finos]:[Kg_Desmoldeo]])+Tabla_master_rend[[#This Row],[L_Agua]]+SUM(Tabla_master_rend[[#This Row],[B_altas]:[B_lab]]) -> 987.58 | BY9: =+BX9-Tabla_master_rend[[#This Row],[Merma_TOT]] -> 62.2 | BZ9: =+BY9/BX9 -> 0.062982239 | CA9: =+Tabla_master_rend[[#This Row],[Kg_Queso_Blan]]*$CA$1 -> 196.36747 | CB9: =+Tabla_master_rend[[#This Row],[Kg_Queso_Blan]]*($CB$1-$CA$1) -> 105.73633 | CC9: =+(Tabla_master_rend[[#This Row],[Kg_Queso_Blan]]-CA9-CB9)*$CC$1 -> 314.0369 | CD9: =+CA9+CB9+CC9 -> 616.1407 | CE9: =+CD9/Tabla_master_rend[[#This Row],[Kg_Queso_Blan]] -> 0.020395 | CF9: =+Tabla_master_rend[[#This Row],[Merma_TOT]]/Tabla_master_rend[[#This Row],[Kg_Queso_Blan]] -> 0.030631194 | CG9: =CD9-Tabla_master_rend[[#This Row],[Merma_TOT]] -> -309.2393 | CH9: {=-BR9 * IFERROR(INDEX('Precio Leche_EBITDA_Ventas'!$BD$87:$BD$110,MATCH(1,('Precio Leche_EBITDA_Ventas'!$AZ$87:$AZ$110=YEAR(A9))*('Precio Leche_EBITDA_Ventas'!$BB$87:$BB$110=C9),0)),1.3)} -> -3238.83 | CI9: =+CG9*$CM$2 -> -402.01109
A10: 45677 | B10: 1 | C10: =+UPPER(TEXT(Tabla_master_rend[[#This Row],[Fecha]],"MMM")) -> ENE | D10: =+UPPER(TEXT(Tabla_master_rend[[#This Row],[Fecha]],"ddd")) -> LU | E10: 200125016 | F10: VACA | G10: EDAM | H10: 3 | I10: =+Tabla_master_rend[[#This Row],[L_Leche_ent]]+Tabla_master_rend[[#This Row],[L_desn_ext]]+Tabla_master_rend[[#This Row],[L_cabra]]+Tabla_master_rend[[#This Row],[L_oveja]] -> 43234 | J10: 43234 | K10: 0.0383 | L10: 0.0343 | M10: =0.93*K10+0.74*L10+0.048 -> 0.109001 | N10: NO | O10: 0 | P10: 0 | Q10: 0 | R10: 1103 | T10: 43300 | U10: =+Tabla_master_rend[[#This Row],[L_suero Total]]/Tabla_master_rend[[#This Row],[Litros_Leche_Total]] -> 1.0015266 | V10: 0.002 | W10: 0.0107 | X10: 40841 | Y10: 11435 | Z10: =IF(Tabla_master_rend[[#This Row],[L_suero para con]]=0,0,+Tabla_master_rend[[#This Row],[L_suero para con]]/Tabla_master_rend[[#This Row],[L_suero_con]]) -> 3.5715785 | AA10: =+Tabla_master_rend[[#This Row],[L_suero Total]]-Tabla_master_rend[[#This Row],[L_suero para con]] -> 2459 | AD10: 8210 | AE10: 0 | AF10: 0 | AI10: =+Tabla_master_rend[[#This Row],[Kg_Finos]]+Tabla_master_rend[[#This Row],[Kg_Llenadora]]+Tabla_master_rend[[#This Row],[Kg_Desmoldeo]]+Tabla_master_rend[[#This Row],[L_Agua]]+Tabla_master_rend[[#This Row],[Kg_SalidaSecadero]] -> 4858.46 | AJ10: =+Tabla_master_rend[[#This Row],[Litros_Leche_Total]]/Tabla_master_rend[[#This Row],[Kg_Queso_Blan]] -> 8.8987045 | AK10: =+Tabla_master_rend[[#This Row],[Litros_Leche_Total]]/(Tabla_master_rend[[#This Row],[Kg_Queso_Blan]]-Tabla_master_rend[[#This Row],[Merma_TOT]]) -> 9.4562968 | AL10: =VLOOKUP(G10,REND_TARGET[#All],8,FALSE) -> 9.195758 | AM10: =(I10*1.03*Tabla_master_rend[[#This Row],[%MG_Leche]])+(I10*1.03*Tabla_master_rend[[#This Row],[%MP_Leche]]) -> 3232.9521 | AN10: 0.2356 | AO10: 0.2388 | AP10: 0.528 | AQ10: =+Tabla_master_rend[[#This Row],[Kg_Queso_Blan]]*Tabla_master_rend[[#This Row],[ES_QUESO]]/(Tabla_master_rend[[#This Row],[Kg_Solidos_leche]]) -> 0.79347508 | AR10: =R10*0.4 -> 441.2 | AS10: =+(Tabla_master_rend[[#This Row],[Kg_Queso_Blan]]*Tabla_master_rend[[#This Row],[%MG_QUESO]]+(Tabla_master_rend[[#This Row],[Kg_MG_Nata]]))/(Tabla_master_rend[[#This Row],[Litros_Leche_Total]]*1.03*Tabla_master_rend[[#This Row],[%MG_Leche]]) -> 0.92982573 | AT10: =+Tabla_master_rend[[#This Row],[Kg_Queso_Blan]]*Tabla_master_rend[[#This Row],[%PT_QUESO]]/(Tabla_master_rend[[#This Row],[Litros_Leche_Total]]*1.03*Tabla_master_rend[[#This Row],[%MP_Leche]]) -> 0.75958467 | AU10: =AR10*$CO$3 -> 3309 | AV10: 10.46 | AW10: 55 | AX10: 27 | AY10: =SUM(Tabla_master_rend[[#This Row],[Kg_Finos]:[Kg_Desmoldeo]]) -> 92.46 | AZ10: =+(Tabla_master_rend[[#This Row],[Kg_Finos]]+Tabla_master_rend[[#This Row],[Kg_Llenadora]]+Tabla_master_rend[[#This Row],[Kg_Desmoldeo]])/(Tabla_master_rend[[#This Row],[Kg_Queso_Blan]]) -> 0.019030722 | BA10: 100 | BB10: =+Tabla_master_rend[[#This Row],[L_Agua]]/(Tabla_master_rend[[#This Row],[L_Agua]]+Tabla_master_rend[[#This Row],[Kg_SalidaSecadero]]) -> 0.020981956 | BC10: 644 | BD10: 610 | BE10: 4548 | BF10: 0 | BG10: =13*6.5 -> 84.5 | BH10: =15*6.5 -> 97.5 | BI10: 0 | BJ10: 37 | BK10: 4666 | BL10: 0 | BM10: 87.71 | BN10: 6.31 | BO10: =+SUM(Tabla_master_rend[[#This Row],[B_altas]:[B_lab]])/Tabla_master_rend[[#This Row],[Kg_SalidaSecadero]] -> 0.046935276 | BP10: =+(Tabla_master_rend[[#This Row],[Kg_mer_env_real]]+Tabla_master_rend[[#This Row],[kg_mer_lab_real]])/Tabla_master_rend[[#This Row],[Kg_SalidaSecadero]] -> 0.020150021 | BQ10: =+Tabla_master_rend[[#This Row],[Merma_TOT]]/Tabla_master_rend[[#This Row],[Kg_Queso_Blan]] -> 0.058965186 | BR10: =+Tabla_master_rend[[#This Row],[kg_mer_lab_real]]+Tabla_master_rend[[#This Row],[Kg_mer_env_real]]+Tabla_master_rend[[#This Row],[Kg_rebaba]]+Tabla_master_rend[[#This Row],[L_Agua]]+Tabla_master_rend[[#This Row],[Kg_Desmoldeo]]+Tabla_master_rend[[#This Row],[Kg_Llenadora]]+Tabla_master_rend[[#This Row],[Kg_Finos]] -> 286.48 | BT10: =IF(+Tabla_master_rend[[#This Row],[Kg_Env_Total]]=0,0,Tabla_master_rend[[#This Row],[Kg_Env_Total]]-Tabla_master_rend[[#This Row],[Kg_SalidaSecadero]]) -> 0 | BU10: =+Tabla_master_rend[[#This Row],[Diferencia_Env_vs_Sec_kg]]/Tabla_master_rend[[#This Row],[Kg_SalidaSecadero]] -> 0 | BV10: =IFERROR(Tabla_master_rend[[#This Row],[Litros_Leche_Total]]*SUMIFS(tbl_PrecioLeche[PMV_eur_L],tbl_PrecioLeche[AñoMes],TEXT(Tabla_master_rend[[#This Row],[Fecha]],"yyyy-mm"),tbl_PrecioLeche[Tipo_Leche],Tabla_master_rend[[#This Row],[Tipo_Leche]]),"") -> 0 | BW10: =+(Tabla_master_rend[[#This Row],[Coste_Leche_€]]-Tabla_master_rend[[#This Row],[Kg_MG_Nata]]*$CO$3)/Tabla_master_rend[[#This Row],[Kg_Queso_Blan]] -> -0.68108001 | BX10: =SUM(Tabla_master_rend[[#This Row],[Kg_Finos]:[Kg_Desmoldeo]])+Tabla_master_rend[[#This Row],[L_Agua]]+SUM(Tabla_master_rend[[#This Row],[B_altas]:[B_lab]]) -> 411.46 | BY10: =+BX10-Tabla_master_rend[[#This Row],[Merma_TOT]] -> 124.98 | BZ10: =+BY10/BX10 -> 0.30374763 | CA10: =+Tabla_master_rend[[#This Row],[Kg_Queso_Blan]]*$CA$1 -> 31.57999 | CB10: =+Tabla_master_rend[[#This Row],[Kg_Queso_Blan]]*($CB$1-$CA$1) -> 17.00461 | CC10: =+(Tabla_master_rend[[#This Row],[Kg_Queso_Blan]]-CA10-CB10)*$CC$1 -> 50.503692 | CD10: =+CA10+CB10+CC10 -> 99.088292 | CE10: =+CD10/Tabla_master_rend[[#This Row],[Kg_Queso_Blan]] -> 0.020395 | CF10: =+Tabla_master_rend[[#This Row],[Merma_TOT]]/Tabla_master_rend[[#This Row],[Kg_Queso_Blan]] -> 0.058965186 | CG10: =CD10-Tabla_master_rend[[#This Row],[Merma_TOT]] -> -187.39171 | CH10: {=-BR10 * IFERROR(INDEX('Precio Leche_EBITDA_Ventas'!$BD$87:$BD$110,MATCH(1,('Precio Leche_EBITDA_Ventas'!$AZ$87:$AZ$110=YEAR(A10))*('Precio Leche_EBITDA_Ventas'!$BB$87:$BB$110=C10),0)),1.3)} -> -1002.68 | CI10: =+CG10*$CM$2 -> -243.60922
A11: 45678 | B11: 1 | C11: =+UPPER(TEXT(Tabla_master_rend[[#This Row],[Fecha]],"MMM")) -> ENE | D11: =+UPPER(TEXT(Tabla_master_rend[[#This Row],[Fecha]],"ddd")) -> MA | E11: 210125026 | F11: VACA | G11: GOUDA | H11: 17 | I11: =+Tabla_master_rend[[#This Row],[L_Leche_ent]]+Tabla_master_rend[[#This Row],[L_desn_ext]]+Tabla_master_rend[[#This Row],[L_cabra]]+Tabla_master_rend[[#This Row],[L_oveja]] -> 243613 | J11: 243613 | K11: 0.038 | L11: 0.0342 | M11: =0.93*K11+0.74*L11+0.048 -> 0.108648 | N11: NO | O11: 0 | P11: 0 | Q11: 0 | R11: 0 | T11: 232070 | U11: =+Tabla_master_rend[[#This Row],[L_suero Total]]/Tabla_master_rend[[#This Row],[Litros_Leche_Total]] -> 0.95261747 | V11: 0.0031 | W11: 0.0101 | X11: 91249 | Y11: 25873 | Z11: =IF(Tabla_master_rend[[#This Row],[L_suero para con]]=0,0,+Tabla_master_rend[[#This Row],[L_suero para con]]/Tabla_master_rend[[#This Row],[L_suero_con]]) -> 3.526804 | AA11: =+Tabla_master_rend[[#This Row],[L_suero Total]]-Tabla_master_rend[[#This Row],[L_suero para con]] -> 140821 | AD11: 42052 | AE11: 0 | AF11: 0 | AI11: =+Tabla_master_rend[[#This Row],[Kg_Finos]]+Tabla_master_rend[[#This Row],[Kg_Llenadora]]+Tabla_master_rend[[#This Row],[Kg_Desmoldeo]]+Tabla_master_rend[[#This Row],[L_Agua]]+Tabla_master_rend[[#This Row],[Kg_SalidaSecadero]] -> 31443.34 | AJ11: =+Tabla_master_rend[[#This Row],[Litros_Leche_Total]]/Tabla_master_rend[[#This Row],[Kg_Queso_Blan]] -> 7.747682 | AK11: =+Tabla_master_rend[[#This Row],[Litros_Leche_Total]]/(Tabla_master_rend[[#This Row],[Kg_Queso_Blan]]-Tabla_master_rend[[#This Row],[Merma_TOT]]) -> 8.0062403 | AL11: =VLOOKUP(G11,REND_TARGET[#All],8,FALSE) -> 8.494317 | AM11: =(I11*1.03*Tabla_master_rend[[#This Row],[%MG_Leche]])+(I11*1.03*Tabla_master_rend[[#This Row],[%MP_Leche]]) -> 18116.524 | AN11: 0.2957 | AO11: 0.2164 | AP11: 0.561 | AQ11: =+Tabla_master_rend[[#This Row],[Kg_Queso_Blan]]*Tabla_master_rend[[#This Row],[ES_QUESO]]/(Tabla_master_rend[[#This Row],[Kg_Solidos_leche]]) -> 0.9736809 | AR11: =R11*0.4 -> 0 | AS11: =+(Tabla_master_rend[[#This Row],[Kg_Queso_Blan]]*Tabla_master_rend[[#This Row],[%MG_QUESO]]+(Tabla_master_rend[[#This Row],[Kg_MG_Nata]]))/(Tabla_master_rend[[#This Row],[Litros_Leche_Total]]*1.03*Tabla_master_rend[[#This Row],[%MG_Leche]]) -> 0.97512146 | AT11: =+Tabla_master_rend[[#This Row],[Kg_Queso_Blan]]*Tabla_master_rend[[#This Row],[%PT_QUESO]]/(Tabla_master_rend[[#This Row],[Litros_Leche_Total]]*1.03*Tabla_master_rend[[#This Row],[%MP_Leche]]) -> 0.79290679 | AU11: =AR11*$CO$3 -> 0 | AV11: 88.24 | AW11: 171.4 | AX11: 34.7 | AY11: =SUM(Tabla_master_rend[[#This Row],[Kg_Finos]:[Kg_Desmoldeo]]) -> 294.34 | AZ11: =+(Tabla_master_rend[[#This Row],[Kg_Finos]]+Tabla_master_rend[[#This Row],[Kg_Llenadora]]+Tabla_master_rend[[#This Row],[Kg_Desmoldeo]])/(Tabla_master_rend[[#This Row],[Kg_Queso_Blan]]) -> 0.0093609648 | BA11: 600 | BB11: =+Tabla_master_rend[[#This Row],[L_Agua]]/(Tabla_master_rend[[#This Row],[L_Agua]]+Tabla_master_rend[[#This Row],[Kg_SalidaSecadero]]) -> 0.019262256 | BC11: 4176 | BD11: 4135 | BE11: 30891 | BF11: =106*6.2 -> 657.2 | BG11: =11*6.2 -> 68.2 | BH11: =9*6.2 -> 55.8 | BI11: =6*6.2 -> 37.2 | BJ11: 96 | BK11: 30549 | BL11: 2.38 | BM11: 102.77 | BN11: 15.96 | BO11: =+SUM(Tabla_master_rend[[#This Row],[B_altas]:[B_lab]])/Tabla_master_rend[[#This Row],[Kg_SalidaSecadero]] -> 0.02993224 | BP11: =+(Tabla_master_rend[[#This Row],[Kg_mer_env_real]]+Tabla_master_rend[[#This Row],[kg_mer_lab_real]])/Tabla_master_rend[[#This Row],[Kg_SalidaSecadero]] -> 0.0038865429 | BQ11: =+Tabla_master_rend[[#This Row],[Merma_TOT]]/Tabla_master_rend[[#This Row],[Kg_Queso_Blan]] -> 0.032294597 | BR11: =+Tabla_master_rend[[#This Row],[kg_mer_lab_real]]+Tabla_master_rend[[#This Row],[Kg_mer_env_real]]+Tabla_master_rend[[#This Row],[Kg_rebaba]]+Tabla_master_rend[[#This Row],[L_Agua]]+Tabla_master_rend[[#This Row],[Kg_Desmoldeo]]+Tabla_master_rend[[#This Row],[Kg_Llenadora]]+Tabla_master_rend[[#This Row],[Kg_Finos]] -> 1015.45 | BT11: =IF(+Tabla_master_rend[[#This Row],[Kg_Env_Total]]=0,0,Tabla_master_rend[[#This Row],[Kg_Env_Total]]-Tabla_master_rend[[#This Row],[Kg_SalidaSecadero]]) -> 0 | BU11: =+Tabla_master_rend[[#This Row],[Diferencia_Env_vs_Sec_kg]]/Tabla_master_rend[[#This Row],[Kg_SalidaSecadero]] -> 0 | BV11: =IFERROR(Tabla_master_rend[[#This Row],[Litros_Leche_Total]]*SUMIFS(tbl_PrecioLeche[PMV_eur_L],tbl_PrecioLeche[AñoMes],TEXT(Tabla_master_rend[[#This Row],[Fecha]],"yyyy-mm"),tbl_PrecioLeche[Tipo_Leche],Tabla_master_rend[[#This Row],[Tipo_Leche]]),"") -> 0 | BW11: =+(Tabla_master_rend[[#This Row],[Coste_Leche_€]]-Tabla_master_rend[[#This Row],[Kg_MG_Nata]]*$CO$3)/Tabla_master_rend[[#This Row],[Kg_Queso_Blan]] -> 0 | BX11: =SUM(Tabla_master_rend[[#This Row],[Kg_Finos]:[Kg_Desmoldeo]])+Tabla_master_rend[[#This Row],[L_Agua]]+SUM(Tabla_master_rend[[#This Row],[B_altas]:[B_lab]]) -> 1808.74 | BY11: =+BX11-Tabla_master_rend[[#This Row],[Merma_TOT]] -> 793.29 | BZ11: =+BY11/BX11 -> 0.43858708 | CA11: =+Tabla_master_rend[[#This Row],[Kg_Queso_Blan]]*$CA$1 -> 204.38171 | CB11: =+Tabla_master_rend[[#This Row],[Kg_Queso_Blan]]*($CB$1-$CA$1) -> 110.05169 | CC11: =+(Tabla_master_rend[[#This Row],[Kg_Queso_Blan]]-CA11-CB11)*$CC$1 -> 326.85352 | CD11: =+CA11+CB11+CC11 -> 641.28692 | CE11: =+CD11/Tabla_master_rend[[#This Row],[Kg_Queso_Blan]] -> 0.020395 | CF11: =+Tabla_master_rend[[#This Row],[Merma_TOT]]/Tabla_master_rend[[#This Row],[Kg_Queso_Blan]] -> 0.032294597 | CG11: =CD11-Tabla_master_rend[[#This Row],[Merma_TOT]] -> -374.16308 | CH11: {=-BR11 * IFERROR(INDEX('Precio Leche_EBITDA_Ventas'!$BD$87:$BD$110,MATCH(1,('Precio Leche_EBITDA_Ventas'!$AZ$87:$AZ$110=YEAR(A11))*('Precio Leche_EBITDA_Ventas'!$BB$87:$BB$110=C11),0)),1.3)} -> -3554.075 | CI11: =+CG11*$CM$2 -> -486.412
A12: 45680 | B12: 1 | C12: =+UPPER(TEXT(Tabla_master_rend[[#This Row],[Fecha]],"MMM")) -> ENE | D12: =+UPPER(TEXT(Tabla_master_rend[[#This Row],[Fecha]],"ddd")) -> JU | E12: 230125026 | F12: VACA | G12: GOUDA | H12: 17 | I12: =+Tabla_master_rend[[#This Row],[L_Leche_ent]]+Tabla_master_rend[[#This Row],[L_desn_ext]]+Tabla_master_rend[[#This Row],[L_cabra]]+Tabla_master_rend[[#This Row],[L_oveja]] -> 249563 | J12: 249563 | K12: 0.039 | L12: 0.0344 | M12: =0.93*K12+0.74*L12+0.048 -> 0.109726 | N12: NO | O12: 0 | P12: 0 | Q12: 0 | R12: 0 | T12: 237550 | U12: =+Tabla_master_rend[[#This Row],[L_suero Total]]/Tabla_master_rend[[#This Row],[Litros_Leche_Total]] -> 0.95186386 | V12: 0.0034 | W12: 0.0105 | X12: 139532 | Y12: 40137 | Z12: =IF(Tabla_master_rend[[#This Row],[L_suero para con]]=0,0,+Tabla_master_rend[[#This Row],[L_suero para con]]/Tabla_master_rend[[#This Row],[L_suero_con]]) -> 3.4763934 | AA12: =+Tabla_master_rend[[#This Row],[L_suero Total]]-Tabla_master_rend[[#This Row],[L_suero para con]] -> 98018 | AD12: 42052 | AE12: 0 | AF12: 0 | AI12: =+Tabla_master_rend[[#This Row],[Kg_Finos]]+Tabla_master_rend[[#This Row],[Kg_Llenadora]]+Tabla_master_rend[[#This Row],[Kg_Desmoldeo]]+Tabla_master_rend[[#This Row],[L_Agua]]+Tabla_master_rend[[#This Row],[Kg_SalidaSecadero]] -> 32310.53 | AJ12: =+Tabla_master_rend[[#This Row],[Litros_Leche_Total]]/Tabla_master_rend[[#This Row],[Kg_Queso_Blan]] -> 7.7238906 | AK12: =+Tabla_master_rend[[#This Row],[Litros_Leche_Total]]/(Tabla_master_rend[[#This Row],[Kg_Queso_Blan]]-Tabla_master_rend[[#This Row],[Merma_TOT]]) -> 7.9770434 | AL12: =VLOOKUP(G12,REND_TARGET[#All],8,FALSE) -> 8.494317 | AM12: =(I12*1.03*Tabla_master_rend[[#This Row],[%MG_Leche]])+(I12*1.03*Tabla_master_rend[[#This Row],[%MP_Leche]]) -> 18867.462 | AN12: 0.3038 | AO12: 0.2176 | AP12: 0.5719 | AQ12: =+Tabla_master_rend[[#This Row],[Kg_Queso_Blan]]*Tabla_master_rend[[#This Row],[ES_QUESO]]/(Tabla_master_rend[[#This Row],[Kg_Solidos_leche]]) -> 0.97937879 | AR12: =R12*0.4 -> 0 | AS12: =+(Tabla_master_rend[[#This Row],[Kg_Queso_Blan]]*Tabla_master_rend[[#This Row],[%MG_QUESO]]+(Tabla_master_rend[[#This Row],[Kg_MG_Nata]]))/(Tabla_master_rend[[#This Row],[Litros_Leche_Total]]*1.03*Tabla_master_rend[[#This Row],[%MG_Leche]]) -> 0.97915134 | AT12: =+Tabla_master_rend[[#This Row],[Kg_Queso_Blan]]*Tabla_master_rend[[#This Row],[%PT_QUESO]]/(Tabla_master_rend[[#This Row],[Litros_Leche_Total]]*1.03*Tabla_master_rend[[#This Row],[%MP_Leche]]) -> 0.7951098 | AU12: =AR12*$CO$3 -> 0 | AV12: 87.73 | AW12: 195 | AX12: 8.8 | AY12: =SUM(Tabla_master_rend[[#This Row],[Kg_Finos]:[Kg_Desmoldeo]]) -> 291.53 | AZ12: =+(Tabla_master_rend[[#This Row],[Kg_Finos]]+Tabla_master_rend[[#This Row],[Kg_Llenadora]]+Tabla_master_rend[[#This Row],[Kg_Desmoldeo]])/(Tabla_master_rend[[#This Row],[Kg_Queso_Blan]]) -> 0.0090227551 | BA12: 650 | BB12: =+Tabla_master_rend[[#This Row],[L_Agua]]/(Tabla_master_rend[[#This Row],[L_Agua]]+Tabla_master_rend[[#This Row],[Kg_SalidaSecadero]]) -> 0.020300447 | BC12: 4282 | BD12: 4254 | BE12: 31837 | BF12: =122*6.6 -> 805.2 | BG12: =8*6.6 -> 52.8 | BH12: =5*6.6 -> 33 | BI12: =9*6.6 -> 59.4 | BJ12: 89 | BK12: 31369 | BL12: 4.89 | BM12: 62.85 | BN12: 16.11 | BO12: =+SUM(Tabla_master_rend[[#This Row],[B_altas]:[B_lab]])/Tabla_master_rend[[#This Row],[Kg_SalidaSecadero]] -> 0.033134623 | BP12: =+(Tabla_master_rend[[#This Row],[Kg_mer_env_real]]+Tabla_master_rend[[#This Row],[kg_mer_lab_real]])/Tabla_master_rend[[#This Row],[Kg_SalidaSecadero]] -> 0.0025171348 | BQ12: =+Tabla_master_rend[[#This Row],[Merma_TOT]]/Tabla_master_rend[[#This Row],[Kg_Queso_Blan]] -> 0.031735165 | BR12: =+Tabla_master_rend[[#This Row],[kg_mer_lab_real]]+Tabla_master_rend[[#This Row],[Kg_mer_env_real]]+Tabla_master_rend[[#This Row],[Kg_rebaba]]+Tabla_master_rend[[#This Row],[L_Agua]]+Tabla_master_rend[[#This Row],[Kg_Desmoldeo]]+Tabla_master_rend[[#This Row],[Kg_Llenadora]]+Tabla_master_rend[[#This Row],[Kg_Finos]] -> 1025.38 | BT12: =IF(+Tabla_master_rend[[#This Row],[Kg_Env_Total]]=0,0,Tabla_master_rend[[#This Row],[Kg_Env_Total]]-Tabla_master_rend[[#This Row],[Kg_SalidaSecadero]]) -> 0 | BU12: =+Tabla_master_rend[[#This Row],[Diferencia_Env_vs_Sec_kg]]/Tabla_master_rend[[#This Row],[Kg_SalidaSecadero]] -> 0 | BV12: =IFERROR(Tabla_master_rend[[#This Row],[Litros_Leche_Total]]*SUMIFS(tbl_PrecioLeche[PMV_eur_L],tbl_PrecioLeche[AñoMes],TEXT(Tabla_master_rend[[#This Row],[Fecha]],"yyyy-mm"),tbl_PrecioLeche[Tipo_Leche],Tabla_master_rend[[#This Row],[Tipo_Leche]]),"") -> 0 | BW12: =+(Tabla_master_rend[[#This Row],[Coste_Leche_€]]-Tabla_master_rend[[#This Row],[Kg_MG_Nata]]*$CO$3)/Tabla_master_rend[[#This Row],[Kg_Queso_Blan]] -> 0 | BX12: =SUM(Tabla_master_rend[[#This Row],[Kg_Finos]:[Kg_Desmoldeo]])+Tabla_master_rend[[#This Row],[L_Agua]]+SUM(Tabla_master_rend[[#This Row],[B_altas]:[B_lab]]) -> 1980.93 | BY12: =+BX12-Tabla_master_rend[[#This Row],[Merma_TOT]] -> 955.55 | BZ12: =+BY12/BX12 -> 0.48237444 | CA12: =+Tabla_master_rend[[#This Row],[Kg_Queso_Blan]]*$CA$1 -> 210.01844 | CB12: =+Tabla_master_rend[[#This Row],[Kg_Queso_Blan]]*($CB$1-$CA$1) -> 113.08686 | CC12: =+(Tabla_master_rend[[#This Row],[Kg_Queso_Blan]]-CA12-CB12)*$CC$1 -> 335.86796 | CD12: =+CA12+CB12+CC12 -> 658.97326 | CE12: =+CD12/Tabla_master_rend[[#This Row],[Kg_Queso_Blan]] -> 0.020395 | CF12: =+Tabla_master_rend[[#This Row],[Merma_TOT]]/Tabla_master_rend[[#This Row],[Kg_Queso_Blan]] -> 0.031735165 | CG12: =CD12-Tabla_master_rend[[#This Row],[Merma_TOT]] -> -366.40674 | CH12: {=-BR12 * IFERROR(INDEX('Precio Leche_EBITDA_Ventas'!$BD$87:$BD$110,MATCH(1,('Precio Leche_EBITDA_Ventas'!$AZ$87:$AZ$110=YEAR(A12))*('Precio Leche_EBITDA_Ventas'!$BB$87:$BB$110=C12),0)),1.3)} -> -3588.83 | CI12: =+CG12*$CM$2 -> -476.32876
A13: 45684 | B13: 1 | C13: =+UPPER(TEXT(Tabla_master_rend[[#This Row],[Fecha]],"MMM")) -> ENE | D13: =+UPPER(TEXT(Tabla_master_rend[[#This Row],[Fecha]],"ddd")) -> LU | E13: 270125116 | F13: VACA | G13: EDAM_F | H13: 12 | I13: =+Tabla_master_rend[[#This Row],[L_Leche_ent]]+Tabla_master_rend[[#This Row],[L_desn_ext]]+Tabla_master_rend[[#This Row],[L_cabra]]+Tabla_master_rend[[#This Row],[L_oveja]] -> 193094 | J13: 193094 | K13: 0.0367 | L13: 0.0337 | M13: =0.93*K13+0.74*L13+0.048 -> 0.107069 | N13: NO | O13: 0 | P13: 0 | Q13: 0 | R13: 4854 | T13: 166366.29 | U13: =+Tabla_master_rend[[#This Row],[L_suero Total]]/Tabla_master_rend[[#This Row],[Litros_Leche_Total]] -> 0.86158185 | V13: 0.0013 | W13: 0.0089 | X13: =90773/(13864+166366)*166366 -> 83790.384 | Y13: =29400/(13864+166366)*166366 -> 27138.436 | Z13: =IF(Tabla_master_rend[[#This Row],[L_suero para con]]=0,0,+Tabla_master_rend[[#This Row],[L_suero para con]]/Tabla_master_rend[[#This Row],[L_suero_con]]) -> 3.087517 | AA13: =+Tabla_master_rend[[#This Row],[L_suero Total]]-Tabla_master_rend[[#This Row],[L_suero para con]] -> 82575.902 | AD13: 42052 | AE13: 0 | AF13: 0 | AI13: =+Tabla_master_rend[[#This Row],[Kg_Finos]]+Tabla_master_rend[[#This Row],[Kg_Llenadora]]+Tabla_master_rend[[#This Row],[Kg_Desmoldeo]]+Tabla_master_rend[[#This Row],[L_Agua]]+Tabla_master_rend[[#This Row],[Kg_SalidaSecadero]] -> 21130.399 | AJ13: =+Tabla_master_rend[[#This Row],[Litros_Leche_Total]]/Tabla_master_rend[[#This Row],[Kg_Queso_Blan]] -> 9.1382087 | AK13: =+Tabla_master_rend[[#This Row],[Litros_Leche_Total]]/(Tabla_master_rend[[#This Row],[Kg_Queso_Blan]]-Tabla_master_rend[[#This Row],[Merma_TOT]]) -> 9.5330205 | AL13: =VLOOKUP(G13,REND_TARGET[#All],8,FALSE) -> 9.80785 | AM13: =(I13*1.03*Tabla_master_rend[[#This Row],[%MG_Leche]])+(I13*1.03*Tabla_master_rend[[#This Row],[%MP_Leche]]) -> 14001.632 | AN13: 0.2241 | AO13: 0.2424 | AP13: 0.522 | AQ13: =+Tabla_master_rend[[#This Row],[Kg_Queso_Blan]]*Tabla_master_rend[[#This Row],[ES_QUESO]]/(Tabla_master_rend[[#This Row],[Kg_Solidos_leche]]) -> 0.78777019 | AR13: =R13*0.4 -> 1941.6 | AS13: =+(Tabla_master_rend[[#This Row],[Kg_Queso_Blan]]*Tabla_master_rend[[#This Row],[%MG_QUESO]]+(Tabla_master_rend[[#This Row],[Kg_MG_Nata]]))/(Tabla_master_rend[[#This Row],[Litros_Leche_Total]]*1.03*Tabla_master_rend[[#This Row],[%MG_Leche]]) -> 0.91475389 | AT13: =+Tabla_master_rend[[#This Row],[Kg_Queso_Blan]]*Tabla_master_rend[[#This Row],[%PT_QUESO]]/(Tabla_master_rend[[#This Row],[Litros_Leche_Total]]*1.03*Tabla_master_rend[[#This Row],[%MP_Leche]]) -> 0.76419539 | AU13: =AR13*$CO$3 -> 14562 | AV13: 35.630798 | AW13: 77.172724 | AX13: 18.595837 | AY13: =SUM(Tabla_master_rend[[#This Row],[Kg_Finos]:[Kg_Desmoldeo]]) -> 131.39936 | AZ13: =+(Tabla_master_rend[[#This Row],[Kg_Finos]]+Tabla_master_rend[[#This Row],[Kg_Llenadora]]+Tabla_master_rend[[#This Row],[Kg_Desmoldeo]])/(Tabla_master_rend[[#This Row],[Kg_Queso_Blan]]) -> 0.0062184986 | BA13: 455 | BB13: =+Tabla_master_rend[[#This Row],[L_Agua]]/(Tabla_master_rend[[#This Row],[L_Agua]]+Tabla_master_rend[[#This Row],[Kg_SalidaSecadero]]) -> 0.021667698 | BC13: 2993 | BD13: 2864 | BE13: 20193 | BF13: =2*6.3 -> 12.6 | BG13: =48*6.3 -> 302.4 | BH13: 0 | BI13: =70*6.3 -> 441 | BJ13: 63 | BK13: 20544 | BL13: 7.88 | BM13: 266.49 | BN13: 14.35 | BO13: =+SUM(Tabla_master_rend[[#This Row],[B_altas]:[B_lab]])/Tabla_master_rend[[#This Row],[Kg_SalidaSecadero]] -> 0.039865654 | BP13: =+(Tabla_master_rend[[#This Row],[Kg_mer_env_real]]+Tabla_master_rend[[#This Row],[kg_mer_lab_real]])/Tabla_master_rend[[#This Row],[Kg_SalidaSecadero]] -> 0.013670171 | BQ13: =+Tabla_master_rend[[#This Row],[Merma_TOT]]/Tabla_master_rend[[#This Row],[Kg_Queso_Blan]] -> 0.041415183 | BR13: =+Tabla_master_rend[[#This Row],[kg_mer_lab_real]]+Tabla_master_rend[[#This Row],[Kg_mer_env_real]]+Tabla_master_rend[[#This Row],[Kg_rebaba]]+Tabla_master_rend[[#This Row],[L_Agua]]+Tabla_master_rend[[#This Row],[Kg_Desmoldeo]]+Tabla_master_rend[[#This Row],[Kg_Llenadora]]+Tabla_master_rend[[#This Row],[Kg_Finos]] -> 875.11936 | BT13: =IF(+Tabla_master_rend[[#This Row],[Kg_Env_Total]]=0,0,Tabla_master_rend[[#This Row],[Kg_Env_Total]]-Tabla_master_rend[[#This Row],[Kg_SalidaSecadero]]) -> 0 | BU13: =+Tabla_master_rend[[#This Row],[Diferencia_Env_vs_Sec_kg]]/Tabla_master_rend[[#This Row],[Kg_SalidaSecadero]] -> 0 | BV13: =IFERROR(Tabla_master_rend[[#This Row],[Litros_Leche_Total]]*SUMIFS(tbl_PrecioLeche[PMV_eur_L],tbl_PrecioLeche[AñoMes],TEXT(Tabla_master_rend[[#This Row],[Fecha]],"yyyy-mm"),tbl_PrecioLeche[Tipo_Leche],Tabla_master_rend[[#This Row],[Tipo_Leche]]),"") -> 0 | BW13: =+(Tabla_master_rend[[#This Row],[Coste_Leche_€]]-Tabla_master_rend[[#This Row],[Kg_MG_Nata]]*$CO$3)/Tabla_master_rend[[#This Row],[Kg_Queso_Blan]] -> -0.6891493 | BX13: =SUM(Tabla_master_rend[[#This Row],[Kg_Finos]:[Kg_Desmoldeo]])+Tabla_master_rend[[#This Row],[L_Agua]]+SUM(Tabla_master_rend[[#This Row],[B_altas]:[B_lab]]) -> 1405.3994 | BY13: =+BX13-Tabla_master_rend[[#This Row],[Merma_TOT]] -> 530.28 | BZ13: =+BY13/BX13 -> 0.37731624 | CA13: =+Tabla_master_rend[[#This Row],[Kg_Queso_Blan]]*$CA$1 -> 137.3476 | CB13: =+Tabla_master_rend[[#This Row],[Kg_Queso_Blan]]*($CB$1-$CA$1) -> 73.956398 | CC13: =+(Tabla_master_rend[[#This Row],[Kg_Queso_Blan]]-CA13-CB13)*$CC$1 -> 219.6505 | CD13: =+CA13+CB13+CC13 -> 430.95449 | CE13: =+CD13/Tabla_master_rend[[#This Row],[Kg_Queso_Blan]] -> 0.020395 | CF13: =+Tabla_master_rend[[#This Row],[Merma_TOT]]/Tabla_master_rend[[#This Row],[Kg_Queso_Blan]] -> 0.041415183 | CG13: =CD13-Tabla_master_rend[[#This Row],[Merma_TOT]] -> -444.16486 | CH13: {=-BR13 * IFERROR(INDEX('Precio Leche_EBITDA_Ventas'!$BD$87:$BD$110,MATCH(1,('Precio Leche_EBITDA_Ventas'!$AZ$87:$AZ$110=YEAR(A13))*('Precio Leche_EBITDA_Ventas'!$BB$87:$BB$110=C13),0)),1.3)} -> -3062.9178 | CI13: =+CG13*$CM$2 -> -577.41432
A14: 45684 | B14: 1 | C14: =+UPPER(TEXT(Tabla_master_rend[[#This Row],[Fecha]],"MMM")) -> ENE | D14: =+UPPER(TEXT(Tabla_master_rend[[#This Row],[Fecha]],"ddd")) -> LU | E14: 270125326 | F14: VACA | G14: GOUDA_F | H14: 1 | I14: =+Tabla_master_rend[[#This Row],[L_Leche_ent]]+Tabla_master_rend[[#This Row],[L_desn_ext]]+Tabla_master_rend[[#This Row],[L_cabra]]+Tabla_master_rend[[#This Row],[L_oveja]] -> 16091.154 | J14: 16091.154 | K14: 0.0367 | L14: 0.0337 | M14: =0.93*K14+0.74*L14+0.048 -> 0.107069 | N14: NO | O14: 0 | P14: 0 | Q14: 0 | R14: 284 | T14: 13863.714 | U14: =+Tabla_master_rend[[#This Row],[L_suero Total]]/Tabla_master_rend[[#This Row],[Litros_Leche_Total]] -> 0.86157362 | V14: 0.0013 | W14: 0.0089 | X14: =90773/(13864+166366)*13864 -> 6982.6159 | Y14: =29400/(13864+166366)*13864 -> 2261.5636 | Z14: =IF(Tabla_master_rend[[#This Row],[L_suero para con]]=0,0,+Tabla_master_rend[[#This Row],[L_suero para con]]/Tabla_master_rend[[#This Row],[L_suero_con]]) -> 3.087517 | AA14: =+Tabla_master_rend[[#This Row],[L_suero Total]]-Tabla_master_rend[[#This Row],[L_suero para con]] -> 6881.0977 | AD14: 42052 | AE14: 0 | AF14: 0 | AI14: =+Tabla_master_rend[[#This Row],[Kg_Finos]]+Tabla_master_rend[[#This Row],[Kg_Llenadora]]+Tabla_master_rend[[#This Row],[Kg_Desmoldeo]]+Tabla_master_rend[[#This Row],[L_Agua]]+Tabla_master_rend[[#This Row],[Kg_SalidaSecadero]] -> 1624.2006 | AJ14: =+Tabla_master_rend[[#This Row],[Litros_Leche_Total]]/Tabla_master_rend[[#This Row],[Kg_Queso_Blan]] -> 9.907122 | AK14: =+Tabla_master_rend[[#This Row],[Litros_Leche_Total]]/(Tabla_master_rend[[#This Row],[Kg_Queso_Blan]]-Tabla_master_rend[[#This Row],[Merma_TOT]]) -> 10.323246 | AL14: =VLOOKUP(G14,REND_TARGET[#All],8,FALSE) -> 9.354943 | AM14: =(I14*1.03*Tabla_master_rend[[#This Row],[%MG_Leche]])+(I14*1.03*Tabla_master_rend[[#This Row],[%MP_Leche]]) -> 1166.8017 | AN14: 0.2597 | AO14: 0.2257 | AP14: 0.5409 | AQ14: =+Tabla_master_rend[[#This Row],[Kg_Queso_Blan]]*Tabla_master_rend[[#This Row],[ES_QUESO]]/(Tabla_master_rend[[#This Row],[Kg_Solidos_leche]]) -> 0.75293864 | AR14: =R14*0.4 -> 113.6 | AS14: =+(Tabla_master_rend[[#This Row],[Kg_Queso_Blan]]*Tabla_master_rend[[#This Row],[%MG_QUESO]]+(Tabla_master_rend[[#This Row],[Kg_MG_Nata]]))/(Tabla_master_rend[[#This Row],[Litros_Leche_Total]]*1.03*Tabla_master_rend[[#This Row],[%MG_Leche]]) -> 0.88022129 | AT14: =+Tabla_master_rend[[#This Row],[Kg_Queso_Blan]]*Tabla_master_rend[[#This Row],[%PT_QUESO]]/(Tabla_master_rend[[#This Row],[Litros_Leche_Total]]*1.03*Tabla_master_rend[[#This Row],[%MP_Leche]]) -> 0.65632194 | AU14: =AR14*$CO$3 -> 852 | AV14: 2.9692024 | AW14: 5.8272756 | AX14: 1.4041628 | AY14: =SUM(Tabla_master_rend[[#This Row],[Kg_Finos]:[Kg_Desmoldeo]]) -> 10.200641 | AZ14: =+(Tabla_master_rend[[#This Row],[Kg_Finos]]+Tabla_master_rend[[#This Row],[Kg_Llenadora]]+Tabla_master_rend[[#This Row],[Kg_Desmoldeo]])/(Tabla_master_rend[[#This Row],[Kg_Queso_Blan]]) -> 0.0062804068 | BA14: 35 | BB14: =+Tabla_master_rend[[#This Row],[L_Agua]]/(Tabla_master_rend[[#This Row],[L_Agua]]+Tabla_master_rend[[#This Row],[Kg_SalidaSecadero]]) -> 0.021685254 | BC14: 226 | BD14: 209 | BE14: 1502 | BF14: 0 | BG14: =15*6.7 -> 100.5 | BH14: 0 | BI14: 0 | BJ14: 12 | BK14: 1579 | BL14: 0 | BM14: 8.45 | BN14: 11.82 | BO14: =+SUM(Tabla_master_rend[[#This Row],[B_altas]:[B_lab]])/Tabla_master_rend[[#This Row],[Kg_SalidaSecadero]] -> 0.071247625 | BP14: =+(Tabla_master_rend[[#This Row],[Kg_mer_env_real]]+Tabla_master_rend[[#This Row],[kg_mer_lab_real]])/Tabla_master_rend[[#This Row],[Kg_SalidaSecadero]] -> 0.012837239 | BQ14: =+Tabla_master_rend[[#This Row],[Merma_TOT]]/Tabla_master_rend[[#This Row],[Kg_Queso_Blan]] -> 0.040309454 | BR14: =+Tabla_master_rend[[#This Row],[kg_mer_lab_real]]+Tabla_master_rend[[#This Row],[Kg_mer_env_real]]+Tabla_master_rend[[#This Row],[Kg_rebaba]]+Tabla_master_rend[[#This Row],[L_Agua]]+Tabla_master_rend[[#This Row],[Kg_Desmoldeo]]+Tabla_master_rend[[#This Row],[Kg_Llenadora]]+Tabla_master_rend[[#This Row],[Kg_Finos]] -> 65.470641 | BT14: =IF(+Tabla_master_rend[[#This Row],[Kg_Env_Total]]=0,0,Tabla_master_rend[[#This Row],[Kg_Env_Total]]-Tabla_master_rend[[#This Row],[Kg_SalidaSecadero]]) -> 0 | BU14: =+Tabla_master_rend[[#This Row],[Diferencia_Env_vs_Sec_kg]]/Tabla_master_rend[[#This Row],[Kg_SalidaSecadero]] -> 0 | BV14: =IFERROR(Tabla_master_rend[[#This Row],[Litros_Leche_Total]]*SUMIFS(tbl_PrecioLeche[PMV_eur_L],tbl_PrecioLeche[AñoMes],TEXT(Tabla_master_rend[[#This Row],[Fecha]],"yyyy-mm"),tbl_PrecioLeche[Tipo_Leche],Tabla_master_rend[[#This Row],[Tipo_Leche]]),"") -> 0 | BW14: =+(Tabla_master_rend[[#This Row],[Coste_Leche_€]]-Tabla_master_rend[[#This Row],[Kg_MG_Nata]]*$CO$3)/Tabla_master_rend[[#This Row],[Kg_Queso_Blan]] -> -0.52456573 | BX14: =SUM(Tabla_master_rend[[#This Row],[Kg_Finos]:[Kg_Desmoldeo]])+Tabla_master_rend[[#This Row],[L_Agua]]+SUM(Tabla_master_rend[[#This Row],[B_altas]:[B_lab]]) -> 157.70064 | BY14: =+BX14-Tabla_master_rend[[#This Row],[Merma_TOT]] -> 92.23 | BZ14: =+BY14/BX14 -> 0.58484227 | CA14: =+Tabla_master_rend[[#This Row],[Kg_Queso_Blan]]*$CA$1 -> 10.557304 | CB14: =+Tabla_master_rend[[#This Row],[Kg_Queso_Blan]]*($CB$1-$CA$1) -> 5.6847022 | CC14: =+(Tabla_master_rend[[#This Row],[Kg_Queso_Blan]]-CA14-CB14)*$CC$1 -> 16.883566 | CD14: =+CA14+CB14+CC14 -> 33.125572 | CE14: =+CD14/Tabla_master_rend[[#This Row],[Kg_Queso_Blan]] -> 0.020395 | CF14: =+Tabla_master_rend[[#This Row],[Merma_TOT]]/Tabla_master_rend[[#This Row],[Kg_Queso_Blan]] -> 0.040309454 | CG14: =CD14-Tabla_master_rend[[#This Row],[Merma_TOT]] -> -32.345069 | CH14: {=-BR14 * IFERROR(INDEX('Precio Leche_EBITDA_Ventas'!$BD$87:$BD$110,MATCH(1,('Precio Leche_EBITDA_Ventas'!$AZ$87:$AZ$110=YEAR(A14))*('Precio Leche_EBITDA_Ventas'!$BB$87:$BB$110=C14),0)),1.3)} -> -229.14724 | CI14: =+CG14*$CM$2 -> -42.048589
A15: 45685 | B15: 1 | C15: =+UPPER(TEXT(Tabla_master_rend[[#This Row],[Fecha]],"MMM")) -> ENE | D15: =+UPPER(TEXT(Tabla_master_rend[[#This Row],[Fecha]],"ddd")) -> MA | E15: 280125176 | F15: VACA | G15: BAJO_GRASA_F | H15: 3 | I15: =+Tabla_master_rend[[#This Row],[L_Leche_ent]]+Tabla_master_rend[[#This Row],[L_desn_ext]]+Tabla_master_rend[[#This Row],[L_cabra]]+Tabla_master_rend[[#This Row],[L_oveja]] -> 49809 | J15: 49809 | K15: 0.0378 | L15: 0.0333 | M15: =0.93*K15+0.74*L15+0.048 -> 0.107796 | N15: SI | O15: 0 | P15: 0 | Q15: 0 | R15: 5020 | T15: 41820 | U15: =+Tabla_master_rend[[#This Row],[L_suero Total]]/Tabla_master_rend[[#This Row],[Litros_Leche_Total]] -> 0.8396073 | V15: 0 | W15: 0.0098 | X15: =70226/(27180+41820)*41820 -> 42563.063 | Y15: =20219/(27180+41820)*41820 -> 12254.472 | Z15: =IF(Tabla_master_rend[[#This Row],[L_suero para con]]=0,0,+Tabla_master_rend[[#This Row],[L_suero para con]]/Tabla_master_rend[[#This Row],[L_suero_con]]) -> 3.4732677 | AA15: =+Tabla_master_rend[[#This Row],[L_suero Total]]-Tabla_master_rend[[#This Row],[L_suero para con]] -> -743.06261 | AD15: 0 | AE15: 0 | AF15: 0 | AG15: 0 | AH15: 0 | AI15: =+Tabla_master_rend[[#This Row],[Kg_Finos]]+Tabla_master_rend[[#This Row],[Kg_Llenadora]]+Tabla_master_rend[[#This Row],[Kg_Desmoldeo]]+Tabla_master_rend[[#This Row],[L_Agua]]+Tabla_master_rend[[#This Row],[Kg_SalidaSecadero]] -> 3953.4509 | AJ15: =+Tabla_master_rend[[#This Row],[Litros_Leche_Total]]/Tabla_master_rend[[#This Row],[Kg_Queso_Blan]] -> 12.598866 | AK15: =+Tabla_master_rend[[#This Row],[Litros_Leche_Total]]/(Tabla_master_rend[[#This Row],[Kg_Queso_Blan]]-Tabla_master_rend[[#This Row],[Merma_TOT]]) -> 13.313572 | AL15: =VLOOKUP(G15,REND_TARGET[#All],8,FALSE) -> #N/A | AM15: =(I15*1.03*Tabla_master_rend[[#This Row],[%MG_Leche]])+(I15*1.03*Tabla_master_rend[[#This Row],[%MP_Leche]]) -> 3647.6625 | AN15: 0.0614 | AO15: 0.3165 | AP15: 0.5493 | AQ15: =+Tabla_master_rend[[#This Row],[Kg_Queso_Blan]]*Tabla_master_rend[[#This Row],[ES_QUESO]]/(Tabla_master_rend[[#This Row],[Kg_Solidos_leche]]) -> 0.59534856 | AR15: =R15*0.4 -> 2008 | AS15: =+(Tabla_master_rend[[#This Row],[Kg_Queso_Blan]]*Tabla_master_rend[[#This Row],[%MG_QUESO]]+(Tabla_master_rend[[#This Row],[Kg_MG_Nata]]))/(Tabla_master_rend[[#This Row],[Litros_Leche_Total]]*1.03*Tabla_master_rend[[#This Row],[%MG_Leche]]) -> 1.1606168 | AT15: =+Tabla_master_rend[[#This Row],[Kg_Queso_Blan]]*Tabla_master_rend[[#This Row],[%PT_QUESO]]/(Tabla_master_rend[[#This Row],[Litros_Leche_Total]]*1.03*Tabla_master_rend[[#This Row],[%MP_Leche]]) -> 0.732421 | AU15: =AR15*$CO$3 -> 15060 | AV15: 9.6509405 | AW15: 16.8 | AX15: 0 | AY15: =SUM(Tabla_master_rend[[#This Row],[Kg_Finos]:[Kg_Desmoldeo]]) -> 26.450941 | AZ15: =+(Tabla_master_rend[[#This Row],[Kg_Finos]]+Tabla_master_rend[[#This Row],[Kg_Llenadora]]+Tabla_master_rend[[#This Row],[Kg_Desmoldeo]])/(Tabla_master_rend[[#This Row],[Kg_Queso_Blan]]) -> 0.0066905954 | BA15: 180 | BB15: =+Tabla_master_rend[[#This Row],[L_Agua]]/(Tabla_master_rend[[#This Row],[L_Agua]]+Tabla_master_rend[[#This Row],[Kg_SalidaSecadero]]) -> 0.045836516 | BC15: 604 | BD15: 598 | BE15: 3893 | BF15: 0 | BG15: 0 | BH15: 0 | BI15: 0 | BJ15: 34 | BK15: 3747 | BL15: 0 | BM15: 0 | BN15: 5.78 | BO15: =+SUM(Tabla_master_rend[[#This Row],[B_altas]:[B_lab]])/Tabla_master_rend[[#This Row],[Kg_SalidaSecadero]] -> 0.0090739258 | BP15: =+(Tabla_master_rend[[#This Row],[Kg_mer_env_real]]+Tabla_master_rend[[#This Row],[kg_mer_lab_real]])/Tabla_master_rend[[#This Row],[Kg_SalidaSecadero]] -> 0.0015425674 | BQ15: =+Tabla_master_rend[[#This Row],[Merma_TOT]]/Tabla_master_rend[[#This Row],[Kg_Queso_Blan]] -> 0.053682452 | BR15: =+Tabla_master_rend[[#This Row],[kg_mer_lab_real]]+Tabla_master_rend[[#This Row],[Kg_mer_env_real]]+Tabla_master_rend[[#This Row],[Kg_rebaba]]+Tabla_master_rend[[#This Row],[L_Agua]]+Tabla_master_rend[[#This Row],[Kg_Desmoldeo]]+Tabla_master_rend[[#This Row],[Kg_Llenadora]]+Tabla_master_rend[[#This Row],[Kg_Finos]] -> 212.23094 | BT15: =IF(+Tabla_master_rend[[#This Row],[Kg_Env_Total]]=0,0,Tabla_master_rend[[#This Row],[Kg_Env_Total]]-Tabla_master_rend[[#This Row],[Kg_SalidaSecadero]]) -> 0 | BU15: =+Tabla_master_rend[[#This Row],[Diferencia_Env_vs_Sec_kg]]/Tabla_master_rend[[#This Row],[Kg_SalidaSecadero]] -> 0 | BV15: =IFERROR(Tabla_master_rend[[#This Row],[Litros_Leche_Total]]*SUMIFS(tbl_PrecioLeche[PMV_eur_L],tbl_PrecioLeche[AñoMes],TEXT(Tabla_master_rend[[#This Row],[Fecha]],"yyyy-mm"),tbl_PrecioLeche[Tipo_Leche],Tabla_master_rend[[#This Row],[Tipo_Leche]]),"") -> 0 | BW15: =+(Tabla_master_rend[[#This Row],[Coste_Leche_€]]-Tabla_master_rend[[#This Row],[Kg_MG_Nata]]*$CO$3)/Tabla_master_rend[[#This Row],[Kg_Queso_Blan]] -> -3.8093302 | BX15: =SUM(Tabla_master_rend[[#This Row],[Kg_Finos]:[Kg_Desmoldeo]])+Tabla_master_rend[[#This Row],[L_Agua]]+SUM(Tabla_master_rend[[#This Row],[B_altas]:[B_lab]]) -> 240.45094 | BY15: =+BX15-Tabla_master_rend[[#This Row],[Merma_TOT]] -> 28.22 | BZ15: =+BY15/BX15 -> 0.11736282 | CA15: =+Tabla_master_rend[[#This Row],[Kg_Queso_Blan]]*$CA$1 -> 25.697431 | CB15: =+Tabla_master_rend[[#This Row],[Kg_Queso_Blan]]*($CB$1-$CA$1) -> 13.837078 | CC15: =+(Tabla_master_rend[[#This Row],[Kg_Queso_Blan]]-CA15-CB15)*$CC$1 -> 41.096123 | CD15: =+CA15+CB15+CC15 -> 80.630632 | CE15: =+CD15/Tabla_master_rend[[#This Row],[Kg_Queso_Blan]] -> 0.020395 | CF15: =+Tabla_master_rend[[#This Row],[Merma_TOT]]/Tabla_master_rend[[#This Row],[Kg_Queso_Blan]] -> 0.053682452 | CG15: =CD15-Tabla_master_rend[[#This Row],[Merma_TOT]] -> -131.60031 | CH15: {=-BR15 * IFERROR(INDEX('Precio Leche_EBITDA_Ventas'!$BD$87:$BD$110,MATCH(1,('Precio Leche_EBITDA_Ventas'!$AZ$87:$AZ$110=YEAR(A15))*('Precio Leche_EBITDA_Ventas'!$BB$87:$BB$110=C15),0)),1.3)} -> -742.80829 | CI15: =+CG15*$CM$2 -> -171.0804
A16: 45685 | B16: 1 | C16: =+UPPER(TEXT(Tabla_master_rend[[#This Row],[Fecha]],"MMM")) -> ENE | D16: =+UPPER(TEXT(Tabla_master_rend[[#This Row],[Fecha]],"ddd")) -> MA | E16: 280125196 | F16: VACA | G16: CAGLIATA | H16: 2 | I16: =+Tabla_master_rend[[#This Row],[L_Leche_ent]]+Tabla_master_rend[[#This Row],[L_desn_ext]]+Tabla_master_rend[[#This Row],[L_cabra]]+Tabla_master_rend[[#This Row],[L_oveja]] -> 24376 | J16: 24376 | K16: 0.0356 | L16: 0.0329 | M16: =0.93*K16+0.74*L16+0.048 -> 0.105454 | N16: SI | O16: 0 | P16: 0 | Q16: 0 | R16: 671 | T16: 27180 | U16: =+Tabla_master_rend[[#This Row],[L_suero Total]]/Tabla_master_rend[[#This Row],[Litros_Leche_Total]] -> 1.1150312 | V16: 0.0034 | W16: 0.0089 | X16: =70226/(27180+41820)*27180 -> 27662.937 | Y16: =20219/(27180+41820)*27180 -> 7964.5278 | Z16: =IF(Tabla_master_rend[[#This Row],[L_suero para con]]=0,0,+Tabla_master_rend[[#This Row],[L_suero para con]]/Tabla_master_rend[[#This Row],[L_suero_con]]) -> 3.4732677 | AA16: =+Tabla_master_rend[[#This Row],[L_suero Total]]-Tabla_master_rend[[#This Row],[L_suero para con]] -> -482.93739 | AI16: =+Tabla_master_rend[[#This Row],[Kg_Finos]]+Tabla_master_rend[[#This Row],[Kg_Llenadora]]+Tabla_master_rend[[#This Row],[Kg_Desmoldeo]]+Tabla_master_rend[[#This Row],[L_Agua]]+Tabla_master_rend[[#This Row],[Kg_SalidaSecadero]] -> 2491.6291 | AJ16: =+Tabla_master_rend[[#This Row],[Litros_Leche_Total]]/Tabla_master_rend[[#This Row],[Kg_Queso_Blan]] -> 9.7831577 | AK16: =+Tabla_master_rend[[#This Row],[Litros_Leche_Total]]/(Tabla_master_rend[[#This Row],[Kg_Queso_Blan]]-Tabla_master_rend[[#This Row],[Merma_TOT]]) -> 10.184419 | AL16: =VLOOKUP(G16,REND_TARGET[#All],8,FALSE) -> 10.141625 | AM16: =(I16*1.03*Tabla_master_rend[[#This Row],[%MG_Leche]])+(I16*1.03*Tabla_master_rend[[#This Row],[%MP_Leche]]) -> 1719.8487 | AN16: 0.2552 | AO16: 0.2528 | AP16: 0.4498 | AQ16: =+Tabla_master_rend[[#This Row],[Kg_Queso_Blan]]*Tabla_master_rend[[#This Row],[ES_QUESO]]/(Tabla_master_rend[[#This Row],[Kg_Solidos_leche]]) -> 0.6516473 | AR16: =R16*0.4 -> 268.4 | AS16: =+(Tabla_master_rend[[#This Row],[Kg_Queso_Blan]]*Tabla_master_rend[[#This Row],[%MG_QUESO]]+(Tabla_master_rend[[#This Row],[Kg_MG_Nata]]))/(Tabla_master_rend[[#This Row],[Litros_Leche_Total]]*1.03*Tabla_master_rend[[#This Row],[%MG_Leche]]) -> 1.0116853 | AT16: =+Tabla_master_rend[[#This Row],[Kg_Queso_Blan]]*Tabla_master_rend[[#This Row],[%PT_QUESO]]/(Tabla_master_rend[[#This Row],[Litros_Leche_Total]]*1.03*Tabla_master_rend[[#This Row],[%MP_Leche]]) -> 0.76254397 | AU16: =AR16*$CO$3 -> 2013 | AV16: 5.1290595 | AW16: 44 | AX16: 5.5 | AY16: =SUM(Tabla_master_rend[[#This Row],[Kg_Finos]:[Kg_Desmoldeo]]) -> 54.629059 | AZ16: =+(Tabla_master_rend[[#This Row],[Kg_Finos]]+Tabla_master_rend[[#This Row],[Kg_Llenadora]]+Tabla_master_rend[[#This Row],[Kg_Desmoldeo]])/(Tabla_master_rend[[#This Row],[Kg_Queso_Blan]]) -> 0.021925037 | BA16: 30 | BB16: =+Tabla_master_rend[[#This Row],[L_Agua]]/(Tabla_master_rend[[#This Row],[L_Agua]]+Tabla_master_rend[[#This Row],[Kg_SalidaSecadero]]) -> 0.012310217 | BC16: 321 | BD16: 312 | BE16: 2371 | BF16: 0 | BG16: 0 | BH16: 0 | BI16: 0 | BJ16: 28 | BK16: 2407 | BL16: 0 | BM16: 0 | BN16: 13.54 | BO16: =+SUM(Tabla_master_rend[[#This Row],[B_altas]:[B_lab]])/Tabla_master_rend[[#This Row],[Kg_SalidaSecadero]] -> 0.011632738 | BP16: =+(Tabla_master_rend[[#This Row],[Kg_mer_env_real]]+Tabla_master_rend[[#This Row],[kg_mer_lab_real]])/Tabla_master_rend[[#This Row],[Kg_SalidaSecadero]] -> 0.0056252597 | BQ16: =+Tabla_master_rend[[#This Row],[Merma_TOT]]/Tabla_master_rend[[#This Row],[Kg_Queso_Blan]] -> 0.039399548 | BR16: =+Tabla_master_rend[[#This Row],[kg_mer_lab_real]]+Tabla_master_rend[[#This Row],[Kg_mer_env_real]]+Tabla_master_rend[[#This Row],[Kg_rebaba]]+Tabla_master_rend[[#This Row],[L_Agua]]+Tabla_master_rend[[#This Row],[Kg_Desmoldeo]]+Tabla_master_rend[[#This Row],[Kg_Llenadora]]+Tabla_master_rend[[#This Row],[Kg_Finos]] -> 98.169059 | BT16: =IF(+Tabla_master_rend[[#This Row],[Kg_Env_Total]]=0,0,Tabla_master_rend[[#This Row],[Kg_Env_Total]]-Tabla_master_rend[[#This Row],[Kg_SalidaSecadero]]) -> 0 | BU16: =+Tabla_master_rend[[#This Row],[Diferencia_Env_vs_Sec_kg]]/Tabla_master_rend[[#This Row],[Kg_SalidaSecadero]] -> 0 | BV16: =IFERROR(Tabla_master_rend[[#This Row],[Litros_Leche_Total]]*SUMIFS(tbl_PrecioLeche[PMV_eur_L],tbl_PrecioLeche[AñoMes],TEXT(Tabla_master_rend[[#This Row],[Fecha]],"yyyy-mm"),tbl_PrecioLeche[Tipo_Leche],Tabla_master_rend[[#This Row],[Tipo_Leche]]),"") -> 0 | BW16: =+(Tabla_master_rend[[#This Row],[Coste_Leche_€]]-Tabla_master_rend[[#This Row],[Kg_MG_Nata]]*$CO$3)/Tabla_master_rend[[#This Row],[Kg_Queso_Blan]] -> -0.80790517 | BX16: =SUM(Tabla_master_rend[[#This Row],[Kg_Finos]:[Kg_Desmoldeo]])+Tabla_master_rend[[#This Row],[L_Agua]]+SUM(Tabla_master_rend[[#This Row],[B_altas]:[B_lab]]) -> 112.62906 | BY16: =+BX16-Tabla_master_rend[[#This Row],[Merma_TOT]] -> 14.46 | BZ16: =+BY16/BX16 -> 0.12838605 | CA16: =+Tabla_master_rend[[#This Row],[Kg_Queso_Blan]]*$CA$1 -> 16.195589 | CB16: =+Tabla_master_rend[[#This Row],[Kg_Queso_Blan]]*($CB$1-$CA$1) -> 8.7207017 | CC16: =+(Tabla_master_rend[[#This Row],[Kg_Queso_Blan]]-CA16-CB16)*$CC$1 -> 25.900484 | CD16: =+CA16+CB16+CC16 -> 50.816775 | CE16: =+CD16/Tabla_master_rend[[#This Row],[Kg_Queso_Blan]] -> 0.020395 | CF16: =+Tabla_master_rend[[#This Row],[Merma_TOT]]/Tabla_master_rend[[#This Row],[Kg_Queso_Blan]] -> 0.039399548 | CG16: =CD16-Tabla_master_rend[[#This Row],[Merma_TOT]] -> -47.352285 | CH16: {=-BR16 * IFERROR(INDEX('Precio Leche_EBITDA_Ventas'!$BD$87:$BD$110,MATCH(1,('Precio Leche_EBITDA_Ventas'!$AZ$87:$AZ$110=YEAR(A16))*('Precio Leche_EBITDA_Ventas'!$BB$87:$BB$110=C16),0)),1.3)} -> -343.59171 | CI16: =+CG16*$CM$2 -> -61.55797 | CK16: Venta Kg Q Ok | CM16: 4.775 | CO16: 7.5
A17: 45687 | B17: 1 | C17: =+UPPER(TEXT(Tabla_master_rend[[#This Row],[Fecha]],"MMM")) -> ENE | D17: =+UPPER(TEXT(Tabla_master_rend[[#This Row],[Fecha]],"ddd")) -> JU | E17: 0300125146 | F17: VACA | G17: CREMOSO | H17: 13 | I17: =+Tabla_master_rend[[#This Row],[L_Leche_ent]]+Tabla_master_rend[[#This Row],[L_desn_ext]]+Tabla_master_rend[[#This Row],[L_cabra]]+Tabla_master_rend[[#This Row],[L_oveja]] -> 211266 | J17: 211266 | K17: 0.0357 | L17: 0.0339 | M17: =0.93*K17+0.74*L17+0.048 -> 0.106287 | N17: SI | O17: 0 | P17: 0 | Q17: 0 | R17: 664 | T17: 178460 | U17: =+Tabla_master_rend[[#This Row],[L_suero Total]]/Tabla_master_rend[[#This Row],[Litros_Leche_Total]] -> 0.84471709 | V17: 0.0034 | W17: 0.01 | X17: 179167 | Y17: 59574 | Z17: =IF(Tabla_master_rend[[#This Row],[L_suero para con]]=0,0,+Tabla_master_rend[[#This Row],[L_suero para con]]/Tabla_master_rend[[#This Row],[L_suero_con]]) -> 3.0074697 | AA17: =+Tabla_master_rend[[#This Row],[L_suero Total]]-Tabla_master_rend[[#This Row],[L_suero para con]] -> -707 | AI17: =+Tabla_master_rend[[#This Row],[Kg_Finos]]+Tabla_master_rend[[#This Row],[Kg_Llenadora]]+Tabla_master_rend[[#This Row],[Kg_Desmoldeo]]+Tabla_master_rend[[#This Row],[L_Agua]]+Tabla_master_rend[[#This Row],[Kg_SalidaSecadero]] -> 24555.6 | AJ17: =+Tabla_master_rend[[#This Row],[Litros_Leche_Total]]/Tabla_master_rend[[#This Row],[Kg_Queso_Blan]] -> 8.6035772 | AK17: =+Tabla_master_rend[[#This Row],[Litros_Leche_Total]]/(Tabla_master_rend[[#This Row],[Kg_Queso_Blan]]-Tabla_master_rend[[#This Row],[Merma_TOT]]) -> 9.2218001 | AL17: =VLOOKUP(G17,REND_TARGET[#All],8,FALSE) -> 8.933873 | AM17: =(I17*1.03*Tabla_master_rend[[#This Row],[%MG_Leche]])+(I17*1.03*Tabla_master_rend[[#This Row],[%MP_Leche]]) -> 15145.237 | AN17: 0.2991 | AO17: 0.2301 | AP17: 0.5767 | AQ17: =+Tabla_master_rend[[#This Row],[Kg_Queso_Blan]]*Tabla_master_rend[[#This Row],[ES_QUESO]]/(Tabla_master_rend[[#This Row],[Kg_Solidos_leche]]) -> 0.93502759 | AR17: =R17*0.4 -> 265.6 | AS17: =+(Tabla_master_rend[[#This Row],[Kg_Queso_Blan]]*Tabla_master_rend[[#This Row],[%MG_QUESO]]+(Tabla_master_rend[[#This Row],[Kg_MG_Nata]]))/(Tabla_master_rend[[#This Row],[Litros_Leche_Total]]*1.03*Tabla_master_rend[[#This Row],[%MG_Leche]]) -> 0.97962504 | AT17: =+Tabla_master_rend[[#This Row],[Kg_Queso_Blan]]*Tabla_master_rend[[#This Row],[%PT_QUESO]]/(Tabla_master_rend[[#This Row],[Litros_Leche_Total]]*1.03*Tabla_master_rend[[#This Row],[%MP_Leche]]) -> 0.76595038 | AU17: =AR17*$CO$3 -> 1992 | AV17: 91 | AW17: 141.3 | AX17: 95.3 | AY17: =SUM(Tabla_master_rend[[#This Row],[Kg_Finos]:[Kg_Desmoldeo]]) -> 327.6 | AZ17: =+(Tabla_master_rend[[#This Row],[Kg_Finos]]+Tabla_master_rend[[#This Row],[Kg_Llenadora]]+Tabla_master_rend[[#This Row],[Kg_Desmoldeo]])/(Tabla_master_rend[[#This Row],[Kg_Queso_Blan]]) -> 0.013341152 | BA17: 650 | BB17: =+Tabla_master_rend[[#This Row],[L_Agua]]/(Tabla_master_rend[[#This Row],[L_Agua]]+Tabla_master_rend[[#This Row],[Kg_SalidaSecadero]]) -> 0.026828463 | BC17: 3449 | BD17: 3255 | BE17: 22965 | BF17: =33*6.6 -> 217.8 | BG17: =11*6.6 -> 72.6 | BH17: =5*6.6 -> 33 | BI17: =164*6.6 -> 1082.4 | BJ17: 81 | BK17: 23578 | BL17: 0.53 | BM17: 650.4 | BN17: 17.66 | BO17: =+SUM(Tabla_master_rend[[#This Row],[B_altas]:[B_lab]])/Tabla_master_rend[[#This Row],[Kg_SalidaSecadero]] -> 0.063058784 | BP17: =+(Tabla_master_rend[[#This Row],[Kg_mer_env_real]]+Tabla_master_rend[[#This Row],[kg_mer_lab_real]])/Tabla_master_rend[[#This Row],[Kg_SalidaSecadero]] -> 0.02833404 | BQ17: =+Tabla_master_rend[[#This Row],[Merma_TOT]]/Tabla_master_rend[[#This Row],[Kg_Queso_Blan]] -> 0.06703929 | BR17: =+Tabla_master_rend[[#This Row],[kg_mer_lab_real]]+Tabla_master_rend[[#This Row],[Kg_mer_env_real]]+Tabla_master_rend[[#This Row],[Kg_rebaba]]+Tabla_master_rend[[#This Row],[L_Agua]]+Tabla_master_rend[[#This Row],[Kg_Desmoldeo]]+Tabla_master_rend[[#This Row],[Kg_Llenadora]]+Tabla_master_rend[[#This Row],[Kg_Finos]] -> 1646.19 | BT17: =IF(+Tabla_master_rend[[#This Row],[Kg_Env_Total]]=0,0,Tabla_master_rend[[#This Row],[Kg_Env_Total]]-Tabla_master_rend[[#This Row],[Kg_SalidaSecadero]]) -> 0 | BU17: =+Tabla_master_rend[[#This Row],[Diferencia_Env_vs_Sec_kg]]/Tabla_master_rend[[#This Row],[Kg_SalidaSecadero]] -> 0 | BV17: =IFERROR(Tabla_master_rend[[#This Row],[Litros_Leche_Total]]*SUMIFS(tbl_PrecioLeche[PMV_eur_L],tbl_PrecioLeche[AñoMes],TEXT(Tabla_master_rend[[#This Row],[Fecha]],"yyyy-mm"),tbl_PrecioLeche[Tipo_Leche],Tabla_master_rend[[#This Row],[Tipo_Leche]]),"") -> 0 | BW17: =+(Tabla_master_rend[[#This Row],[Coste_Leche_€]]-Tabla_master_rend[[#This Row],[Kg_MG_Nata]]*$CO$3)/Tabla_master_rend[[#This Row],[Kg_Queso_Blan]] -> -0.081122025 | BX17: =SUM(Tabla_master_rend[[#This Row],[Kg_Finos]:[Kg_Desmoldeo]])+Tabla_master_rend[[#This Row],[L_Agua]]+SUM(Tabla_master_rend[[#This Row],[B_altas]:[B_lab]]) -> 2464.4 | BY17: =+BX17-Tabla_master_rend[[#This Row],[Merma_TOT]] -> 818.21 | BZ17: =+BY17/BX17 -> 0.33201185 | CA17: =+Tabla_master_rend[[#This Row],[Kg_Queso_Blan]]*$CA$1 -> 159.6114 | CB17: =+Tabla_master_rend[[#This Row],[Kg_Queso_Blan]]*($CB$1-$CA$1) -> 85.9446 | CC17: =+(Tabla_master_rend[[#This Row],[Kg_Queso_Blan]]-CA17-CB17)*$CC$1 -> 255.25546 | CD17: =+CA17+CB17+CC17 -> 500.81146 | CE17: =+CD17/Tabla_master_rend[[#This Row],[Kg_Queso_Blan]] -> 0.020395 | CF17: =+Tabla_master_rend[[#This Row],[Merma_TOT]]/Tabla_master_rend[[#This Row],[Kg_Queso_Blan]] -> 0.06703929 | CG17: =CD17-Tabla_master_rend[[#This Row],[Merma_TOT]] -> -1145.3785 | CH17: {=-BR17 * IFERROR(INDEX('Precio Leche_EBITDA_Ventas'!$BD$87:$BD$110,MATCH(1,('Precio Leche_EBITDA_Ventas'!$AZ$87:$AZ$110=YEAR(A17))*('Precio Leche_EBITDA_Ventas'!$BB$87:$BB$110=C17),0)),1.3)} -> -5761.665 | CI17: =+CG17*$CM$2 -> -1488.9921 | CK17: Venta kg Merma | CM17: 3.475
A18: 45691 | B18: 2 | C18: =+UPPER(TEXT(Tabla_master_rend[[#This Row],[Fecha]],"MMM")) -> FEB | D18: =+UPPER(TEXT(Tabla_master_rend[[#This Row],[Fecha]],"ddd")) -> LU | E18: 030225116 | F18: VACA | G18: EDAM_F | H18: 17 | I18: =+Tabla_master_rend[[#This Row],[L_Leche_ent]]+Tabla_master_rend[[#This Row],[L_desn_ext]]+Tabla_master_rend[[#This Row],[L_cabra]]+Tabla_master_rend[[#This Row],[L_oveja]] -> 279824 | J18: 279824 | K18: 0.0371 | L18: 0.0335 | M18: =0.93*K18+0.74*L18+0.048 -> 0.107293 | N18: NO | O18: 0 | P18: 0 | Q18: 0 | R18: 8821 | T18: 233970 | U18: =+Tabla_master_rend[[#This Row],[L_suero Total]]/Tabla_master_rend[[#This Row],[Litros_Leche_Total]] -> 0.83613271 | V18: 0.001 | W18: 0.0093 | X18: 234233 | Y18: 74923 | Z18: =IF(Tabla_master_rend[[#This Row],[L_suero para con]]=0,0,+Tabla_master_rend[[#This Row],[L_suero para con]]/Tabla_master_rend[[#This Row],[L_suero_con]]) -> 3.1263164 | AA18: =+Tabla_master_rend[[#This Row],[L_suero Total]]-Tabla_master_rend[[#This Row],[L_suero para con]] -> -263 | AI18: =+Tabla_master_rend[[#This Row],[Kg_Finos]]+Tabla_master_rend[[#This Row],[Kg_Llenadora]]+Tabla_master_rend[[#This Row],[Kg_Desmoldeo]]+Tabla_master_rend[[#This Row],[L_Agua]]+Tabla_master_rend[[#This Row],[Kg_SalidaSecadero]] -> 30123.31 | AJ18: =+Tabla_master_rend[[#This Row],[Litros_Leche_Total]]/Tabla_master_rend[[#This Row],[Kg_Queso_Blan]] -> 9.2892846 | AK18: =+Tabla_master_rend[[#This Row],[Litros_Leche_Total]]/(Tabla_master_rend[[#This Row],[Kg_Queso_Blan]]-Tabla_master_rend[[#This Row],[Merma_TOT]]) -> 9.6976653 | AL18: =VLOOKUP(G18,REND_TARGET[#All],8,FALSE) -> 9.80785 | AM18: =(I18*1.03*Tabla_master_rend[[#This Row],[%MG_Leche]])+(I18*1.03*Tabla_master_rend[[#This Row],[%MP_Leche]]) -> 20348.242 | AN18: 0.2261 | AO18: 0.2468 | AP18: 0.5295 | AQ18: =+Tabla_master_rend[[#This Row],[Kg_Queso_Blan]]*Tabla_master_rend[[#This Row],[ES_QUESO]]/(Tabla_master_rend[[#This Row],[Kg_Solidos_leche]]) -> 0.7838659 | AR18: =R18*0.4 -> 3528.4 | AS18: =+(Tabla_master_rend[[#This Row],[Kg_Queso_Blan]]*Tabla_master_rend[[#This Row],[%MG_QUESO]]+(Tabla_master_rend[[#This Row],[Kg_MG_Nata]]))/(Tabla_master_rend[[#This Row],[Litros_Leche_Total]]*1.03*Tabla_master_rend[[#This Row],[%MG_Leche]]) -> 0.96692818 | AT18: =+Tabla_master_rend[[#This Row],[Kg_Queso_Blan]]*Tabla_master_rend[[#This Row],[%PT_QUESO]]/(Tabla_master_rend[[#This Row],[Litros_Leche_Total]]*1.03*Tabla_master_rend[[#This Row],[%MP_Leche]]) -> 0.7699825 | AU18: =AR18*$CO$3 -> 26463 | AV18: 55.41 | AW18: 97.7 | AX18: 170.2 | AY18: =SUM(Tabla_master_rend[[#This Row],[Kg_Finos]:[Kg_Desmoldeo]]) -> 323.31 | AZ18: =+(Tabla_master_rend[[#This Row],[Kg_Finos]]+Tabla_master_rend[[#This Row],[Kg_Llenadora]]+Tabla_master_rend[[#This Row],[Kg_Desmoldeo]])/(Tabla_master_rend[[#This Row],[Kg_Queso_Blan]]) -> 0.010732884 | BA18: 525 | BB18: =+Tabla_master_rend[[#This Row],[L_Agua]]/(Tabla_master_rend[[#This Row],[L_Agua]]+Tabla_master_rend[[#This Row],[Kg_SalidaSecadero]]) -> 0.01761745 | BC18: 4229 | BD18: 3930 | BE18: 27978 | BF18: =2*6.1 -> 12.2 | BG18: =82*6.1 -> 500.2 | BH18: 0 | BI18: =203*6.1 -> 1238.3 | BJ18: 82 | BK18: 29275 | BL18: 8 | BM18: 397.58 | BN18: 14.64 | BO18: =+SUM(Tabla_master_rend[[#This Row],[B_altas]:[B_lab]])/Tabla_master_rend[[#This Row],[Kg_SalidaSecadero]] -> 0.062602904 | BP18: =+(Tabla_master_rend[[#This Row],[Kg_mer_env_real]]+Tabla_master_rend[[#This Row],[kg_mer_lab_real]])/Tabla_master_rend[[#This Row],[Kg_SalidaSecadero]] -> 0.014080956 | BQ18: =+Tabla_master_rend[[#This Row],[Merma_TOT]]/Tabla_master_rend[[#This Row],[Kg_Queso_Blan]] -> 0.042111242 | BR18: =+Tabla_master_rend[[#This Row],[kg_mer_lab_real]]+Tabla_master_rend[[#This Row],[Kg_mer_env_real]]+Tabla_master_rend[[#This Row],[Kg_rebaba]]+Tabla_master_rend[[#This Row],[L_Agua]]+Tabla_master_rend[[#This Row],[Kg_Desmoldeo]]+Tabla_master_rend[[#This Row],[Kg_Llenadora]]+Tabla_master_rend[[#This Row],[Kg_Finos]] -> 1268.53 | BT18: =IF(+Tabla_master_rend[[#This Row],[Kg_Env_Total]]=0,0,Tabla_master_rend[[#This Row],[Kg_Env_Total]]-Tabla_master_rend[[#This Row],[Kg_SalidaSecadero]]) -> 0 | BU18: =+Tabla_master_rend[[#This Row],[Diferencia_Env_vs_Sec_kg]]/Tabla_master_rend[[#This Row],[Kg_SalidaSecadero]] -> 0 | BV18: =IFERROR(Tabla_master_rend[[#This Row],[Litros_Leche_Total]]*SUMIFS(tbl_PrecioLeche[PMV_eur_L],tbl_PrecioLeche[AñoMes],TEXT(Tabla_master_rend[[#This Row],[Fecha]],"yyyy-mm"),tbl_PrecioLeche[Tipo_Leche],Tabla_master_rend[[#This Row],[Tipo_Leche]]),"") -> 0 | BW18: =+(Tabla_master_rend[[#This Row],[Coste_Leche_€]]-Tabla_master_rend[[#This Row],[Kg_MG_Nata]]*$CO$3)/Tabla_master_rend[[#This Row],[Kg_Queso_Blan]] -> -0.87848912 | BX18: =SUM(Tabla_master_rend[[#This Row],[Kg_Finos]:[Kg_Desmoldeo]])+Tabla_master_rend[[#This Row],[L_Agua]]+SUM(Tabla_master_rend[[#This Row],[B_altas]:[B_lab]]) -> 2681.01 | BY18: =+BX18-Tabla_master_rend[[#This Row],[Merma_TOT]] -> 1412.48 | BZ18: =+BY18/BX18 -> 0.52684623 | CA18: =+Tabla_master_rend[[#This Row],[Kg_Queso_Blan]]*$CA$1 -> 195.80151 | CB18: =+Tabla_master_rend[[#This Row],[Kg_Queso_Blan]]*($CB$1-$CA$1) -> 105.43159 | CC18: =+(Tabla_master_rend[[#This Row],[Kg_Queso_Blan]]-CA18-CB18)*$CC$1 -> 313.13181 | CD18: =+CA18+CB18+CC18 -> 614.36491 | CE18: =+CD18/Tabla_master_rend[[#This Row],[Kg_Queso_Blan]] -> 0.020395 | CF18: =+Tabla_master_rend[[#This Row],[Merma_TOT]]/Tabla_master_rend[[#This Row],[Kg_Queso_Blan]] -> 0.042111242 | CG18: =CD18-Tabla_master_rend[[#This Row],[Merma_TOT]] -> -654.16509 | CH18: {=-BR18 * IFERROR(INDEX('Precio Leche_EBITDA_Ventas'!$BD$87:$BD$110,MATCH(1,('Precio Leche_EBITDA_Ventas'!$AZ$87:$AZ$110=YEAR(A18))*('Precio Leche_EBITDA_Ventas'!$BB$87:$BB$110=C18),0)),1.3)} -> -4439.855 | CI18: =+CG18*$CM$2 -> -850.41462
A19: 45694 | B19: 2 | C19: =+UPPER(TEXT(Tabla_master_rend[[#This Row],[Fecha]],"MMM")) -> FEB | D19: =+UPPER(TEXT(Tabla_master_rend[[#This Row],[Fecha]],"ddd")) -> JU | E19: 060225146 | F19: VACA | G19: CREMOSO | H19: 17 | I19: =+Tabla_master_rend[[#This Row],[L_Leche_ent]]+Tabla_master_rend[[#This Row],[L_desn_ext]]+Tabla_master_rend[[#This Row],[L_cabra]]+Tabla_master_rend[[#This Row],[L_oveja]] -> 283132 | J19: 283132 | K19: 0.0388 | L19: 0.0339 | M19: =0.93*K19+0.74*L19+0.048 -> 0.10917 | N19: SI | O19: 0 | P19: 0 | Q19: 0 | R19: 3429 | T19: 235260 | U19: =+Tabla_master_rend[[#This Row],[L_suero Total]]/Tabla_master_rend[[#This Row],[Litros_Leche_Total]] -> 0.83091985 | V19: 0.0025 | W19: 0.0093 | X19: 105845 | Y19: 28385 | Z19: =IF(Tabla_master_rend[[#This Row],[L_suero para con]]=0,0,+Tabla_master_rend[[#This Row],[L_suero para con]]/Tabla_master_rend[[#This Row],[L_suero_con]]) -> 3.7289061 | AA19: =+Tabla_master_rend[[#This Row],[L_suero Total]]-Tabla_master_rend[[#This Row],[L_suero para con]] -> 129415 | AI19: =+Tabla_master_rend[[#This Row],[Kg_Finos]]+Tabla_master_rend[[#This Row],[Kg_Llenadora]]+Tabla_master_rend[[#This Row],[Kg_Desmoldeo]]+Tabla_master_rend[[#This Row],[L_Agua]]+Tabla_master_rend[[#This Row],[Kg_SalidaSecadero]] -> 33189.44 | AJ19: =+Tabla_master_rend[[#This Row],[Litros_Leche_Total]]/Tabla_master_rend[[#This Row],[Kg_Queso_Blan]] -> 8.5307857 | AK19: =+Tabla_master_rend[[#This Row],[Litros_Leche_Total]]/(Tabla_master_rend[[#This Row],[Kg_Queso_Blan]]-Tabla_master_rend[[#This Row],[Merma_TOT]]) -> 8.9110684 | AL19: =VLOOKUP(G19,REND_TARGET[#All],8,FALSE) -> 8.933873 | AM19: =(I19*1.03*Tabla_master_rend[[#This Row],[%MG_Leche]])+(I19*1.03*Tabla_master_rend[[#This Row],[%MP_Leche]]) -> 21201.207 | AN19: 0.292 | AO19: 0.228 | AP19: 0.5711 | AQ19: =+Tabla_master_rend[[#This Row],[Kg_Queso_Blan]]*Tabla_master_rend[[#This Row],[ES_QUESO]]/(Tabla_master_rend[[#This Row],[Kg_Solidos_leche]]) -> 0.89402877 | AR19: =R19*0.4 -> 1371.6 | AS19: =+(Tabla_master_rend[[#This Row],[Kg_Queso_Blan]]*Tabla_master_rend[[#This Row],[%MG_QUESO]]+(Tabla_master_rend[[#This Row],[Kg_MG_Nata]]))/(Tabla_master_rend[[#This Row],[Litros_Leche_Total]]*1.03*Tabla_master_rend[[#This Row],[%MG_Leche]]) -> 0.97771376 | AT19: =+Tabla_master_rend[[#This Row],[Kg_Queso_Blan]]*Tabla_master_rend[[#This Row],[%PT_QUESO]]/(Tabla_master_rend[[#This Row],[Litros_Leche_Total]]*1.03*Tabla_master_rend[[#This Row],[%MP_Leche]]) -> 0.76543601 | AU19: =AR19*$CO$3 -> 10287 | AV19: 67.44 | AW19: 105.2 | AX19: 31.8 | AY19: =SUM(Tabla_master_rend[[#This Row],[Kg_Finos]:[Kg_Desmoldeo]]) -> 204.44 | AZ19: =+(Tabla_master_rend[[#This Row],[Kg_Finos]]+Tabla_master_rend[[#This Row],[Kg_Llenadora]]+Tabla_master_rend[[#This Row],[Kg_Desmoldeo]])/(Tabla_master_rend[[#This Row],[Kg_Queso_Blan]]) -> 0.0061597906 | BA19: 890 | BB19: =+Tabla_master_rend[[#This Row],[L_Agua]]/(Tabla_master_rend[[#This Row],[L_Agua]]+Tabla_master_rend[[#This Row],[Kg_SalidaSecadero]]) -> 0.026981961 | BC19: 4609 | BD19: 4509 | BE19: 32307 | BF19: =48*6.8 -> 326.4 | BG19: =10*6.8 -> 68 | BH19: =7*6.8 -> 47.6 | BI19: =68*6.8 -> 462.4 | BJ19: 99 | BK19: 32095 | BL19: 3.04 | BM19: 302.79 | BN19: 16.1 | BO19: =+SUM(Tabla_master_rend[[#This Row],[B_altas]:[B_lab]])/Tabla_master_rend[[#This Row],[Kg_SalidaSecadero]] -> 0.031263437 | BP19: =+(Tabla_master_rend[[#This Row],[Kg_mer_env_real]]+Tabla_master_rend[[#This Row],[kg_mer_lab_real]])/Tabla_master_rend[[#This Row],[Kg_SalidaSecadero]] -> 0.0099358155 | BQ19: =+Tabla_master_rend[[#This Row],[Merma_TOT]]/Tabla_master_rend[[#This Row],[Kg_Queso_Blan]] -> 0.042675321 | BR19: =+Tabla_master_rend[[#This Row],[kg_mer_lab_real]]+Tabla_master_rend[[#This Row],[Kg_mer_env_real]]+Tabla_master_rend[[#This Row],[Kg_rebaba]]+Tabla_master_rend[[#This Row],[L_Agua]]+Tabla_master_rend[[#This Row],[Kg_Desmoldeo]]+Tabla_master_rend[[#This Row],[Kg_Llenadora]]+Tabla_master_rend[[#This Row],[Kg_Finos]] -> 1416.37 | BT19: =IF(+Tabla_master_rend[[#This Row],[Kg_Env_Total]]=0,0,Tabla_master_rend[[#This Row],[Kg_Env_Total]]-Tabla_master_rend[[#This Row],[Kg_SalidaSecadero]]) -> 0 | BU19: =+Tabla_master_rend[[#This Row],[Diferencia_Env_vs_Sec_kg]]/Tabla_master_rend[[#This Row],[Kg_SalidaSecadero]] -> 0 | BV19: =IFERROR(Tabla_master_rend[[#This Row],[Litros_Leche_Total]]*SUMIFS(tbl_PrecioLeche[PMV_eur_L],tbl_PrecioLeche[AñoMes],TEXT(Tabla_master_rend[[#This Row],[Fecha]],"yyyy-mm"),tbl_PrecioLeche[Tipo_Leche],Tabla_master_rend[[#This Row],[Tipo_Leche]]),"") -> 0 | BW19: =+(Tabla_master_rend[[#This Row],[Coste_Leche_€]]-Tabla_master_rend[[#This Row],[Kg_MG_Nata]]*$CO$3)/Tabla_master_rend[[#This Row],[Kg_Queso_Blan]] -> -0.30994798 | BX19: =SUM(Tabla_master_rend[[#This Row],[Kg_Finos]:[Kg_Desmoldeo]])+Tabla_master_rend[[#This Row],[L_Agua]]+SUM(Tabla_master_rend[[#This Row],[B_altas]:[B_lab]]) -> 2097.84 | BY19: =+BX19-Tabla_master_rend[[#This Row],[Merma_TOT]] -> 681.47 | BZ19: =+BY19/BX19 -> 0.32484365 | CA19: =+Tabla_master_rend[[#This Row],[Kg_Queso_Blan]]*$CA$1 -> 215.73136 | CB19: =+Tabla_master_rend[[#This Row],[Kg_Queso_Blan]]*($CB$1-$CA$1) -> 116.16304 | CC19: =+(Tabla_master_rend[[#This Row],[Kg_Queso_Blan]]-CA19-CB19)*$CC$1 -> 345.00423 | CD19: =+CA19+CB19+CC19 -> 676.89863 | CE19: =+CD19/Tabla_master_rend[[#This Row],[Kg_Queso_Blan]] -> 0.020395 | CF19: =+Tabla_master_rend[[#This Row],[Merma_TOT]]/Tabla_master_rend[[#This Row],[Kg_Queso_Blan]] -> 0.042675321 | CG19: =CD19-Tabla_master_rend[[#This Row],[Merma_TOT]] -> -739.47137 | CH19: {=-BR19 * IFERROR(INDEX('Precio Leche_EBITDA_Ventas'!$BD$87:$BD$110,MATCH(1,('Precio Leche_EBITDA_Ventas'!$AZ$87:$AZ$110=YEAR(A19))*('Precio Leche_EBITDA_Ventas'!$BB$87:$BB$110=C19),0)),1.3)} -> -4957.295 | CI19: =+CG19*$CM$2 -> -961.31278
A20: 45698 | B20: 2 | C20: =+UPPER(TEXT(Tabla_master_rend[[#This Row],[Fecha]],"MMM")) -> FEB | D20: =+UPPER(TEXT(Tabla_master_rend[[#This Row],[Fecha]],"ddd")) -> LU | E20: 100225026 | F20: VACA | G20: GOUDA | H20: 17 | I20: =+Tabla_master_rend[[#This Row],[L_Leche_ent]]+Tabla_master_rend[[#This Row],[L_desn_ext]]+Tabla_master_rend[[#This Row],[L_cabra]]+Tabla_master_rend[[#This Row],[L_oveja]] -> 248425 | J20: 248425 | K20: 0.0384 | L20: 0.034 | M20: =0.93*K20+0.74*L20+0.048 -> 0.108872 | N20: NO | O20: 0 | P20: 0 | Q20: 0 | R20: 1992 | T20: 233200 | U20: =+Tabla_master_rend[[#This Row],[L_suero Total]]/Tabla_master_rend[[#This Row],[Litros_Leche_Total]] -> 0.9387139 | V20: 0.0026 | W20: 0.0095 | X20: 145497 | Y20: 44646 | Z20: =IF(Tabla_master_rend[[#This Row],[L_suero para con]]=0,0,+Tabla_master_rend[[#This Row],[L_suero para con]]/Tabla_master_rend[[#This Row],[L_suero_con]]) -> 3.2589034 | AA20: =+Tabla_master_rend[[#This Row],[L_suero Total]]-Tabla_master_rend[[#This Row],[L_suero para con]] -> 87703 | AI20: =+Tabla_master_rend[[#This Row],[Kg_Finos]]+Tabla_master_rend[[#This Row],[Kg_Llenadora]]+Tabla_master_rend[[#This Row],[Kg_Desmoldeo]]+Tabla_master_rend[[#This Row],[L_Agua]]+Tabla_master_rend[[#This Row],[Kg_SalidaSecadero]] -> 31836.87 | AJ20: =+Tabla_master_rend[[#This Row],[Litros_Leche_Total]]/Tabla_master_rend[[#This Row],[Kg_Queso_Blan]] -> 7.8030598 | AK20: =+Tabla_master_rend[[#This Row],[Litros_Leche_Total]]/(Tabla_master_rend[[#This Row],[Kg_Queso_Blan]]-Tabla_master_rend[[#This Row],[Merma_TOT]]) -> 8.0650371 | AL20: =VLOOKUP(G20,REND_TARGET[#All],8,FALSE) -> 8.494317 | AM20: =(I20*1.03*Tabla_master_rend[[#This Row],[%MG_Leche]])+(I20*1.03*Tabla_master_rend[[#This Row],[%MP_Leche]]) -> 18525.549 | AN20: 0.2787 | AO20: 0.222 | AP20: 0.5545 | AQ20: =+Tabla_master_rend[[#This Row],[Kg_Queso_Blan]]*Tabla_master_rend[[#This Row],[ES_QUESO]]/(Tabla_master_rend[[#This Row],[Kg_Solidos_leche]]) -> 0.95292962 | AR20: =R20*0.4 -> 796.8 | AS20: =+(Tabla_master_rend[[#This Row],[Kg_Queso_Blan]]*Tabla_master_rend[[#This Row],[%MG_QUESO]]+(Tabla_master_rend[[#This Row],[Kg_MG_Nata]]))/(Tabla_master_rend[[#This Row],[Litros_Leche_Total]]*1.03*Tabla_master_rend[[#This Row],[%MG_Leche]]) -> 0.98412634 | AT20: =+Tabla_master_rend[[#This Row],[Kg_Queso_Blan]]*Tabla_master_rend[[#This Row],[%PT_QUESO]]/(Tabla_master_rend[[#This Row],[Litros_Leche_Total]]*1.03*Tabla_master_rend[[#This Row],[%MP_Leche]]) -> 0.81240371 | AU20: =AR20*$CO$3 -> 5976 | AV20: 85.17 | AW20: 216 | AX20: 18.7 | AY20: =SUM(Tabla_master_rend[[#This Row],[Kg_Finos]:[Kg_Desmoldeo]]) -> 319.87 | AZ20: =+(Tabla_master_rend[[#This Row],[Kg_Finos]]+Tabla_master_rend[[#This Row],[Kg_Llenadora]]+Tabla_master_rend[[#This Row],[Kg_Desmoldeo]])/(Tabla_master_rend[[#This Row],[Kg_Queso_Blan]]) -> 0.010047156 | BA20: 600 | BB20: =+Tabla_master_rend[[#This Row],[L_Agua]]/(Tabla_master_rend[[#This Row],[L_Agua]]+Tabla_master_rend[[#This Row],[Kg_SalidaSecadero]]) -> 0.019037345 | BC20: 4393 | BD20: 4368 | BE20: 31358 | BF20: =27*6.5 -> 175.5 | BG20: =3*6.5 -> 19.5 | BH20: =5*6.5 -> 32.5 | BI20: =3*6.5 -> 19.5 | BJ20: 88 | BK20: 30917 | BL20: 0 | BM20: 77.95 | BN20: 36.34 | BO20: =+SUM(Tabla_master_rend[[#This Row],[B_altas]:[B_lab]])/Tabla_master_rend[[#This Row],[Kg_SalidaSecadero]] -> 0.010835463 | BP20: =+(Tabla_master_rend[[#This Row],[Kg_mer_env_real]]+Tabla_master_rend[[#This Row],[kg_mer_lab_real]])/Tabla_master_rend[[#This Row],[Kg_SalidaSecadero]] -> 0.0036966717 | BQ20: =+Tabla_master_rend[[#This Row],[Merma_TOT]]/Tabla_master_rend[[#This Row],[Kg_Queso_Blan]] -> 0.032483093 | BR20: =+Tabla_master_rend[[#This Row],[kg_mer_lab_real]]+Tabla_master_rend[[#This Row],[Kg_mer_env_real]]+Tabla_master_rend[[#This Row],[Kg_rebaba]]+Tabla_master_rend[[#This Row],[L_Agua]]+Tabla_master_rend[[#This Row],[Kg_Desmoldeo]]+Tabla_master_rend[[#This Row],[Kg_Llenadora]]+Tabla_master_rend[[#This Row],[Kg_Finos]] -> 1034.16 | BT20: =IF(+Tabla_master_rend[[#This Row],[Kg_Env_Total]]=0,0,Tabla_master_rend[[#This Row],[Kg_Env_Total]]-Tabla_master_rend[[#This Row],[Kg_SalidaSecadero]]) -> 0 | BU20: =+Tabla_master_rend[[#This Row],[Diferencia_Env_vs_Sec_kg]]/Tabla_master_rend[[#This Row],[Kg_SalidaSecadero]] -> 0 | BV20: =IFERROR(Tabla_master_rend[[#This Row],[Litros_Leche_Total]]*SUMIFS(tbl_PrecioLeche[PMV_eur_L],tbl_PrecioLeche[AñoMes],TEXT(Tabla_master_rend[[#This Row],[Fecha]],"yyyy-mm"),tbl_PrecioLeche[Tipo_Leche],Tabla_master_rend[[#This Row],[Tipo_Leche]]),"") -> 0 | BW20: =+(Tabla_master_rend[[#This Row],[Coste_Leche_€]]-Tabla_master_rend[[#This Row],[Kg_MG_Nata]]*$CO$3)/Tabla_master_rend[[#This Row],[Kg_Queso_Blan]] -> -0.18770689 | BX20: =SUM(Tabla_master_rend[[#This Row],[Kg_Finos]:[Kg_Desmoldeo]])+Tabla_master_rend[[#This Row],[L_Agua]]+SUM(Tabla_master_rend[[#This Row],[B_altas]:[B_lab]]) -> 1254.87 | BY20: =+BX20-Tabla_master_rend[[#This Row],[Merma_TOT]] -> 220.71 | BZ20: =+BY20/BX20 -> 0.17588276 | CA20: =+Tabla_master_rend[[#This Row],[Kg_Queso_Blan]]*$CA$1 -> 206.93965 | CB20: =+Tabla_master_rend[[#This Row],[Kg_Queso_Blan]]*($CB$1-$CA$1) -> 111.42905 | CC20: =+(Tabla_master_rend[[#This Row],[Kg_Queso_Blan]]-CA20-CB20)*$CC$1 -> 330.94426 | CD20: =+CA20+CB20+CC20 -> 649.31296 | CE20: =+CD20/Tabla_master_rend[[#This Row],[Kg_Queso_Blan]] -> 0.020395 | CF20: =+Tabla_master_rend[[#This Row],[Merma_TOT]]/Tabla_master_rend[[#This Row],[Kg_Queso_Blan]] -> 0.032483093 | CG20: =CD20-Tabla_master_rend[[#This Row],[Merma_TOT]] -> -384.84704 | CH20: {=-BR20 * IFERROR(INDEX('Precio Leche_EBITDA_Ventas'!$BD$87:$BD$110,MATCH(1,('Precio Leche_EBITDA_Ventas'!$AZ$87:$AZ$110=YEAR(A20))*('Precio Leche_EBITDA_Ventas'!$BB$87:$BB$110=C20),0)),1.3)} -> -3619.56 | CI20: =+CG20*$CM$2 -> -500.30115
A21: 45700 | B21: 2 | C21: =+UPPER(TEXT(Tabla_master_rend[[#This Row],[Fecha]],"MMM")) -> FEB | D21: =+UPPER(TEXT(Tabla_master_rend[[#This Row],[Fecha]],"ddd")) -> MI | E21: 120225026 | F21: VACA | G21: GOUDA | H21: 15 | I21: =+Tabla_master_rend[[#This Row],[L_Leche_ent]]+Tabla_master_rend[[#This Row],[L_desn_ext]]+Tabla_master_rend[[#This Row],[L_cabra]]+Tabla_master_rend[[#This Row],[L_oveja]] -> 218473 | J21: 218473 | K21: 0.0383 | L21: 0.0338 | M21: =0.93*K21+0.74*L21+0.048 -> 0.108631 | N21: SI | O21: 0 | P21: 0 | Q21: 0 | R21: 2169 | T21: 204940 | U21: =+Tabla_master_rend[[#This Row],[L_suero Total]]/Tabla_master_rend[[#This Row],[Litros_Leche_Total]] -> 0.93805642 | V21: 0.0025 | W21: 0.0096 | X21: 120201 | Y21: 39043 | Z21: =IF(Tabla_master_rend[[#This Row],[L_suero para con]]=0,0,+Tabla_master_rend[[#This Row],[L_suero para con]]/Tabla_master_rend[[#This Row],[L_suero_con]]) -> 3.0786825 | AA21: =+Tabla_master_rend[[#This Row],[L_suero Total]]-Tabla_master_rend[[#This Row],[L_suero para con]] -> 84739 | AI21: =+Tabla_master_rend[[#This Row],[Kg_Finos]]+Tabla_master_rend[[#This Row],[Kg_Llenadora]]+Tabla_master_rend[[#This Row],[Kg_Desmoldeo]]+Tabla_master_rend[[#This Row],[L_Agua]]+Tabla_master_rend[[#This Row],[Kg_SalidaSecadero]] -> 28129.55 | AJ21: =+Tabla_master_rend[[#This Row],[Litros_Leche_Total]]/Tabla_master_rend[[#This Row],[Kg_Queso_Blan]] -> 7.7666724 | AK21: =+Tabla_master_rend[[#This Row],[Litros_Leche_Total]]/(Tabla_master_rend[[#This Row],[Kg_Queso_Blan]]-Tabla_master_rend[[#This Row],[Merma_TOT]]) -> 8.0255807 | AL21: =VLOOKUP(G21,REND_TARGET[#All],8,FALSE) -> 8.494317 | AM21: =(I21*1.03*Tabla_master_rend[[#This Row],[%MG_Leche]])+(I21*1.03*Tabla_master_rend[[#This Row],[%MP_Leche]]) -> 16224.46 | AN21: 0.2746 | AO21: 0.2235 | AP21: 0.5515 | AQ21: =+Tabla_master_rend[[#This Row],[Kg_Queso_Blan]]*Tabla_master_rend[[#This Row],[ES_QUESO]]/(Tabla_master_rend[[#This Row],[Kg_Solidos_leche]]) -> 0.95617644 | AR21: =R21*0.4 -> 867.6 | AS21: =+(Tabla_master_rend[[#This Row],[Kg_Queso_Blan]]*Tabla_master_rend[[#This Row],[%MG_QUESO]]+(Tabla_master_rend[[#This Row],[Kg_MG_Nata]]))/(Tabla_master_rend[[#This Row],[Litros_Leche_Total]]*1.03*Tabla_master_rend[[#This Row],[%MG_Leche]]) -> 0.99691747 | AT21: =+Tabla_master_rend[[#This Row],[Kg_Queso_Blan]]*Tabla_master_rend[[#This Row],[%PT_QUESO]]/(Tabla_master_rend[[#This Row],[Litros_Leche_Total]]*1.03*Tabla_master_rend[[#This Row],[%MP_Leche]]) -> 0.82658708 | AU21: =AR21*$CO$3 -> 6507 | AV21: 64.05 | AW21: 153 | AX21: 7.5 | AY21: =SUM(Tabla_master_rend[[#This Row],[Kg_Finos]:[Kg_Desmoldeo]]) -> 224.55 | AZ21: =+(Tabla_master_rend[[#This Row],[Kg_Finos]]+Tabla_master_rend[[#This Row],[Kg_Llenadora]]+Tabla_master_rend[[#This Row],[Kg_Desmoldeo]])/(Tabla_master_rend[[#This Row],[Kg_Queso_Blan]]) -> 0.0079827086 | BA21: 585 | BB21: =+Tabla_master_rend[[#This Row],[L_Agua]]/(Tabla_master_rend[[#This Row],[L_Agua]]+Tabla_master_rend[[#This Row],[Kg_SalidaSecadero]]) -> 0.020963985 | BC21: 3883 | BD21: 3847 | BE21: 27684 | BF21: =5*6.2 -> 31 | BG21: =10*6.2 -> 62 | BH21: =5*6.2 -> 31 | BI21: =3*6.2 -> 18.6 | BJ21: 109 | BK21: 27320 | BL21: 2.62 | BM21: 71.85 | BN21: 23.45 | BO21: =+SUM(Tabla_master_rend[[#This Row],[B_altas]:[B_lab]])/Tabla_master_rend[[#This Row],[Kg_SalidaSecadero]] -> 0.0092093704 | BP21: =+(Tabla_master_rend[[#This Row],[Kg_mer_env_real]]+Tabla_master_rend[[#This Row],[kg_mer_lab_real]])/Tabla_master_rend[[#This Row],[Kg_SalidaSecadero]] -> 0.003488287 | BQ21: =+Tabla_master_rend[[#This Row],[Merma_TOT]]/Tabla_master_rend[[#This Row],[Kg_Queso_Blan]] -> 0.032260381 | BR21: =+Tabla_master_rend[[#This Row],[kg_mer_lab_real]]+Tabla_master_rend[[#This Row],[Kg_mer_env_real]]+Tabla_master_rend[[#This Row],[Kg_rebaba]]+Tabla_master_rend[[#This Row],[L_Agua]]+Tabla_master_rend[[#This Row],[Kg_Desmoldeo]]+Tabla_master_rend[[#This Row],[Kg_Llenadora]]+Tabla_master_rend[[#This Row],[Kg_Finos]] -> 907.47 | BT21: =IF(+Tabla_master_rend[[#This Row],[Kg_Env_Total]]=0,0,Tabla_master_rend[[#This Row],[Kg_Env_Total]]-Tabla_master_rend[[#This Row],[Kg_SalidaSecadero]]) -> 0 | BU21: =+Tabla_master_rend[[#This Row],[Diferencia_Env_vs_Sec_kg]]/Tabla_master_rend[[#This Row],[Kg_SalidaSecadero]] -> 0 | BV21: =IFERROR(Tabla_master_rend[[#This Row],[Litros_Leche_Total]]*SUMIFS(tbl_PrecioLeche[PMV_eur_L],tbl_PrecioLeche[AñoMes],TEXT(Tabla_master_rend[[#This Row],[Fecha]],"yyyy-mm"),tbl_PrecioLeche[Tipo_Leche],Tabla_master_rend[[#This Row],[Tipo_Leche]]),"") -> 0 | BW21: =+(Tabla_master_rend[[#This Row],[Coste_Leche_€]]-Tabla_master_rend[[#This Row],[Kg_MG_Nata]]*$CO$3)/Tabla_master_rend[[#This Row],[Kg_Queso_Blan]] -> -0.23132258 | BX21: =SUM(Tabla_master_rend[[#This Row],[Kg_Finos]:[Kg_Desmoldeo]])+Tabla_master_rend[[#This Row],[L_Agua]]+SUM(Tabla_master_rend[[#This Row],[B_altas]:[B_lab]]) -> 1061.15 | BY21: =+BX21-Tabla_master_rend[[#This Row],[Merma_TOT]] -> 153.68 | BZ21: =+BY21/BX21 -> 0.14482401 | CA21: =+Tabla_master_rend[[#This Row],[Kg_Queso_Blan]]*$CA$1 -> 182.84207 | CB21: =+Tabla_master_rend[[#This Row],[Kg_Queso_Blan]]*($CB$1-$CA$1) -> 98.453425 | CC21: =+(Tabla_master_rend[[#This Row],[Kg_Queso_Blan]]-CA21-CB21)*$CC$1 -> 292.40667 | CD21: =+CA21+CB21+CC21 -> 573.70217 | CE21: =+CD21/Tabla_master_rend[[#This Row],[Kg_Queso_Blan]] -> 0.020395 | CF21: =+Tabla_master_rend[[#This Row],[Merma_TOT]]/Tabla_master_rend[[#This Row],[Kg_Queso_Blan]] -> 0.032260381 | CG21: =CD21-Tabla_master_rend[[#This Row],[Merma_TOT]] -> -333.76783 | CH21: {=-BR21 * IFERROR(INDEX('Precio Leche_EBITDA_Ventas'!$BD$87:$BD$110,MATCH(1,('Precio Leche_EBITDA_Ventas'!$AZ$87:$AZ$110=YEAR(A21))*('Precio Leche_EBITDA_Ventas'!$BB$87:$BB$110=C21),0)),1.3)} -> -3176.145 | CI21: =+CG21*$CM$2 -> -433.89818
A22: 45701 | B22: 2 | C22: =+UPPER(TEXT(Tabla_master_rend[[#This Row],[Fecha]],"MMM")) -> FEB | D22: =+UPPER(TEXT(Tabla_master_rend[[#This Row],[Fecha]],"ddd")) -> JU | E22: 130225026 | F22: VACA | G22: GOUDA | H22: 11 | I22: =+Tabla_master_rend[[#This Row],[L_Leche_ent]]+Tabla_master_rend[[#This Row],[L_desn_ext]]+Tabla_master_rend[[#This Row],[L_cabra]]+Tabla_master_rend[[#This Row],[L_oveja]] -> 159852 | J22: 159852 | K22: 0.038 | L22: 0.034 | M22: =0.93*K22+0.74*L22+0.048 -> 0.1085 | N22: SI | O22: 0 | P22: 0 | Q22: 0 | R22: 1343 | T22: 152450 | U22: =+Tabla_master_rend[[#This Row],[L_suero Total]]/Tabla_master_rend[[#This Row],[Litros_Leche_Total]] -> 0.95369467 | V22: 0.0024 | W22: 0.0098 | X22: 151720 | Y22: 48811 | Z22: =IF(Tabla_master_rend[[#This Row],[L_suero para con]]=0,0,+Tabla_master_rend[[#This Row],[L_suero para con]]/Tabla_master_rend[[#This Row],[L_suero_con]]) -> 3.1083157 | AA22: =+Tabla_master_rend[[#This Row],[L_suero Total]]-Tabla_master_rend[[#This Row],[L_suero para con]] -> 730 | AI22: =+Tabla_master_rend[[#This Row],[Kg_Finos]]+Tabla_master_rend[[#This Row],[Kg_Llenadora]]+Tabla_master_rend[[#This Row],[Kg_Desmoldeo]]+Tabla_master_rend[[#This Row],[L_Agua]]+Tabla_master_rend[[#This Row],[Kg_SalidaSecadero]] -> 20243.91 | AJ22: =+Tabla_master_rend[[#This Row],[Litros_Leche_Total]]/Tabla_master_rend[[#This Row],[Kg_Queso_Blan]] -> 7.8963007 | AK22: =+Tabla_master_rend[[#This Row],[Litros_Leche_Total]]/(Tabla_master_rend[[#This Row],[Kg_Queso_Blan]]-Tabla_master_rend[[#This Row],[Merma_TOT]]) -> 8.1776228 | AL22: =VLOOKUP(G22,REND_TARGET[#All],8,FALSE) -> 8.494317 | AM22: =(I22*1.03*Tabla_master_rend[[#This Row],[%MG_Leche]])+(I22*1.03*Tabla_master_rend[[#This Row],[%MP_Leche]]) -> 11854.624 | AN22: 0.2824 | AO22: 0.225 | AP22: 0.5588 | AQ22: =+Tabla_master_rend[[#This Row],[Kg_Queso_Blan]]*Tabla_master_rend[[#This Row],[ES_QUESO]]/(Tabla_master_rend[[#This Row],[Kg_Solidos_leche]]) -> 0.95425183 | AR22: =R22*0.4 -> 537.2 | AS22: =+(Tabla_master_rend[[#This Row],[Kg_Queso_Blan]]*Tabla_master_rend[[#This Row],[%MG_QUESO]]+(Tabla_master_rend[[#This Row],[Kg_MG_Nata]]))/(Tabla_master_rend[[#This Row],[Litros_Leche_Total]]*1.03*Tabla_master_rend[[#This Row],[%MG_Leche]]) -> 0.99959609 | AT22: =+Tabla_master_rend[[#This Row],[Kg_Queso_Blan]]*Tabla_master_rend[[#This Row],[%PT_QUESO]]/(Tabla_master_rend[[#This Row],[Litros_Leche_Total]]*1.03*Tabla_master_rend[[#This Row],[%MP_Leche]]) -> 0.8136595 | AU22: =AR22*$CO$3 -> 4029 | AV22: 35.31 | AW22: 138.6 | AX22: 14 | AY22: =SUM(Tabla_master_rend[[#This Row],[Kg_Finos]:[Kg_Desmoldeo]]) -> 187.91 | AZ22: =+(Tabla_master_rend[[#This Row],[Kg_Finos]]+Tabla_master_rend[[#This Row],[Kg_Llenadora]]+Tabla_master_rend[[#This Row],[Kg_Desmoldeo]])/(Tabla_master_rend[[#This Row],[Kg_Queso_Blan]]) -> 0.0092822977 | BA22: 440 | BB22: =+Tabla_master_rend[[#This Row],[L_Agua]]/(Tabla_master_rend[[#This Row],[L_Agua]]+Tabla_master_rend[[#This Row],[Kg_SalidaSecadero]]) -> 0.021938572 | BC22: 2843 | BD22: 2823 | BE22: 19928 | BF22: =7*6.9 -> 48.3 | BG22: =3*6.9 -> 20.7 | BH22: =3*6.9 -> 20.7 | BI22: =1*6.9 -> 6.9 | BJ22: 80 | BK22: 19616 | BL22: 2.62 | BM22: 41.16 | BN22: 24.73 | BO22: =+SUM(Tabla_master_rend[[#This Row],[B_altas]:[B_lab]])/Tabla_master_rend[[#This Row],[Kg_SalidaSecadero]] -> 0.0090028548 | BP22: =+(Tabla_master_rend[[#This Row],[Kg_mer_env_real]]+Tabla_master_rend[[#This Row],[kg_mer_lab_real]])/Tabla_master_rend[[#This Row],[Kg_SalidaSecadero]] -> 0.0033589927 | BQ22: =+Tabla_master_rend[[#This Row],[Merma_TOT]]/Tabla_master_rend[[#This Row],[Kg_Queso_Blan]] -> 0.034401457 | BR22: =+Tabla_master_rend[[#This Row],[kg_mer_lab_real]]+Tabla_master_rend[[#This Row],[Kg_mer_env_real]]+Tabla_master_rend[[#This Row],[Kg_rebaba]]+Tabla_master_rend[[#This Row],[L_Agua]]+Tabla_master_rend[[#This Row],[Kg_Desmoldeo]]+Tabla_master_rend[[#This Row],[Kg_Llenadora]]+Tabla_master_rend[[#This Row],[Kg_Finos]] -> 696.42 | BT22: =IF(+Tabla_master_rend[[#This Row],[Kg_Env_Total]]=0,0,Tabla_master_rend[[#This Row],[Kg_Env_Total]]-Tabla_master_rend[[#This Row],[Kg_SalidaSecadero]]) -> 0 | BU22: =+Tabla_master_rend[[#This Row],[Diferencia_Env_vs_Sec_kg]]/Tabla_master_rend[[#This Row],[Kg_SalidaSecadero]] -> 0 | BV22: =IFERROR(Tabla_master_rend[[#This Row],[Litros_Leche_Total]]*SUMIFS(tbl_PrecioLeche[PMV_eur_L],tbl_PrecioLeche[AñoMes],TEXT(Tabla_master_rend[[#This Row],[Fecha]],"yyyy-mm"),tbl_PrecioLeche[Tipo_Leche],Tabla_master_rend[[#This Row],[Tipo_Leche]]),"") -> 0 | BW22: =+(Tabla_master_rend[[#This Row],[Coste_Leche_€]]-Tabla_master_rend[[#This Row],[Kg_MG_Nata]]*$CO$3)/Tabla_master_rend[[#This Row],[Kg_Queso_Blan]] -> -0.19902282 | BX22: =SUM(Tabla_master_rend[[#This Row],[Kg_Finos]:[Kg_Desmoldeo]])+Tabla_master_rend[[#This Row],[L_Agua]]+SUM(Tabla_master_rend[[#This Row],[B_altas]:[B_lab]]) -> 804.51 | BY22: =+BX22-Tabla_master_rend[[#This Row],[Merma_TOT]] -> 108.09 | BZ22: =+BY22/BX22 -> 0.13435507 | CA22: =+Tabla_master_rend[[#This Row],[Kg_Queso_Blan]]*$CA$1 -> 131.58541 | CB22: =+Tabla_master_rend[[#This Row],[Kg_Queso_Blan]]*($CB$1-$CA$1) -> 70.853685 | CC22: =+(Tabla_master_rend[[#This Row],[Kg_Queso_Blan]]-CA22-CB22)*$CC$1 -> 210.43544 | CD22: =+CA22+CB22+CC22 -> 412.87454 | CE22: =+CD22/Tabla_master_rend[[#This Row],[Kg_Queso_Blan]] -> 0.020395 | CF22: =+Tabla_master_rend[[#This Row],[Merma_TOT]]/Tabla_master_rend[[#This Row],[Kg_Queso_Blan]] -> 0.034401457 | CG22: =CD22-Tabla_master_rend[[#This Row],[Merma_TOT]] -> -283.54546 | CH22: {=-BR22 * IFERROR(INDEX('Precio Leche_EBITDA_Ventas'!$BD$87:$BD$110,MATCH(1,('Precio Leche_EBITDA_Ventas'!$AZ$87:$AZ$110=YEAR(A22))*('Precio Leche_EBITDA_Ventas'!$BB$87:$BB$110=C22),0)),1.3)} -> -2437.47 | CI22: =+CG22*$CM$2 -> -368.60909
A23: 45706 | B23: 2 | C23: =+UPPER(TEXT(Tabla_master_rend[[#This Row],[Fecha]],"MMM")) -> FEB | D23: =+UPPER(TEXT(Tabla_master_rend[[#This Row],[Fecha]],"ddd")) -> MA | E23: 180225316 | F23: VACA | G23: EDAM_F | H23: 16 | I23: =+Tabla_master_rend[[#This Row],[L_Leche_ent]]+Tabla_master_rend[[#This Row],[L_desn_ext]]+Tabla_master_rend[[#This Row],[L_cabra]]+Tabla_master_rend[[#This Row],[L_oveja]] -> 265993 | J23: 265993 | K23: 0.0359 | L23: 0.0333 | M23: =0.93*K23+0.74*L23+0.048 -> 0.106029 | N23: NO | O23: 0 | P23: 0 | Q23: 0 | R23: 7762 | T23: 223420 | U23: =+Tabla_master_rend[[#This Row],[L_suero Total]]/Tabla_master_rend[[#This Row],[Litros_Leche_Total]] -> 0.83994692 | V23: 0.0012 | W23: 0.0092 | X23: 222855 | Y23: 71608 | Z23: =IF(Tabla_master_rend[[#This Row],[L_suero para con]]=0,0,+Tabla_master_rend[[#This Row],[L_suero para con]]/Tabla_master_rend[[#This Row],[L_suero_con]]) -> 3.1121523 | AA23: =+Tabla_master_rend[[#This Row],[L_suero Total]]-Tabla_master_rend[[#This Row],[L_suero para con]] -> 565 | AI23: =+Tabla_master_rend[[#This Row],[Kg_Finos]]+Tabla_master_rend[[#This Row],[Kg_Llenadora]]+Tabla_master_rend[[#This Row],[Kg_Desmoldeo]]+Tabla_master_rend[[#This Row],[L_Agua]]+Tabla_master_rend[[#This Row],[Kg_SalidaSecadero]] -> 27820.8 | AJ23: =+Tabla_master_rend[[#This Row],[Litros_Leche_Total]]/Tabla_master_rend[[#This Row],[Kg_Queso_Blan]] -> 9.56094 | AK23: =+Tabla_master_rend[[#This Row],[Litros_Leche_Total]]/(Tabla_master_rend[[#This Row],[Kg_Queso_Blan]]-Tabla_master_rend[[#This Row],[Merma_TOT]]) -> 9.9608334 | AL23: =VLOOKUP(G23,REND_TARGET[#All],8,FALSE) -> 9.80785 | AM23: =(I23*1.03*Tabla_master_rend[[#This Row],[%MG_Leche]])+(I23*1.03*Tabla_master_rend[[#This Row],[%MP_Leche]]) -> 18958.917 | AN23: 0.2275 | AO23: 0.2521 | AP23: 0.534 | AQ23: =+Tabla_master_rend[[#This Row],[Kg_Queso_Blan]]*Tabla_master_rend[[#This Row],[ES_QUESO]]/(Tabla_master_rend[[#This Row],[Kg_Solidos_leche]]) -> 0.78360526 | AR23: =R23*0.4 -> 3104.8 | AS23: =+(Tabla_master_rend[[#This Row],[Kg_Queso_Blan]]*Tabla_master_rend[[#This Row],[%MG_QUESO]]+(Tabla_master_rend[[#This Row],[Kg_MG_Nata]]))/(Tabla_master_rend[[#This Row],[Litros_Leche_Total]]*1.03*Tabla_master_rend[[#This Row],[%MG_Leche]]) -> 0.95916973 | AT23: =+Tabla_master_rend[[#This Row],[Kg_Queso_Blan]]*Tabla_master_rend[[#This Row],[%PT_QUESO]]/(Tabla_master_rend[[#This Row],[Litros_Leche_Total]]*1.03*Tabla_master_rend[[#This Row],[%MP_Leche]]) -> 0.76876003 | AU23: =AR23*$CO$3 -> 23286 | AV23: 57.7 | AW23: 64.8 | AX23: 142.3 | AY23: =SUM(Tabla_master_rend[[#This Row],[Kg_Finos]:[Kg_Desmoldeo]]) -> 264.8 | AZ23: =+(Tabla_master_rend[[#This Row],[Kg_Finos]]+Tabla_master_rend[[#This Row],[Kg_Llenadora]]+Tabla_master_rend[[#This Row],[Kg_Desmoldeo]])/(Tabla_master_rend[[#This Row],[Kg_Queso_Blan]]) -> 0.0095180584 | BA23: 570 | BB23: =+Tabla_master_rend[[#This Row],[L_Agua]]/(Tabla_master_rend[[#This Row],[L_Agua]]+Tabla_master_rend[[#This Row],[Kg_SalidaSecadero]]) -> 0.02068515 | BC23: 3829 | BD23: 3581 | BE23: 26018 | BF23: =67*6.2 -> 415.4 | BG23: =24*6.2 -> 148.8 | BH23: 0 | BI23: =174*6.2 -> 1078.8 | BJ23: 120 | BK23: 26986 | BL23: 4.99 | BM23: 238.43 | BN23: 38.69 | BO23: =+SUM(Tabla_master_rend[[#This Row],[B_altas]:[B_lab]])/Tabla_master_rend[[#This Row],[Kg_SalidaSecadero]] -> 0.065330171 | BP23: =+(Tabla_master_rend[[#This Row],[Kg_mer_env_real]]+Tabla_master_rend[[#This Row],[kg_mer_lab_real]])/Tabla_master_rend[[#This Row],[Kg_SalidaSecadero]] -> 0.010269028 | BQ23: =+Tabla_master_rend[[#This Row],[Merma_TOT]]/Tabla_master_rend[[#This Row],[Kg_Queso_Blan]] -> 0.040146581 | BR23: =+Tabla_master_rend[[#This Row],[kg_mer_lab_real]]+Tabla_master_rend[[#This Row],[Kg_mer_env_real]]+Tabla_master_rend[[#This Row],[Kg_rebaba]]+Tabla_master_rend[[#This Row],[L_Agua]]+Tabla_master_rend[[#This Row],[Kg_Desmoldeo]]+Tabla_master_rend[[#This Row],[Kg_Llenadora]]+Tabla_master_rend[[#This Row],[Kg_Finos]] -> 1116.91 | BT23: =IF(+Tabla_master_rend[[#This Row],[Kg_Env_Total]]=0,0,Tabla_master_rend[[#This Row],[Kg_Env_Total]]-Tabla_master_rend[[#This Row],[Kg_SalidaSecadero]]) -> 0 | BU23: =+Tabla_master_rend[[#This Row],[Diferencia_Env_vs_Sec_kg]]/Tabla_master_rend[[#This Row],[Kg_SalidaSecadero]] -> 0 | BV23: =IFERROR(Tabla_master_rend[[#This Row],[Litros_Leche_Total]]*SUMIFS(tbl_PrecioLeche[PMV_eur_L],tbl_PrecioLeche[AñoMes],TEXT(Tabla_master_rend[[#This Row],[Fecha]],"yyyy-mm"),tbl_PrecioLeche[Tipo_Leche],Tabla_master_rend[[#This Row],[Tipo_Leche]]),"") -> 0 | BW23: =+(Tabla_master_rend[[#This Row],[Coste_Leche_€]]-Tabla_master_rend[[#This Row],[Kg_MG_Nata]]*$CO$3)/Tabla_master_rend[[#This Row],[Kg_Queso_Blan]] -> -0.83699965 | BX23: =SUM(Tabla_master_rend[[#This Row],[Kg_Finos]:[Kg_Desmoldeo]])+Tabla_master_rend[[#This Row],[L_Agua]]+SUM(Tabla_master_rend[[#This Row],[B_altas]:[B_lab]]) -> 2597.8 | BY23: =+BX23-Tabla_master_rend[[#This Row],[Merma_TOT]] -> 1480.89 | BZ23: =+BY23/BX23 -> 0.57005543 | CA23: =+Tabla_master_rend[[#This Row],[Kg_Queso_Blan]]*$CA$1 -> 180.8352 | CB23: =+Tabla_master_rend[[#This Row],[Kg_Queso_Blan]]*($CB$1-$CA$1) -> 97.3728 | CC23: =+(Tabla_master_rend[[#This Row],[Kg_Queso_Blan]]-CA23-CB23)*$CC$1 -> 289.19722 | CD23: =+CA23+CB23+CC23 -> 567.40522 | CE23: =+CD23/Tabla_master_rend[[#This Row],[Kg_Queso_Blan]] -> 0.020395 | CF23: =+Tabla_master_rend[[#This Row],[Merma_TOT]]/Tabla_master_rend[[#This Row],[Kg_Queso_Blan]] -> 0.040146581 | CG23: =CD23-Tabla_master_rend[[#This Row],[Merma_TOT]] -> -549.50478 | CH23: {=-BR23 * IFERROR(INDEX('Precio Leche_EBITDA_Ventas'!$BD$87:$BD$110,MATCH(1,('Precio Leche_EBITDA_Ventas'!$AZ$87:$AZ$110=YEAR(A23))*('Precio Leche_EBITDA_Ventas'!$BB$87:$BB$110=C23),0)),1.3)} -> -3909.185 | CI23: =+CG23*$CM$2 -> -714.35622
A24: 45707 | B24: 2 | C24: =+UPPER(TEXT(Tabla_master_rend[[#This Row],[Fecha]],"MMM")) -> FEB | D24: =+UPPER(TEXT(Tabla_master_rend[[#This Row],[Fecha]],"ddd")) -> MI | E24: 190225126 | F24: VACA | G24: GOUDA_F_C | H24: 10 | I24: =+Tabla_master_rend[[#This Row],[L_Leche_ent]]+Tabla_master_rend[[#This Row],[L_desn_ext]]+Tabla_master_rend[[#This Row],[L_cabra]]+Tabla_master_rend[[#This Row],[L_oveja]] -> 119449 | J24: 119449 | K24: 0.0391 | L24: 0.0342 | M24: =0.93*K24+0.74*L24+0.048 -> 0.109671 | N24: NO | O24: 0 | P24: 0 | Q24: 0 | R24: 0 | T24: 140570 | U24: =+Tabla_master_rend[[#This Row],[L_suero Total]]/Tabla_master_rend[[#This Row],[Litros_Leche_Total]] -> 1.1768202 | V24: 0.0018 | W24: 0.008 | X24: 142538 | Y24: 39868 | Z24: =IF(Tabla_master_rend[[#This Row],[L_suero para con]]=0,0,+Tabla_master_rend[[#This Row],[L_suero para con]]/Tabla_master_rend[[#This Row],[L_suero_con]]) -> 3.5752483 | AA24: =+Tabla_master_rend[[#This Row],[L_suero Total]]-Tabla_master_rend[[#This Row],[L_suero para con]] -> -1968 | AI24: =+Tabla_master_rend[[#This Row],[Kg_Finos]]+Tabla_master_rend[[#This Row],[Kg_Llenadora]]+Tabla_master_rend[[#This Row],[Kg_Desmoldeo]]+Tabla_master_rend[[#This Row],[L_Agua]]+Tabla_master_rend[[#This Row],[Kg_SalidaSecadero]] -> 16145.7 | AJ24: =+Tabla_master_rend[[#This Row],[Litros_Leche_Total]]/Tabla_master_rend[[#This Row],[Kg_Queso_Blan]] -> 7.3981927 | AK24: =+Tabla_master_rend[[#This Row],[Litros_Leche_Total]]/(Tabla_master_rend[[#This Row],[Kg_Queso_Blan]]-Tabla_master_rend[[#This Row],[Merma_TOT]]) -> 7.5829032 | AL24: =VLOOKUP(G24,REND_TARGET[#All],8,FALSE) -> 7.189 | AM24: =(I24*1.03*Tabla_master_rend[[#This Row],[%MG_Leche]])+(I24*1.03*Tabla_master_rend[[#This Row],[%MP_Leche]]) -> 9018.2801 | AN24: 0.291 | AO24: 0.2419 | AP24: 0.5792 | AQ24: =+Tabla_master_rend[[#This Row],[Kg_Queso_Blan]]*Tabla_master_rend[[#This Row],[ES_QUESO]]/(Tabla_master_rend[[#This Row],[Kg_Solidos_leche]]) -> 1.0369593 | AR24: =R24*0.4 -> 0 | AS24: =+(Tabla_master_rend[[#This Row],[Kg_Queso_Blan]]*Tabla_master_rend[[#This Row],[%MG_QUESO]]+(Tabla_master_rend[[#This Row],[Kg_MG_Nata]]))/(Tabla_master_rend[[#This Row],[Litros_Leche_Total]]*1.03*Tabla_master_rend[[#This Row],[%MG_Leche]]) -> 0.97668241 | AT24: =+Tabla_master_rend[[#This Row],[Kg_Queso_Blan]]*Tabla_master_rend[[#This Row],[%PT_QUESO]]/(Tabla_master_rend[[#This Row],[Litros_Leche_Total]]*1.03*Tabla_master_rend[[#This Row],[%MP_Leche]]) -> 0.9282114 | AU24: =AR24*$CO$3 -> 0 | AV24: 27 | AW24: 37.2 | AX24: 7.5 | AY24: =SUM(Tabla_master_rend[[#This Row],[Kg_Finos]:[Kg_Desmoldeo]]) -> 71.7 | AZ24: =+(Tabla_master_rend[[#This Row],[Kg_Finos]]+Tabla_master_rend[[#This Row],[Kg_Llenadora]]+Tabla_master_rend[[#This Row],[Kg_Desmoldeo]])/(Tabla_master_rend[[#This Row],[Kg_Queso_Blan]]) -> 0.0044408109 | BA24: 240 | BB24: =+Tabla_master_rend[[#This Row],[L_Agua]]/(Tabla_master_rend[[#This Row],[L_Agua]]+Tabla_master_rend[[#This Row],[Kg_SalidaSecadero]]) -> 0.014930944 | BC24: 2181 | BD24: 2152 | BE24: 15896 | BF24: =50*5.9 -> 295 | BG24: =15*5.9 -> 88.5 | BH24: 0 | BI24: =2*5.9 -> 11.8 | BJ24: 78 | BK24: 15834 | BL24: 3.75 | BM24: 55.85 | BN24: 21.99 | BO24: =+SUM(Tabla_master_rend[[#This Row],[B_altas]:[B_lab]])/Tabla_master_rend[[#This Row],[Kg_SalidaSecadero]] -> 0.029891373 | BP24: =+(Tabla_master_rend[[#This Row],[Kg_mer_env_real]]+Tabla_master_rend[[#This Row],[kg_mer_lab_real]])/Tabla_master_rend[[#This Row],[Kg_SalidaSecadero]] -> 0.0049160035 | BQ24: =+Tabla_master_rend[[#This Row],[Merma_TOT]]/Tabla_master_rend[[#This Row],[Kg_Queso_Blan]] -> 0.024358808 | BR24: =+Tabla_master_rend[[#This Row],[kg_mer_lab_real]]+Tabla_master_rend[[#This Row],[Kg_mer_env_real]]+Tabla_master_rend[[#This Row],[Kg_rebaba]]+Tabla_master_rend[[#This Row],[L_Agua]]+Tabla_master_rend[[#This Row],[Kg_Desmoldeo]]+Tabla_master_rend[[#This Row],[Kg_Llenadora]]+Tabla_master_rend[[#This Row],[Kg_Finos]] -> 393.29 | BT24: =IF(+Tabla_master_rend[[#This Row],[Kg_Env_Total]]=0,0,Tabla_master_rend[[#This Row],[Kg_Env_Total]]-Tabla_master_rend[[#This Row],[Kg_SalidaSecadero]]) -> 0 | BU24: =+Tabla_master_rend[[#This Row],[Diferencia_Env_vs_Sec_kg]]/Tabla_master_rend[[#This Row],[Kg_SalidaSecadero]] -> 0 | BV24: =IFERROR(Tabla_master_rend[[#This Row],[Litros_Leche_Total]]*SUMIFS(tbl_PrecioLeche[PMV_eur_L],tbl_PrecioLeche[AñoMes],TEXT(Tabla_master_rend[[#This Row],[Fecha]],"yyyy-mm"),tbl_PrecioLeche[Tipo_Leche],Tabla_master_rend[[#This Row],[Tipo_Leche]]),"") -> 0 | BW24: =+(Tabla_master_rend[[#This Row],[Coste_Leche_€]]-Tabla_master_rend[[#This Row],[Kg_MG_Nata]]*$CO$3)/Tabla_master_rend[[#This Row],[Kg_Queso_Blan]] -> 0 | BX24: =SUM(Tabla_master_rend[[#This Row],[Kg_Finos]:[Kg_Desmoldeo]])+Tabla_master_rend[[#This Row],[L_Agua]]+SUM(Tabla_master_rend[[#This Row],[B_altas]:[B_lab]]) -> 785 | BY24: =+BX24-Tabla_master_rend[[#This Row],[Merma_TOT]] -> 391.71 | BZ24: =+BY24/BX24 -> 0.49899363 | CA24: =+Tabla_master_rend[[#This Row],[Kg_Queso_Blan]]*$CA$1 -> 104.94705 | CB24: =+Tabla_master_rend[[#This Row],[Kg_Queso_Blan]]*($CB$1-$CA$1) -> 56.50995 | CC24: =+(Tabla_master_rend[[#This Row],[Kg_Queso_Blan]]-CA24-CB24)*$CC$1 -> 167.83455 | CD24: =+CA24+CB24+CC24 -> 329.29155 | CE24: =+CD24/Tabla_master_rend[[#This Row],[Kg_Queso_Blan]] -> 0.020395 | CF24: =+Tabla_master_rend[[#This Row],[Merma_TOT]]/Tabla_master_rend[[#This Row],[Kg_Queso_Blan]] -> 0.024358808 | CG24: =CD24-Tabla_master_rend[[#This Row],[Merma_TOT]] -> -63.998448 | CH24: {=-BR24 * IFERROR(INDEX('Precio Leche_EBITDA_Ventas'!$BD$87:$BD$110,MATCH(1,('Precio Leche_EBITDA_Ventas'!$AZ$87:$AZ$110=YEAR(A24))*('Precio Leche_EBITDA_Ventas'!$BB$87:$BB$110=C24),0)),1.3)} -> -1376.515 | CI24: =+CG24*$CM$2 -> -83.197983
A25: 45708 | B25: 2 | C25: =+UPPER(TEXT(Tabla_master_rend[[#This Row],[Fecha]],"MMM")) -> FEB | D25: =+UPPER(TEXT(Tabla_master_rend[[#This Row],[Fecha]],"ddd")) -> JU | E25: 200225116 | F25: VACA | G25: EDAM_F | H25: 17 | I25: =+Tabla_master_rend[[#This Row],[L_Leche_ent]]+Tabla_master_rend[[#This Row],[L_desn_ext]]+Tabla_master_rend[[#This Row],[L_cabra]]+Tabla_master_rend[[#This Row],[L_oveja]] -> 272576 | J25: 272576 | K25: 0.0377 | L25: 0.0335 | M25: =0.93*K25+0.74*L25+0.048 -> 0.107851 | N25: SI | O25: 0 | P25: 0 | Q25: 0 | R25: 9030 | T25: 234360 | U25: =+Tabla_master_rend[[#This Row],[L_suero Total]]/Tabla_master_rend[[#This Row],[Litros_Leche_Total]] -> 0.8597969 | V25: 0.0011 | W25: 0.0086 | X25: 155018 | Y25: 45829 | Z25: =IF(Tabla_master_rend[[#This Row],[L_suero para con]]=0,0,+Tabla_master_rend[[#This Row],[L_suero para con]]/Tabla_master_rend[[#This Row],[L_suero_con]]) -> 3.3825307 | AA25: =+Tabla_master_rend[[#This Row],[L_suero Total]]-Tabla_master_rend[[#This Row],[L_suero para con]] -> 79342 | AI25: =+Tabla_master_rend[[#This Row],[Kg_Finos]]+Tabla_master_rend[[#This Row],[Kg_Llenadora]]+Tabla_master_rend[[#This Row],[Kg_Desmoldeo]]+Tabla_master_rend[[#This Row],[L_Agua]]+Tabla_master_rend[[#This Row],[Kg_SalidaSecadero]] -> 29170.94 | AJ25: =+Tabla_master_rend[[#This Row],[Litros_Leche_Total]]/Tabla_master_rend[[#This Row],[Kg_Queso_Blan]] -> 9.3440938 | AK25: =+Tabla_master_rend[[#This Row],[Litros_Leche_Total]]/(Tabla_master_rend[[#This Row],[Kg_Queso_Blan]]-Tabla_master_rend[[#This Row],[Merma_TOT]]) -> 9.7006554 | AL25: =VLOOKUP(G25,REND_TARGET[#All],8,FALSE) -> 9.80785 | AM25: =(I25*1.03*Tabla_master_rend[[#This Row],[%MG_Leche]])+(I25*1.03*Tabla_master_rend[[#This Row],[%MP_Leche]]) -> 19989.634 | AN25: 0.2178 | AO25: 0.2453 | AP25: 0.5188 | AQ25: =+Tabla_master_rend[[#This Row],[Kg_Queso_Blan]]*Tabla_master_rend[[#This Row],[ES_QUESO]]/(Tabla_master_rend[[#This Row],[Kg_Solidos_leche]]) -> 0.7570866 | AR25: =R25*0.4 -> 3612 | AS25: =+(Tabla_master_rend[[#This Row],[Kg_Queso_Blan]]*Tabla_master_rend[[#This Row],[%MG_QUESO]]+(Tabla_master_rend[[#This Row],[Kg_MG_Nata]]))/(Tabla_master_rend[[#This Row],[Litros_Leche_Total]]*1.03*Tabla_master_rend[[#This Row],[%MG_Leche]]) -> 0.94152073 | AT25: =+Tabla_master_rend[[#This Row],[Kg_Queso_Blan]]*Tabla_master_rend[[#This Row],[%PT_QUESO]]/(Tabla_master_rend[[#This Row],[Litros_Leche_Total]]*1.03*Tabla_master_rend[[#This Row],[%MP_Leche]]) -> 0.7608137 | AU25: =AR25*$CO$3 -> 27090 | AV25: 57.14 | AW25: 51.2 | AX25: 21.6 | AY25: =SUM(Tabla_master_rend[[#This Row],[Kg_Finos]:[Kg_Desmoldeo]]) -> 129.94 | AZ25: =+(Tabla_master_rend[[#This Row],[Kg_Finos]]+Tabla_master_rend[[#This Row],[Kg_Llenadora]]+Tabla_master_rend[[#This Row],[Kg_Desmoldeo]])/(Tabla_master_rend[[#This Row],[Kg_Queso_Blan]]) -> 0.0044544331 | BA25: 610 | BB25: =+Tabla_master_rend[[#This Row],[L_Agua]]/(Tabla_master_rend[[#This Row],[L_Agua]]+Tabla_master_rend[[#This Row],[Kg_SalidaSecadero]]) -> 0.021004786 | BC25: 4145 | BD25: 3926 | BE25: 27633 | BF25: =12*6.4 -> 76.8 | BG25: =66*6.4 -> 422.4 | BH25: 0 | BI25: =137*6.4 -> 876.8 | BJ25: 100 | BK25: 28431 | BL25: 3.75 | BM25: 319.52 | BN25: 9.01 | BO25: =+SUM(Tabla_master_rend[[#This Row],[B_altas]:[B_lab]])/Tabla_master_rend[[#This Row],[Kg_SalidaSecadero]] -> 0.051915163 | BP25: =+(Tabla_master_rend[[#This Row],[Kg_mer_env_real]]+Tabla_master_rend[[#This Row],[kg_mer_lab_real]])/Tabla_master_rend[[#This Row],[Kg_SalidaSecadero]] -> 0.011555345 | BQ25: =+Tabla_master_rend[[#This Row],[Merma_TOT]]/Tabla_master_rend[[#This Row],[Kg_Queso_Blan]] -> 0.036756443 | BR25: =+Tabla_master_rend[[#This Row],[kg_mer_lab_real]]+Tabla_master_rend[[#This Row],[Kg_mer_env_real]]+Tabla_master_rend[[#This Row],[Kg_rebaba]]+Tabla_master_rend[[#This Row],[L_Agua]]+Tabla_master_rend[[#This Row],[Kg_Desmoldeo]]+Tabla_master_rend[[#This Row],[Kg_Llenadora]]+Tabla_master_rend[[#This Row],[Kg_Finos]] -> 1072.22 | BT25: =IF(+Tabla_master_rend[[#This Row],[Kg_Env_Total]]=0,0,Tabla_master_rend[[#This Row],[Kg_Env_Total]]-Tabla_master_rend[[#This Row],[Kg_SalidaSecadero]]) -> 0 | BU25: =+Tabla_master_rend[[#This Row],[Diferencia_Env_vs_Sec_kg]]/Tabla_master_rend[[#This Row],[Kg_SalidaSecadero]] -> 0 | BV25: =IFERROR(Tabla_master_rend[[#This Row],[Litros_Leche_Total]]*SUMIFS(tbl_PrecioLeche[PMV_eur_L],tbl_PrecioLeche[AñoMes],TEXT(Tabla_master_rend[[#This Row],[Fecha]],"yyyy-mm"),tbl_PrecioLeche[Tipo_Leche],Tabla_master_rend[[#This Row],[Tipo_Leche]]),"") -> 0 | BW25: =+(Tabla_master_rend[[#This Row],[Coste_Leche_€]]-Tabla_master_rend[[#This Row],[Kg_MG_Nata]]*$CO$3)/Tabla_master_rend[[#This Row],[Kg_Queso_Blan]] -> -0.92866394 | BX25: =SUM(Tabla_master_rend[[#This Row],[Kg_Finos]:[Kg_Desmoldeo]])+Tabla_master_rend[[#This Row],[L_Agua]]+SUM(Tabla_master_rend[[#This Row],[B_altas]:[B_lab]]) -> 2215.94 | BY25: =+BX25-Tabla_master_rend[[#This Row],[Merma_TOT]] -> 1143.72 | BZ25: =+BY25/BX25 -> 0.51613311 | CA25: =+Tabla_master_rend[[#This Row],[Kg_Queso_Blan]]*$CA$1 -> 189.61111 | CB25: =+Tabla_master_rend[[#This Row],[Kg_Queso_Blan]]*($CB$1-$CA$1) -> 102.09829 | CC25: =+(Tabla_master_rend[[#This Row],[Kg_Queso_Blan]]-CA25-CB25)*$CC$1 -> 303.23192 | CD25: =+CA25+CB25+CC25 -> 594.94132 | CE25: =+CD25/Tabla_master_rend[[#This Row],[Kg_Queso_Blan]] -> 0.020395 | CF25: =+Tabla_master_rend[[#This Row],[Merma_TOT]]/Tabla_master_rend[[#This Row],[Kg_Queso_Blan]] -> 0.036756443 | CG25: =CD25-Tabla_master_rend[[#This Row],[Merma_TOT]] -> -477.27868 | CH25: {=-BR25 * IFERROR(INDEX('Precio Leche_EBITDA_Ventas'!$BD$87:$BD$110,MATCH(1,('Precio Leche_EBITDA_Ventas'!$AZ$87:$AZ$110=YEAR(A25))*('Precio Leche_EBITDA_Ventas'!$BB$87:$BB$110=C25),0)),1.3)} -> -3752.77 | CI25: =+CG25*$CM$2 -> -620.46228
A26: 45712 | B26: 2 | C26: =+UPPER(TEXT(Tabla_master_rend[[#This Row],[Fecha]],"MMM")) -> FEB | D26: =+UPPER(TEXT(Tabla_master_rend[[#This Row],[Fecha]],"ddd")) -> LU | E26: 240225326 | F26: VACA | G26: GOUDA_F | H26: 16 | I26: =+Tabla_master_rend[[#This Row],[L_Leche_ent]]+Tabla_master_rend[[#This Row],[L_desn_ext]]+Tabla_master_rend[[#This Row],[L_cabra]]+Tabla_master_rend[[#This Row],[L_oveja]] -> 256272 | J26: 256272 | K26: 0.037 | L26: 0.0332 | M26: =0.93*K26+0.74*L26+0.048 -> 0.106978 | N26: NO | O26: 0 | P26: 0 | Q26: 0 | R26: 2831 | T26: 220680 | U26: =+Tabla_master_rend[[#This Row],[L_suero Total]]/Tabla_master_rend[[#This Row],[Litros_Leche_Total]] -> 0.86111631 | V26: 0.0017 | W26: 0.0087 | X26: 168594 | Y26: 51519 | Z26: =IF(Tabla_master_rend[[#This Row],[L_suero para con]]=0,0,+Tabla_master_rend[[#This Row],[L_suero para con]]/Tabla_master_rend[[#This Row],[L_suero_con]]) -> 3.2724626 | AA26: =+Tabla_master_rend[[#This Row],[L_suero Total]]-Tabla_master_rend[[#This Row],[L_suero para con]] -> 52086 | AI26: =+Tabla_master_rend[[#This Row],[Kg_Finos]]+Tabla_master_rend[[#This Row],[Kg_Llenadora]]+Tabla_master_rend[[#This Row],[Kg_Desmoldeo]]+Tabla_master_rend[[#This Row],[L_Agua]]+Tabla_master_rend[[#This Row],[Kg_SalidaSecadero]] -> 28728.78 | AJ26: =+Tabla_master_rend[[#This Row],[Litros_Leche_Total]]/Tabla_master_rend[[#This Row],[Kg_Queso_Blan]] -> 8.9203927 | AK26: =+Tabla_master_rend[[#This Row],[Litros_Leche_Total]]/(Tabla_master_rend[[#This Row],[Kg_Queso_Blan]]-Tabla_master_rend[[#This Row],[Merma_TOT]]) -> 9.137475 | AL26: =VLOOKUP(G26,REND_TARGET[#All],8,FALSE) -> 9.354943 | AM26: =(I26*1.03*Tabla_master_rend[[#This Row],[%MG_Leche]])+(I26*1.03*Tabla_master_rend[[#This Row],[%MP_Leche]]) -> 18530.003 | AN26: 0.2899 | AO26: 0.2385 | AP26: 0.577 | AQ26: =+Tabla_master_rend[[#This Row],[Kg_Queso_Blan]]*Tabla_master_rend[[#This Row],[ES_QUESO]]/(Tabla_master_rend[[#This Row],[Kg_Solidos_leche]]) -> 0.89457653 | AR26: =R26*0.4 -> 1132.4 | AS26: =+(Tabla_master_rend[[#This Row],[Kg_Queso_Blan]]*Tabla_master_rend[[#This Row],[%MG_QUESO]]+(Tabla_master_rend[[#This Row],[Kg_MG_Nata]]))/(Tabla_master_rend[[#This Row],[Litros_Leche_Total]]*1.03*Tabla_master_rend[[#This Row],[%MG_Leche]]) -> 0.96870406 | AT26: =+Tabla_master_rend[[#This Row],[Kg_Queso_Blan]]*Tabla_master_rend[[#This Row],[%PT_QUESO]]/(Tabla_master_rend[[#This Row],[Litros_Leche_Total]]*1.03*Tabla_master_rend[[#This Row],[%MP_Leche]]) -> 0.78186019 | AU26: =AR26*$CO$3 -> 8493 | AV26: 54.48 | AW26: 77.3 | AX26: 52 | AY26: =SUM(Tabla_master_rend[[#This Row],[Kg_Finos]:[Kg_Desmoldeo]]) -> 183.78 | AZ26: =+(Tabla_master_rend[[#This Row],[Kg_Finos]]+Tabla_master_rend[[#This Row],[Kg_Llenadora]]+Tabla_master_rend[[#This Row],[Kg_Desmoldeo]])/(Tabla_master_rend[[#This Row],[Kg_Queso_Blan]]) -> 0.0063970694 | BA26: 370 | BB26: =+Tabla_master_rend[[#This Row],[L_Agua]]/(Tabla_master_rend[[#This Row],[L_Agua]]+Tabla_master_rend[[#This Row],[Kg_SalidaSecadero]]) -> 0.01296199 | BC26: 3935 | BD26: 3891 | BE26: 28279 | BF26: =130*6 -> 780 | BG26: =1*6 -> 6 | BH26: =7*6 -> 42 | BI26: =14*6 -> 84 | BJ26: 134 | BK26: 28175 | BL26: 0 | BM26: 101.49 | BN26: 27.25 | BO26: =+SUM(Tabla_master_rend[[#This Row],[B_altas]:[B_lab]])/Tabla_master_rend[[#This Row],[Kg_SalidaSecadero]] -> 0.037125111 | BP26: =+(Tabla_master_rend[[#This Row],[Kg_mer_env_real]]+Tabla_master_rend[[#This Row],[kg_mer_lab_real]])/Tabla_master_rend[[#This Row],[Kg_SalidaSecadero]] -> 0.004569299 | BQ26: =+Tabla_master_rend[[#This Row],[Merma_TOT]]/Tabla_master_rend[[#This Row],[Kg_Queso_Blan]] -> 0.023757361 | BR26: =+Tabla_master_rend[[#This Row],[kg_mer_lab_real]]+Tabla_master_rend[[#This Row],[Kg_mer_env_real]]+Tabla_master_rend[[#This Row],[Kg_rebaba]]+Tabla_master_rend[[#This Row],[L_Agua]]+Tabla_master_rend[[#This Row],[Kg_Desmoldeo]]+Tabla_master_rend[[#This Row],[Kg_Llenadora]]+Tabla_master_rend[[#This Row],[Kg_Finos]] -> 682.52 | BT26: =IF(+Tabla_master_rend[[#This Row],[Kg_Env_Total]]=0,0,Tabla_master_rend[[#This Row],[Kg_Env_Total]]-Tabla_master_rend[[#This Row],[Kg_SalidaSecadero]]) -> 0 | BU26: =+Tabla_master_rend[[#This Row],[Diferencia_Env_vs_Sec_kg]]/Tabla_master_rend[[#This Row],[Kg_SalidaSecadero]] -> 0 | BV26: =IFERROR(Tabla_master_rend[[#This Row],[Litros_Leche_Total]]*SUMIFS(tbl_PrecioLeche[PMV_eur_L],tbl_PrecioLeche[AñoMes],TEXT(Tabla_master_rend[[#This Row],[Fecha]],"yyyy-mm"),tbl_PrecioLeche[Tipo_Leche],Tabla_master_rend[[#This Row],[Tipo_Leche]]),"") -> 0 | BW26: =+(Tabla_master_rend[[#This Row],[Coste_Leche_€]]-Tabla_master_rend[[#This Row],[Kg_MG_Nata]]*$CO$3)/Tabla_master_rend[[#This Row],[Kg_Queso_Blan]] -> -0.29562689 | BX26: =SUM(Tabla_master_rend[[#This Row],[Kg_Finos]:[Kg_Desmoldeo]])+Tabla_master_rend[[#This Row],[L_Agua]]+SUM(Tabla_master_rend[[#This Row],[B_altas]:[B_lab]]) -> 1599.78 | BY26: =+BX26-Tabla_master_rend[[#This Row],[Merma_TOT]] -> 917.26 | BZ26: =+BY26/BX26 -> 0.57336634 | CA26: =+Tabla_master_rend[[#This Row],[Kg_Queso_Blan]]*$CA$1 -> 186.73707 | CB26: =+Tabla_master_rend[[#This Row],[Kg_Queso_Blan]]*($CB$1-$CA$1) -> 100.55073 | CC26: =+(Tabla_master_rend[[#This Row],[Kg_Queso_Blan]]-CA26-CB26)*$CC$1 -> 298.63567 | CD26: =+CA26+CB26+CC26 -> 585.92347 | CE26: =+CD26/Tabla_master_rend[[#This Row],[Kg_Queso_Blan]] -> 0.020395 | CF26: =+Tabla_master_rend[[#This Row],[Merma_TOT]]/Tabla_master_rend[[#This Row],[Kg_Queso_Blan]] -> 0.023757361 | CG26: =CD26-Tabla_master_rend[[#This Row],[Merma_TOT]] -> -96.596532 | CH26: {=-BR26 * IFERROR(INDEX('Precio Leche_EBITDA_Ventas'!$BD$87:$BD$110,MATCH(1,('Precio Leche_EBITDA_Ventas'!$AZ$87:$AZ$110=YEAR(A26))*('Precio Leche_EBITDA_Ventas'!$BB$87:$BB$110=C26),0)),1.3)} -> -2388.82 | CI26: =+CG26*$CM$2 -> -125.57549
A27: 45714 | B27: 2 | C27: =+UPPER(TEXT(Tabla_master_rend[[#This Row],[Fecha]],"MMM")) -> FEB | D27: =+UPPER(TEXT(Tabla_master_rend[[#This Row],[Fecha]],"ddd")) -> MI | E27: 260225116 | F27: VACA | G27: EDAM_F_C | H27: 10 | I27: =+Tabla_master_rend[[#This Row],[L_Leche_ent]]+Tabla_master_rend[[#This Row],[L_desn_ext]]+Tabla_master_rend[[#This Row],[L_cabra]]+Tabla_master_rend[[#This Row],[L_oveja]] -> 121952 | J27: 121952 | K27: 0.0388 | L27: 0.0335 | M27: =0.93*K27+0.74*L27+0.048 -> 0.108874 | N27: SI | O27: 0 | P27: 0 | Q27: 0 | R27: 2516 | T27: 141480 | U27: =+Tabla_master_rend[[#This Row],[L_suero Total]]/Tabla_master_rend[[#This Row],[Litros_Leche_Total]] -> 1.1601286 | V27: 0.0014 | W27: 0.0088 | X27: 141753 | Y27: 40524 | Z27: =IF(Tabla_master_rend[[#This Row],[L_suero para con]]=0,0,+Tabla_master_rend[[#This Row],[L_suero para con]]/Tabla_master_rend[[#This Row],[L_suero_con]]) -> 3.4980012 | AA27: =+Tabla_master_rend[[#This Row],[L_suero Total]]-Tabla_master_rend[[#This Row],[L_suero para con]] -> -273 | AI27: =+Tabla_master_rend[[#This Row],[Kg_Finos]]+Tabla_master_rend[[#This Row],[Kg_Llenadora]]+Tabla_master_rend[[#This Row],[Kg_Desmoldeo]]+Tabla_master_rend[[#This Row],[L_Agua]]+Tabla_master_rend[[#This Row],[Kg_SalidaSecadero]] -> 16835.19 | AJ27: =+Tabla_master_rend[[#This Row],[Litros_Leche_Total]]/Tabla_master_rend[[#This Row],[Kg_Queso_Blan]] -> 7.2438743 | AK27: =+Tabla_master_rend[[#This Row],[Litros_Leche_Total]]/(Tabla_master_rend[[#This Row],[Kg_Queso_Blan]]-Tabla_master_rend[[#This Row],[Merma_TOT]]) -> 7.5320857 | AL27: =VLOOKUP(G27,REND_TARGET[#All],8,FALSE) -> 7.7025 | AM27: =(I27*1.03*Tabla_master_rend[[#This Row],[%MG_Leche]])+(I27*1.03*Tabla_master_rend[[#This Row],[%MP_Leche]]) -> 9081.6435 | AN27: 0.222 | AO27: 0.2508 | AP27: 0.5259 | AQ27: =+Tabla_master_rend[[#This Row],[Kg_Queso_Blan]]*Tabla_master_rend[[#This Row],[ES_QUESO]]/(Tabla_master_rend[[#This Row],[Kg_Solidos_leche]]) -> 0.97489253 | AR27: =R27*0.4 -> 1006.4 | AS27: =+(Tabla_master_rend[[#This Row],[Kg_Queso_Blan]]*Tabla_master_rend[[#This Row],[%MG_QUESO]]+(Tabla_master_rend[[#This Row],[Kg_MG_Nata]]))/(Tabla_master_rend[[#This Row],[Litros_Leche_Total]]*1.03*Tabla_master_rend[[#This Row],[%MG_Leche]]) -> 0.97335129 | AT27: =+Tabla_master_rend[[#This Row],[Kg_Queso_Blan]]*Tabla_master_rend[[#This Row],[%PT_QUESO]]/(Tabla_master_rend[[#This Row],[Litros_Leche_Total]]*1.03*Tabla_master_rend[[#This Row],[%MP_Leche]]) -> 1.0034012 | AU27: =AR27*$CO$3 -> 7548 | AV27: 39.09 | AW27: 46.1 | AX27: 16 | AY27: =SUM(Tabla_master_rend[[#This Row],[Kg_Finos]:[Kg_Desmoldeo]]) -> 101.19 | AZ27: =+(Tabla_master_rend[[#This Row],[Kg_Finos]]+Tabla_master_rend[[#This Row],[Kg_Llenadora]]+Tabla_master_rend[[#This Row],[Kg_Desmoldeo]])/(Tabla_master_rend[[#This Row],[Kg_Queso_Blan]]) -> 0.0060106242 | BA27: 350 | BB27: =+Tabla_master_rend[[#This Row],[L_Agua]]/(Tabla_master_rend[[#This Row],[L_Agua]]+Tabla_master_rend[[#This Row],[Kg_SalidaSecadero]]) -> 0.020915501 | BC27: 2339 | BD27: 2270 | BE27: 16304 | BF27: =44*6.3 -> 277.2 | BG27: =8*6.3 -> 50.4 | BH27: 0 | BI27: =48*6.3 -> 302.4 | BJ27: 79 | BK27: 16384 | BL27: 3.14 | BM27: 174.71 | BN27: 15.15 | BO27: =+SUM(Tabla_master_rend[[#This Row],[B_altas]:[B_lab]])/Tabla_master_rend[[#This Row],[Kg_SalidaSecadero]] -> 0.043273926 | BP27: =+(Tabla_master_rend[[#This Row],[Kg_mer_env_real]]+Tabla_master_rend[[#This Row],[kg_mer_lab_real]])/Tabla_master_rend[[#This Row],[Kg_SalidaSecadero]] -> 0.011588135 | BQ27: =+Tabla_master_rend[[#This Row],[Merma_TOT]]/Tabla_master_rend[[#This Row],[Kg_Queso_Blan]] -> 0.038264492 | BR27: =+Tabla_master_rend[[#This Row],[kg_mer_lab_real]]+Tabla_master_rend[[#This Row],[Kg_mer_env_real]]+Tabla_master_rend[[#This Row],[Kg_rebaba]]+Tabla_master_rend[[#This Row],[L_Agua]]+Tabla_master_rend[[#This Row],[Kg_Desmoldeo]]+Tabla_master_rend[[#This Row],[Kg_Llenadora]]+Tabla_master_rend[[#This Row],[Kg_Finos]] -> 644.19 | BT27: =IF(+Tabla_master_rend[[#This Row],[Kg_Env_Total]]=0,0,Tabla_master_rend[[#This Row],[Kg_Env_Total]]-Tabla_master_rend[[#This Row],[Kg_SalidaSecadero]]) -> 0 | BU27: =+Tabla_master_rend[[#This Row],[Diferencia_Env_vs_Sec_kg]]/Tabla_master_rend[[#This Row],[Kg_SalidaSecadero]] -> 0 | BV27: =IFERROR(Tabla_master_rend[[#This Row],[Litros_Leche_Total]]*SUMIFS(tbl_PrecioLeche[PMV_eur_L],tbl_PrecioLeche[AñoMes],TEXT(Tabla_master_rend[[#This Row],[Fecha]],"yyyy-mm"),tbl_PrecioLeche[Tipo_Leche],Tabla_master_rend[[#This Row],[Tipo_Leche]]),"") -> 0 | BW27: =+(Tabla_master_rend[[#This Row],[Coste_Leche_€]]-Tabla_master_rend[[#This Row],[Kg_MG_Nata]]*$CO$3)/Tabla_master_rend[[#This Row],[Kg_Queso_Blan]] -> -0.44834659 | BX27: =SUM(Tabla_master_rend[[#This Row],[Kg_Finos]:[Kg_Desmoldeo]])+Tabla_master_rend[[#This Row],[L_Agua]]+SUM(Tabla_master_rend[[#This Row],[B_altas]:[B_lab]]) -> 1160.19 | BY27: =+BX27-Tabla_master_rend[[#This Row],[Merma_TOT]] -> 516 | BZ27: =+BY27/BX27 -> 0.44475474 | CA27: =+Tabla_master_rend[[#This Row],[Kg_Queso_Blan]]*$CA$1 -> 109.42873 | CB27: =+Tabla_master_rend[[#This Row],[Kg_Queso_Blan]]*($CB$1-$CA$1) -> 58.923165 | CC27: =+(Tabla_master_rend[[#This Row],[Kg_Queso_Blan]]-CA27-CB27)*$CC$1 -> 175.0018 | CD27: =+CA27+CB27+CC27 -> 343.3537 | CE27: =+CD27/Tabla_master_rend[[#This Row],[Kg_Queso_Blan]] -> 0.020395 | CF27: =+Tabla_master_rend[[#This Row],[Merma_TOT]]/Tabla_master_rend[[#This Row],[Kg_Queso_Blan]] -> 0.038264492 | CG27: =CD27-Tabla_master_rend[[#This Row],[Merma_TOT]] -> -300.8363 | CH27: {=-BR27 * IFERROR(INDEX('Precio Leche_EBITDA_Ventas'!$BD$87:$BD$110,MATCH(1,('Precio Leche_EBITDA_Ventas'!$AZ$87:$AZ$110=YEAR(A27))*('Precio Leche_EBITDA_Ventas'!$BB$87:$BB$110=C27),0)),1.3)} -> -2254.665 | CI27: =+CG27*$CM$2 -> -391.08719
A28: 45715 | B28: 2 | C28: =+UPPER(TEXT(Tabla_master_rend[[#This Row],[Fecha]],"MMM")) -> FEB | D28: =+UPPER(TEXT(Tabla_master_rend[[#This Row],[Fecha]],"ddd")) -> JU | E28: 270225146 | F28: VACA | G28: CREMOSO | H28: 17 | I28: =+Tabla_master_rend[[#This Row],[L_Leche_ent]]+Tabla_master_rend[[#This Row],[L_desn_ext]]+Tabla_master_rend[[#This Row],[L_cabra]]+Tabla_master_rend[[#This Row],[L_oveja]] -> 278752 | J28: 278752 | K28: 0.0388 | L28: 0.0336 | M28: =0.93*K28+0.74*L28+0.048 -> 0.108948 | N28: SI | O28: 0 | P28: 0 | Q28: 0 | R28: 2795 | T28: 234450 | U28: =+Tabla_master_rend[[#This Row],[L_suero Total]]/Tabla_master_rend[[#This Row],[Litros_Leche_Total]] -> 0.8410702 | V28: 0.0019 | W28: 0.0086 | X28: 234897 | Y28: 75463 | Z28: =IF(Tabla_master_rend[[#This Row],[L_suero para con]]=0,0,+Tabla_master_rend[[#This Row],[L_suero para con]]/Tabla_master_rend[[#This Row],[L_suero_con]]) -> 3.112744 | AA28: =+Tabla_master_rend[[#This Row],[L_suero Total]]-Tabla_master_rend[[#This Row],[L_suero para con]] -> -447 | AI28: =+Tabla_master_rend[[#This Row],[Kg_Finos]]+Tabla_master_rend[[#This Row],[Kg_Llenadora]]+Tabla_master_rend[[#This Row],[Kg_Desmoldeo]]+Tabla_master_rend[[#This Row],[L_Agua]]+Tabla_master_rend[[#This Row],[Kg_SalidaSecadero]] -> 33223.69 | AJ28: =+Tabla_master_rend[[#This Row],[Litros_Leche_Total]]/Tabla_master_rend[[#This Row],[Kg_Queso_Blan]] -> 8.3901577 | AK28: =+Tabla_master_rend[[#This Row],[Litros_Leche_Total]]/(Tabla_master_rend[[#This Row],[Kg_Queso_Blan]]-Tabla_master_rend[[#This Row],[Merma_TOT]]) -> 8.6391627 | AL28: =VLOOKUP(G28,REND_TARGET[#All],8,FALSE) -> 8.933873 | AM28: =(I28*1.03*Tabla_master_rend[[#This Row],[%MG_Leche]])+(I28*1.03*Tabla_master_rend[[#This Row],[%MP_Leche]]) -> 20787.094 | AN28: 0.2985 | AO28: 0.2305 | AP28: 0.5759 | AQ28: =+Tabla_master_rend[[#This Row],[Kg_Queso_Blan]]*Tabla_master_rend[[#This Row],[ES_QUESO]]/(Tabla_master_rend[[#This Row],[Kg_Solidos_leche]]) -> 0.92045203 | AR28: =R28*0.4 -> 1118 | AS28: =+(Tabla_master_rend[[#This Row],[Kg_Queso_Blan]]*Tabla_master_rend[[#This Row],[%MG_QUESO]]+(Tabla_master_rend[[#This Row],[Kg_MG_Nata]]))/(Tabla_master_rend[[#This Row],[Litros_Leche_Total]]*1.03*Tabla_master_rend[[#This Row],[%MG_Leche]]) -> 0.99059488 | AT28: =+Tabla_master_rend[[#This Row],[Kg_Queso_Blan]]*Tabla_master_rend[[#This Row],[%PT_QUESO]]/(Tabla_master_rend[[#This Row],[Litros_Leche_Total]]*1.03*Tabla_master_rend[[#This Row],[%MP_Leche]]) -> 0.79382414 | AU28: =AR28*$CO$3 -> 8385 | AV28: 55.69 | AW28: 155 | AX28: 15 | AY28: =SUM(Tabla_master_rend[[#This Row],[Kg_Finos]:[Kg_Desmoldeo]]) -> 225.69 | AZ28: =+(Tabla_master_rend[[#This Row],[Kg_Finos]]+Tabla_master_rend[[#This Row],[Kg_Llenadora]]+Tabla_master_rend[[#This Row],[Kg_Desmoldeo]])/(Tabla_master_rend[[#This Row],[Kg_Queso_Blan]]) -> 0.0067930444 | BA28: 520 | BB28: =+Tabla_master_rend[[#This Row],[L_Agua]]/(Tabla_master_rend[[#This Row],[L_Agua]]+Tabla_master_rend[[#This Row],[Kg_SalidaSecadero]]) -> 0.015758531 | BC28: 4704 | BD28: 4639 | BE28: 32585 | BF28: 0 | BG28: 0 | BH28: =3*6.5 -> 19.5 | BI28: =44*6.5 -> 286 | BJ28: 109 | BK28: 32478 | BL28: 3.25 | BM28: 177.72 | BN28: 30.94 | BO28: =+SUM(Tabla_master_rend[[#This Row],[B_altas]:[B_lab]])/Tabla_master_rend[[#This Row],[Kg_SalidaSecadero]] -> 0.012762485 | BP28: =+(Tabla_master_rend[[#This Row],[Kg_mer_env_real]]+Tabla_master_rend[[#This Row],[kg_mer_lab_real]])/Tabla_master_rend[[#This Row],[Kg_SalidaSecadero]] -> 0.0064246567 | BQ28: =+Tabla_master_rend[[#This Row],[Merma_TOT]]/Tabla_master_rend[[#This Row],[Kg_Queso_Blan]] -> 0.028822807 | BR28: =+Tabla_master_rend[[#This Row],[kg_mer_lab_real]]+Tabla_master_rend[[#This Row],[Kg_mer_env_real]]+Tabla_master_rend[[#This Row],[Kg_rebaba]]+Tabla_master_rend[[#This Row],[L_Agua]]+Tabla_master_rend[[#This Row],[Kg_Desmoldeo]]+Tabla_master_rend[[#This Row],[Kg_Llenadora]]+Tabla_master_rend[[#This Row],[Kg_Finos]] -> 957.6 | BT28: =IF(+Tabla_master_rend[[#This Row],[Kg_Env_Total]]=0,0,Tabla_master_rend[[#This Row],[Kg_Env_Total]]-Tabla_master_rend[[#This Row],[Kg_SalidaSecadero]]) -> 0 | BU28: =+Tabla_master_rend[[#This Row],[Diferencia_Env_vs_Sec_kg]]/Tabla_master_rend[[#This Row],[Kg_SalidaSecadero]] -> 0 | BV28: =IFERROR(Tabla_master_rend[[#This Row],[Litros_Leche_Total]]*SUMIFS(tbl_PrecioLeche[PMV_eur_L],tbl_PrecioLeche[AñoMes],TEXT(Tabla_master_rend[[#This Row],[Fecha]],"yyyy-mm"),tbl_PrecioLeche[Tipo_Leche],Tabla_master_rend[[#This Row],[Tipo_Leche]]),"") -> 0 | BW28: =+(Tabla_master_rend[[#This Row],[Coste_Leche_€]]-Tabla_master_rend[[#This Row],[Kg_MG_Nata]]*$CO$3)/Tabla_master_rend[[#This Row],[Kg_Queso_Blan]] -> -0.25238015 | BX28: =SUM(Tabla_master_rend[[#This Row],[Kg_Finos]:[Kg_Desmoldeo]])+Tabla_master_rend[[#This Row],[L_Agua]]+SUM(Tabla_master_rend[[#This Row],[B_altas]:[B_lab]]) -> 1160.19 | BY28: =+BX28-Tabla_master_rend[[#This Row],[Merma_TOT]] -> 202.59 | BZ28: =+BY28/BX28 -> 0.17461795 | CA28: =+Tabla_master_rend[[#This Row],[Kg_Queso_Blan]]*$CA$1 -> 215.95399 | CB28: =+Tabla_master_rend[[#This Row],[Kg_Queso_Blan]]*($CB$1-$CA$1) -> 116.28292 | CC28: =+(Tabla_master_rend[[#This Row],[Kg_Queso_Blan]]-CA28-CB28)*$CC$1 -> 345.36026 | CD28: =+CA28+CB28+CC28 -> 677.59716 | CE28: =+CD28/Tabla_master_rend[[#This Row],[Kg_Queso_Blan]] -> 0.020395 | CF28: =+Tabla_master_rend[[#This Row],[Merma_TOT]]/Tabla_master_rend[[#This Row],[Kg_Queso_Blan]] -> 0.028822807 | CG28: =CD28-Tabla_master_rend[[#This Row],[Merma_TOT]] -> -280.00284 | CH28: {=-BR28 * IFERROR(INDEX('Precio Leche_EBITDA_Ventas'!$BD$87:$BD$110,MATCH(1,('Precio Leche_EBITDA_Ventas'!$AZ$87:$AZ$110=YEAR(A28))*('Precio Leche_EBITDA_Ventas'!$BB$87:$BB$110=C28),0)),1.3)} -> -3351.6 | CI28: =+CG28*$CM$2 -> -364.0037
A29: 45719 | B29: 3 | C29: =+UPPER(TEXT(Tabla_master_rend[[#This Row],[Fecha]],"MMM")) -> MAR | D29: =+UPPER(TEXT(Tabla_master_rend[[#This Row],[Fecha]],"ddd")) -> LU | E29: 030325116 | F29: VACA | G29: EDAM_F | H29: 18 | I29: =+Tabla_master_rend[[#This Row],[L_Leche_ent]]+Tabla_master_rend[[#This Row],[L_desn_ext]]+Tabla_master_rend[[#This Row],[L_cabra]]+Tabla_master_rend[[#This Row],[L_oveja]] -> 296315 | J29: 296315 | K29: 0.0372 | L29: 0.0333 | M29: =0.93*K29+0.74*L29+0.048 -> 0.107238 | N29: NO | O29: 0 | P29: 0 | Q29: 0 | R29: 9757 | T29: 246380 | U29: =+Tabla_master_rend[[#This Row],[L_suero Total]]/Tabla_master_rend[[#This Row],[Litros_Leche_Total]] -> 0.83148001 | V29: 0.0009 | W29: 0.009 | X29: 164037 | Y29: 51642 | Z29: =IF(Tabla_master_rend[[#This Row],[L_suero para con]]=0,0,+Tabla_master_rend[[#This Row],[L_suero para con]]/Tabla_master_rend[[#This Row],[L_suero_con]]) -> 3.1764262 | AA29: =+Tabla_master_rend[[#This Row],[L_suero Total]]-Tabla_master_rend[[#This Row],[L_suero para con]] -> 82343 | AI29: =+Tabla_master_rend[[#This Row],[Kg_Finos]]+Tabla_master_rend[[#This Row],[Kg_Llenadora]]+Tabla_master_rend[[#This Row],[Kg_Desmoldeo]]+Tabla_master_rend[[#This Row],[L_Agua]]+Tabla_master_rend[[#This Row],[Kg_SalidaSecadero]] -> 31582.31 | AJ29: =+Tabla_master_rend[[#This Row],[Litros_Leche_Total]]/Tabla_master_rend[[#This Row],[Kg_Queso_Blan]] -> 9.3823093 | AK29: =+Tabla_master_rend[[#This Row],[Litros_Leche_Total]]/(Tabla_master_rend[[#This Row],[Kg_Queso_Blan]]-Tabla_master_rend[[#This Row],[Merma_TOT]]) -> 9.7080238 | AL29: =VLOOKUP(G29,REND_TARGET[#All],8,FALSE) -> 9.80785 | AM29: =(I29*1.03*Tabla_master_rend[[#This Row],[%MG_Leche]])+(I29*1.03*Tabla_master_rend[[#This Row],[%MP_Leche]]) -> 21516.914 | AN29: 0.2256 | AO29: 0.2523 | AP29: 0.5324 | AQ29: =+Tabla_master_rend[[#This Row],[Kg_Queso_Blan]]*Tabla_master_rend[[#This Row],[ES_QUESO]]/(Tabla_master_rend[[#This Row],[Kg_Solidos_leche]]) -> 0.78145138 | AR29: =R29*0.4 -> 3902.8 | AS29: =+(Tabla_master_rend[[#This Row],[Kg_Queso_Blan]]*Tabla_master_rend[[#This Row],[%MG_QUESO]]+(Tabla_master_rend[[#This Row],[Kg_MG_Nata]]))/(Tabla_master_rend[[#This Row],[Litros_Leche_Total]]*1.03*Tabla_master_rend[[#This Row],[%MG_Leche]]) -> 0.97130106 | AT29: =+Tabla_master_rend[[#This Row],[Kg_Queso_Blan]]*Tabla_master_rend[[#This Row],[%PT_QUESO]]/(Tabla_master_rend[[#This Row],[Litros_Leche_Total]]*1.03*Tabla_master_rend[[#This Row],[%MP_Leche]]) -> 0.78401803 | AU29: =AR29*$CO$3 -> 29271 | AV29: 66.81 | AW29: 86.6 | AX29: 168.9 | AY29: =SUM(Tabla_master_rend[[#This Row],[Kg_Finos]:[Kg_Desmoldeo]]) -> 322.31 | AZ29: =+(Tabla_master_rend[[#This Row],[Kg_Finos]]+Tabla_master_rend[[#This Row],[Kg_Llenadora]]+Tabla_master_rend[[#This Row],[Kg_Desmoldeo]])/(Tabla_master_rend[[#This Row],[Kg_Queso_Blan]]) -> 0.010205397 | BA29: 580 | BB29: =+Tabla_master_rend[[#This Row],[L_Agua]]/(Tabla_master_rend[[#This Row],[L_Agua]]+Tabla_master_rend[[#This Row],[Kg_SalidaSecadero]]) -> 0.018554063 | BC29: 4412 | BD29: 4101 | BE29: 29294 | BF29: =12*6.4 -> 76.8 | BG29: =64*6.4 -> 409.6 | BH29: 0 | BI29: =231*6.4 -> 1478.4 | BJ29: 105 | BK29: 30680 | BL29: 5.26 | BM29: 128.61 | BN29: 23.44 | BO29: =+SUM(Tabla_master_rend[[#This Row],[B_altas]:[B_lab]])/Tabla_master_rend[[#This Row],[Kg_SalidaSecadero]] -> 0.067464146 | BP29: =+(Tabla_master_rend[[#This Row],[Kg_mer_env_real]]+Tabla_master_rend[[#This Row],[kg_mer_lab_real]])/Tabla_master_rend[[#This Row],[Kg_SalidaSecadero]] -> 0.0049559974 | BQ29: =+Tabla_master_rend[[#This Row],[Merma_TOT]]/Tabla_master_rend[[#This Row],[Kg_Queso_Blan]] -> 0.033551061 | BR29: =+Tabla_master_rend[[#This Row],[kg_mer_lab_real]]+Tabla_master_rend[[#This Row],[Kg_mer_env_real]]+Tabla_master_rend[[#This Row],[Kg_rebaba]]+Tabla_master_rend[[#This Row],[L_Agua]]+Tabla_master_rend[[#This Row],[Kg_Desmoldeo]]+Tabla_master_rend[[#This Row],[Kg_Llenadora]]+Tabla_master_rend[[#This Row],[Kg_Finos]] -> 1059.62 | BT29: =IF(+Tabla_master_rend[[#This Row],[Kg_Env_Total]]=0,0,Tabla_master_rend[[#This Row],[Kg_Env_Total]]-Tabla_master_rend[[#This Row],[Kg_SalidaSecadero]]) -> 0 | BU29: =+Tabla_master_rend[[#This Row],[Diferencia_Env_vs_Sec_kg]]/Tabla_master_rend[[#This Row],[Kg_SalidaSecadero]] -> 0 | BV29: =IFERROR(Tabla_master_rend[[#This Row],[Litros_Leche_Total]]*SUMIFS(tbl_PrecioLeche[PMV_eur_L],tbl_PrecioLeche[AñoMes],TEXT(Tabla_master_rend[[#This Row],[Fecha]],"yyyy-mm"),tbl_PrecioLeche[Tipo_Leche],Tabla_master_rend[[#This Row],[Tipo_Leche]]),"") -> 0 | BW29: =+(Tabla_master_rend[[#This Row],[Coste_Leche_€]]-Tabla_master_rend[[#This Row],[Kg_MG_Nata]]*$CO$3)/Tabla_master_rend[[#This Row],[Kg_Queso_Blan]] -> -0.92681631 | BX29: =SUM(Tabla_master_rend[[#This Row],[Kg_Finos]:[Kg_Desmoldeo]])+Tabla_master_rend[[#This Row],[L_Agua]]+SUM(Tabla_master_rend[[#This Row],[B_altas]:[B_lab]]) -> 2972.11 | BY29: =+BX29-Tabla_master_rend[[#This Row],[Merma_TOT]] -> 1912.49 | BZ29: =+BY29/BX29 -> 0.64347888 | CA29: =+Tabla_master_rend[[#This Row],[Kg_Queso_Blan]]*$CA$1 -> 205.28501 | CB29: =+Tabla_master_rend[[#This Row],[Kg_Queso_Blan]]*($CB$1-$CA$1) -> 110.53809 | CC29: =+(Tabla_master_rend[[#This Row],[Kg_Queso_Blan]]-CA29-CB29)*$CC$1 -> 328.29811 | CD29: =+CA29+CB29+CC29 -> 644.12121 | CE29: =+CD29/Tabla_master_rend[[#This Row],[Kg_Queso_Blan]] -> 0.020395 | CF29: =+Tabla_master_rend[[#This Row],[Merma_TOT]]/Tabla_master_rend[[#This Row],[Kg_Queso_Blan]] -> 0.033551061 | CG29: =CD29-Tabla_master_rend[[#This Row],[Merma_TOT]] -> -415.49879 | CH29: {=-BR29 * IFERROR(INDEX('Precio Leche_EBITDA_Ventas'!$BD$87:$BD$110,MATCH(1,('Precio Leche_EBITDA_Ventas'!$AZ$87:$AZ$110=YEAR(A29))*('Precio Leche_EBITDA_Ventas'!$BB$87:$BB$110=C29),0)),1.3)} -> -3708.67 | CI29: =+CG29*$CM$2 -> -540.14842
A30: 45721 | B30: 3 | C30: =+UPPER(TEXT(Tabla_master_rend[[#This Row],[Fecha]],"MMM")) -> MAR | D30: =+UPPER(TEXT(Tabla_master_rend[[#This Row],[Fecha]],"ddd")) -> MI | E30: 050325126 | F30: VACA | G30: GOUDA_F | H30: 16 | I30: =+Tabla_master_rend[[#This Row],[L_Leche_ent]]+Tabla_master_rend[[#This Row],[L_desn_ext]]+Tabla_master_rend[[#This Row],[L_cabra]]+Tabla_master_rend[[#This Row],[L_oveja]] -> 253833 | J30: 253833 | K30: 0.0378 | L30: 0.0334 | M30: =0.93*K30+0.74*L30+0.048 -> 0.10787 | N30: NO | O30: 0 | P30: 0 | Q30: 0 | R30: 3326 | T30: 219760 | U30: =+Tabla_master_rend[[#This Row],[L_suero Total]]/Tabla_master_rend[[#This Row],[Litros_Leche_Total]] -> 0.86576607 | V30: 0.0023 | W30: 0.009 | X30: 125676 | Y30: 38654 | Z30: =IF(Tabla_master_rend[[#This Row],[L_suero para con]]=0,0,+Tabla_master_rend[[#This Row],[L_suero para con]]/Tabla_master_rend[[#This Row],[L_suero_con]]) -> 3.2513065 | AA30: =+Tabla_master_rend[[#This Row],[L_suero Total]]-Tabla_master_rend[[#This Row],[L_suero para con]] -> 94084 | AI30: =+Tabla_master_rend[[#This Row],[Kg_Finos]]+Tabla_master_rend[[#This Row],[Kg_Llenadora]]+Tabla_master_rend[[#This Row],[Kg_Desmoldeo]]+Tabla_master_rend[[#This Row],[L_Agua]]+Tabla_master_rend[[#This Row],[Kg_SalidaSecadero]] -> 28812.4 | AJ30: =+Tabla_master_rend[[#This Row],[Litros_Leche_Total]]/Tabla_master_rend[[#This Row],[Kg_Queso_Blan]] -> 8.8098527 | AK30: =+Tabla_master_rend[[#This Row],[Litros_Leche_Total]]/(Tabla_master_rend[[#This Row],[Kg_Queso_Blan]]-Tabla_master_rend[[#This Row],[Merma_TOT]]) -> 9.054279 | AL30: =VLOOKUP(G30,REND_TARGET[#All],8,FALSE) -> 9.354943 | AM30: =(I30*1.03*Tabla_master_rend[[#This Row],[%MG_Leche]])+(I30*1.03*Tabla_master_rend[[#This Row],[%MP_Leche]]) -> 18615.097 | AN30: 0.2881 | AO30: 0.2382 | AP30: 0.5749 | AQ30: =+Tabla_master_rend[[#This Row],[Kg_Queso_Blan]]*Tabla_master_rend[[#This Row],[ES_QUESO]]/(Tabla_master_rend[[#This Row],[Kg_Solidos_leche]]) -> 0.88982877 | AR30: =R30*0.4 -> 1330.4 | AS30: =+(Tabla_master_rend[[#This Row],[Kg_Queso_Blan]]*Tabla_master_rend[[#This Row],[%MG_QUESO]]+(Tabla_master_rend[[#This Row],[Kg_MG_Nata]]))/(Tabla_master_rend[[#This Row],[Litros_Leche_Total]]*1.03*Tabla_master_rend[[#This Row],[%MG_Leche]]) -> 0.97455344 | AT30: =+Tabla_master_rend[[#This Row],[Kg_Queso_Blan]]*Tabla_master_rend[[#This Row],[%PT_QUESO]]/(Tabla_master_rend[[#This Row],[Litros_Leche_Total]]*1.03*Tabla_master_rend[[#This Row],[%MP_Leche]]) -> 0.78594005 | AU30: =AR30*$CO$3 -> 9978 | AV30: 47.9 | AW30: 67.4 | AX30: 3.1 | AY30: =SUM(Tabla_master_rend[[#This Row],[Kg_Finos]:[Kg_Desmoldeo]]) -> 118.4 | AZ30: =+(Tabla_master_rend[[#This Row],[Kg_Finos]]+Tabla_master_rend[[#This Row],[Kg_Llenadora]]+Tabla_master_rend[[#This Row],[Kg_Desmoldeo]])/(Tabla_master_rend[[#This Row],[Kg_Queso_Blan]]) -> 0.0041093418 | BA30: 560 | BB30: =+Tabla_master_rend[[#This Row],[L_Agua]]/(Tabla_master_rend[[#This Row],[L_Agua]]+Tabla_master_rend[[#This Row],[Kg_SalidaSecadero]]) -> 0.019516275 | BC30: 3937 | BD30: 3897 | BE30: 28439 | BF30: =78*6.4 -> 499.2 | BG30: =7*6.4 -> 44.8 | BH30: 0 | BI30: =18*6.4 -> 115.2 | BJ30: 94 | BK30: 28134 | BL30: 0 | BM30: 81.33 | BN30: 18.08 | BO30: =+SUM(Tabla_master_rend[[#This Row],[B_altas]:[B_lab]])/Tabla_master_rend[[#This Row],[Kg_SalidaSecadero]] -> 0.026771877 | BP30: =+(Tabla_master_rend[[#This Row],[Kg_mer_env_real]]+Tabla_master_rend[[#This Row],[kg_mer_lab_real]])/Tabla_master_rend[[#This Row],[Kg_SalidaSecadero]] -> 0.0035334471 | BQ30: =+Tabla_master_rend[[#This Row],[Merma_TOT]]/Tabla_master_rend[[#This Row],[Kg_Queso_Blan]] -> 0.026995669 | BR30: =+Tabla_master_rend[[#This Row],[kg_mer_lab_real]]+Tabla_master_rend[[#This Row],[Kg_mer_env_real]]+Tabla_master_rend[[#This Row],[Kg_rebaba]]+Tabla_master_rend[[#This Row],[L_Agua]]+Tabla_master_rend[[#This Row],[Kg_Desmoldeo]]+Tabla_master_rend[[#This Row],[Kg_Llenadora]]+Tabla_master_rend[[#This Row],[Kg_Finos]] -> 777.81 | BT30: =IF(+Tabla_master_rend[[#This Row],[Kg_Env_Total]]=0,0,Tabla_master_rend[[#This Row],[Kg_Env_Total]]-Tabla_master_rend[[#This Row],[Kg_SalidaSecadero]]) -> 0 | BU30: =+Tabla_master_rend[[#This Row],[Diferencia_Env_vs_Sec_kg]]/Tabla_master_rend[[#This Row],[Kg_SalidaSecadero]] -> 0 | BV30: =IFERROR(Tabla_master_rend[[#This Row],[Litros_Leche_Total]]*SUMIFS(tbl_PrecioLeche[PMV_eur_L],tbl_PrecioLeche[AñoMes],TEXT(Tabla_master_rend[[#This Row],[Fecha]],"yyyy-mm"),tbl_PrecioLeche[Tipo_Leche],Tabla_master_rend[[#This Row],[Tipo_Leche]]),"") -> 0 | BW30: =+(Tabla_master_rend[[#This Row],[Coste_Leche_€]]-Tabla_master_rend[[#This Row],[Kg_MG_Nata]]*$CO$3)/Tabla_master_rend[[#This Row],[Kg_Queso_Blan]] -> -0.34630923 | BX30: =SUM(Tabla_master_rend[[#This Row],[Kg_Finos]:[Kg_Desmoldeo]])+Tabla_master_rend[[#This Row],[L_Agua]]+SUM(Tabla_master_rend[[#This Row],[B_altas]:[B_lab]]) -> 1431.6 | BY30: =+BX30-Tabla_master_rend[[#This Row],[Merma_TOT]] -> 653.79 | BZ30: =+BY30/BX30 -> 0.45668483 | CA30: =+Tabla_master_rend[[#This Row],[Kg_Queso_Blan]]*$CA$1 -> 187.2806 | CB30: =+Tabla_master_rend[[#This Row],[Kg_Queso_Blan]]*($CB$1-$CA$1) -> 100.8434 | CC30: =+(Tabla_master_rend[[#This Row],[Kg_Queso_Blan]]-CA30-CB30)*$CC$1 -> 299.5049 | CD30: =+CA30+CB30+CC30 -> 587.6289 | CE30: =+CD30/Tabla_master_rend[[#This Row],[Kg_Queso_Blan]] -> 0.020395 | CF30: =+Tabla_master_rend[[#This Row],[Merma_TOT]]/Tabla_master_rend[[#This Row],[Kg_Queso_Blan]] -> 0.026995669 | CG30: =CD30-Tabla_master_rend[[#This Row],[Merma_TOT]] -> -190.1811 | CH30: {=-BR30 * IFERROR(INDEX('Precio Leche_EBITDA_Ventas'!$BD$87:$BD$110,MATCH(1,('Precio Leche_EBITDA_Ventas'!$AZ$87:$AZ$110=YEAR(A30))*('Precio Leche_EBITDA_Ventas'!$BB$87:$BB$110=C30),0)),1.3)} -> -2722.335 | CI30: =+CG30*$CM$2 -> -247.23543
A31: 45722 | B31: 3 | C31: =+UPPER(TEXT(Tabla_master_rend[[#This Row],[Fecha]],"MMM")) -> MAR | D31: =+UPPER(TEXT(Tabla_master_rend[[#This Row],[Fecha]],"ddd")) -> JU | E31: 060325026 | F31: VACA | G31: GOUDA | H31: 17 | I31: =+Tabla_master_rend[[#This Row],[L_Leche_ent]]+Tabla_master_rend[[#This Row],[L_desn_ext]]+Tabla_master_rend[[#This Row],[L_cabra]]+Tabla_master_rend[[#This Row],[L_oveja]] -> 249248 | J31: 249248 | K31: 0.039 | L31: 0.0336 | M31: =0.93*K31+0.74*L31+0.048 -> 0.109134 | N31: SI | O31: 0 | P31: 0 | Q31: 0 | R31: 2980 | T31: 230310 | U31: =+Tabla_master_rend[[#This Row],[L_suero Total]]/Tabla_master_rend[[#This Row],[Litros_Leche_Total]] -> 0.92401945 | V31: 0.002 | W31: 0.0092 | X31: 231580 | Y31: 78141 | Z31: =IF(Tabla_master_rend[[#This Row],[L_suero para con]]=0,0,+Tabla_master_rend[[#This Row],[L_suero para con]]/Tabla_master_rend[[#This Row],[L_suero_con]]) -> 2.9636171 | AA31: =+Tabla_master_rend[[#This Row],[L_suero Total]]-Tabla_master_rend[[#This Row],[L_suero para con]] -> -1270 | AI31: =+Tabla_master_rend[[#This Row],[Kg_Finos]]+Tabla_master_rend[[#This Row],[Kg_Llenadora]]+Tabla_master_rend[[#This Row],[Kg_Desmoldeo]]+Tabla_master_rend[[#This Row],[L_Agua]]+Tabla_master_rend[[#This Row],[Kg_SalidaSecadero]] -> 30576.2 | AJ31: =+Tabla_master_rend[[#This Row],[Litros_Leche_Total]]/Tabla_master_rend[[#This Row],[Kg_Queso_Blan]] -> 8.1516997 | AK31: =+Tabla_master_rend[[#This Row],[Litros_Leche_Total]]/(Tabla_master_rend[[#This Row],[Kg_Queso_Blan]]-Tabla_master_rend[[#This Row],[Merma_TOT]]) -> 8.4789738 | AL31: =VLOOKUP(G31,REND_TARGET[#All],8,FALSE) -> 8.494317 | AM31: =(I31*1.03*Tabla_master_rend[[#This Row],[%MG_Leche]])+(I31*1.03*Tabla_master_rend[[#This Row],[%MP_Leche]]) -> 18638.267 | AN31: 0.2856 | AO31: 0.2327 | AP31: 0.5684 | AQ31: =+Tabla_master_rend[[#This Row],[Kg_Queso_Blan]]*Tabla_master_rend[[#This Row],[ES_QUESO]]/(Tabla_master_rend[[#This Row],[Kg_Solidos_leche]]) -> 0.93246395 | AR31: =R31*0.4 -> 1192 | AS31: =+(Tabla_master_rend[[#This Row],[Kg_Queso_Blan]]*Tabla_master_rend[[#This Row],[%MG_QUESO]]+(Tabla_master_rend[[#This Row],[Kg_MG_Nata]]))/(Tabla_master_rend[[#This Row],[Litros_Leche_Total]]*1.03*Tabla_master_rend[[#This Row],[%MG_Leche]]) -> 0.99123783 | AT31: =+Tabla_master_rend[[#This Row],[Kg_Queso_Blan]]*Tabla_master_rend[[#This Row],[%PT_QUESO]]/(Tabla_master_rend[[#This Row],[Litros_Leche_Total]]*1.03*Tabla_master_rend[[#This Row],[%MP_Leche]]) -> 0.82484379 | AU31: =AR31*$CO$3 -> 8940 | AV31: 68.6 | AW31: 109.1 | AX31: 54.5 | AY31: =SUM(Tabla_master_rend[[#This Row],[Kg_Finos]:[Kg_Desmoldeo]]) -> 232.2 | AZ31: =+(Tabla_master_rend[[#This Row],[Kg_Finos]]+Tabla_master_rend[[#This Row],[Kg_Llenadora]]+Tabla_master_rend[[#This Row],[Kg_Desmoldeo]])/(Tabla_master_rend[[#This Row],[Kg_Queso_Blan]]) -> 0.0075941418 | BA31: 825 | BB31: =+Tabla_master_rend[[#This Row],[L_Agua]]/(Tabla_master_rend[[#This Row],[L_Agua]]+Tabla_master_rend[[#This Row],[Kg_SalidaSecadero]]) -> 0.027188241 | BC31: 4273 | BD31: 4240 | BE31: 30139 | BF31: =7*6.2 -> 43.4 | BG31: 0 | BH31: =2*6.2 -> 12.4 | BI31: =15*6.2 -> 93 | BJ31: 93 | BK31: 29519 | BL31: 0 | BM31: 93.53 | BN31: 29.46 | BO31: =+SUM(Tabla_master_rend[[#This Row],[B_altas]:[B_lab]])/Tabla_master_rend[[#This Row],[Kg_SalidaSecadero]] -> 0.0081913344 | BP31: =+(Tabla_master_rend[[#This Row],[Kg_mer_env_real]]+Tabla_master_rend[[#This Row],[kg_mer_lab_real]])/Tabla_master_rend[[#This Row],[Kg_SalidaSecadero]] -> 0.0041664691 | BQ31: =+Tabla_master_rend[[#This Row],[Merma_TOT]]/Tabla_master_rend[[#This Row],[Kg_Queso_Blan]] -> 0.038598322 | BR31: =+Tabla_master_rend[[#This Row],[kg_mer_lab_real]]+Tabla_master_rend[[#This Row],[Kg_mer_env_real]]+Tabla_master_rend[[#This Row],[Kg_rebaba]]+Tabla_master_rend[[#This Row],[L_Agua]]+Tabla_master_rend[[#This Row],[Kg_Desmoldeo]]+Tabla_master_rend[[#This Row],[Kg_Llenadora]]+Tabla_master_rend[[#This Row],[Kg_Finos]] -> 1180.19 | BT31: =IF(+Tabla_master_rend[[#This Row],[Kg_Env_Total]]=0,0,Tabla_master_rend[[#This Row],[Kg_Env_Total]]-Tabla_master_rend[[#This Row],[Kg_SalidaSecadero]]) -> 0 | BU31: =+Tabla_master_rend[[#This Row],[Diferencia_Env_vs_Sec_kg]]/Tabla_master_rend[[#This Row],[Kg_SalidaSecadero]] -> 0 | BV31: =IFERROR(Tabla_master_rend[[#This Row],[Litros_Leche_Total]]*SUMIFS(tbl_PrecioLeche[PMV_eur_L],tbl_PrecioLeche[AñoMes],TEXT(Tabla_master_rend[[#This Row],[Fecha]],"yyyy-mm"),tbl_PrecioLeche[Tipo_Leche],Tabla_master_rend[[#This Row],[Tipo_Leche]]),"") -> 0 | BW31: =+(Tabla_master_rend[[#This Row],[Coste_Leche_€]]-Tabla_master_rend[[#This Row],[Kg_MG_Nata]]*$CO$3)/Tabla_master_rend[[#This Row],[Kg_Queso_Blan]] -> -0.29238427 | BX31: =SUM(Tabla_master_rend[[#This Row],[Kg_Finos]:[Kg_Desmoldeo]])+Tabla_master_rend[[#This Row],[L_Agua]]+SUM(Tabla_master_rend[[#This Row],[B_altas]:[B_lab]]) -> 1299 | BY31: =+BX31-Tabla_master_rend[[#This Row],[Merma_TOT]] -> 118.81 | BZ31: =+BY31/BX31 -> 0.091462664 | CA31: =+Tabla_master_rend[[#This Row],[Kg_Queso_Blan]]*$CA$1 -> 198.7453 | CB31: =+Tabla_master_rend[[#This Row],[Kg_Queso_Blan]]*($CB$1-$CA$1) -> 107.0167 | CC31: =+(Tabla_master_rend[[#This Row],[Kg_Queso_Blan]]-CA31-CB31)*$CC$1 -> 317.8396 | CD31: =+CA31+CB31+CC31 -> 623.6016 | CE31: =+CD31/Tabla_master_rend[[#This Row],[Kg_Queso_Blan]] -> 0.020395 | CF31: =+Tabla_master_rend[[#This Row],[Merma_TOT]]/Tabla_master_rend[[#This Row],[Kg_Queso_Blan]] -> 0.038598322 | CG31: =CD31-Tabla_master_rend[[#This Row],[Merma_TOT]] -> -556.5884 | CH31: {=-BR31 * IFERROR(INDEX('Precio Leche_EBITDA_Ventas'!$BD$87:$BD$110,MATCH(1,('Precio Leche_EBITDA_Ventas'!$AZ$87:$AZ$110=YEAR(A31))*('Precio Leche_EBITDA_Ventas'!$BB$87:$BB$110=C31),0)),1.3)} -> -4130.665 | CI31: =+CG31*$CM$2 -> -723.56492
A32: 45726 | B32: 3 | C32: =+UPPER(TEXT(Tabla_master_rend[[#This Row],[Fecha]],"MMM")) -> MAR | D32: =+UPPER(TEXT(Tabla_master_rend[[#This Row],[Fecha]],"ddd")) -> LU | E32: 100325326 | F32: VACA | G32: GOUDA_F | H32: 18 | I32: =+Tabla_master_rend[[#This Row],[L_Leche_ent]]+Tabla_master_rend[[#This Row],[L_desn_ext]]+Tabla_master_rend[[#This Row],[L_cabra]]+Tabla_master_rend[[#This Row],[L_oveja]] -> 287787 | J32: 287787 | K32: 0.0363 | L32: 0.0333 | M32: =0.93*K32+0.74*L32+0.048 -> 0.106401 | N32: NO | O32: 0 | P32: 0 | Q32: 0 | R32: 2478 | T32: 239540 | U32: =+Tabla_master_rend[[#This Row],[L_suero Total]]/Tabla_master_rend[[#This Row],[Litros_Leche_Total]] -> 0.8323517 | V32: 0.0021 | W32: 0.0089 | X32: 239835 | Y32: 80678 | Z32: =IF(Tabla_master_rend[[#This Row],[L_suero para con]]=0,0,+Tabla_master_rend[[#This Row],[L_suero para con]]/Tabla_master_rend[[#This Row],[L_suero_con]]) -> 2.9727435 | AA32: =+Tabla_master_rend[[#This Row],[L_suero Total]]-Tabla_master_rend[[#This Row],[L_suero para con]] -> -295 | AI32: =+Tabla_master_rend[[#This Row],[Kg_Finos]]+Tabla_master_rend[[#This Row],[Kg_Llenadora]]+Tabla_master_rend[[#This Row],[Kg_Desmoldeo]]+Tabla_master_rend[[#This Row],[L_Agua]]+Tabla_master_rend[[#This Row],[Kg_SalidaSecadero]] -> 32417.24 | AJ32: =+Tabla_master_rend[[#This Row],[Litros_Leche_Total]]/Tabla_master_rend[[#This Row],[Kg_Queso_Blan]] -> 8.8775911 | AK32: =+Tabla_master_rend[[#This Row],[Litros_Leche_Total]]/(Tabla_master_rend[[#This Row],[Kg_Queso_Blan]]-Tabla_master_rend[[#This Row],[Merma_TOT]]) -> 9.0427369 | AL32: =VLOOKUP(G32,REND_TARGET[#All],8,FALSE) -> 9.354943 | AM32: =(I32*1.03*Tabla_master_rend[[#This Row],[%MG_Leche]])+(I32*1.03*Tabla_master_rend[[#This Row],[%MP_Leche]]) -> 20630.874 | AN32: 0.2909 | AO32: 0.2385 | AP32: 0.5782 | AQ32: =+Tabla_master_rend[[#This Row],[Kg_Queso_Blan]]*Tabla_master_rend[[#This Row],[ES_QUESO]]/(Tabla_master_rend[[#This Row],[Kg_Solidos_leche]]) -> 0.90852417 | AR32: =R32*0.4 -> 991.2 | AS32: =+(Tabla_master_rend[[#This Row],[Kg_Queso_Blan]]*Tabla_master_rend[[#This Row],[%MG_QUESO]]+(Tabla_master_rend[[#This Row],[Kg_MG_Nata]]))/(Tabla_master_rend[[#This Row],[Litros_Leche_Total]]*1.03*Tabla_master_rend[[#This Row],[%MG_Leche]]) -> 0.96852315 | AT32: =+Tabla_master_rend[[#This Row],[Kg_Queso_Blan]]*Tabla_master_rend[[#This Row],[%PT_QUESO]]/(Tabla_master_rend[[#This Row],[Litros_Leche_Total]]*1.03*Tabla_master_rend[[#This Row],[%MP_Leche]]) -> 0.78327053 | AU32: =AR32*$CO$3 -> 7434 | AV32: 37.04 | AW32: 124.3 | AX32: 19.9 | AY32: =SUM(Tabla_master_rend[[#This Row],[Kg_Finos]:[Kg_Desmoldeo]]) -> 181.24 | AZ32: =+(Tabla_master_rend[[#This Row],[Kg_Finos]]+Tabla_master_rend[[#This Row],[Kg_Llenadora]]+Tabla_master_rend[[#This Row],[Kg_Desmoldeo]])/(Tabla_master_rend[[#This Row],[Kg_Queso_Blan]]) -> 0.0055908523 | BA32: 295 | BB32: =+Tabla_master_rend[[#This Row],[L_Agua]]/(Tabla_master_rend[[#This Row],[L_Agua]]+Tabla_master_rend[[#This Row],[Kg_SalidaSecadero]]) -> 0.0091512595 | BC32: 4497 | BD32: 4462 | BE32: 32019 | BF32: =10*5.8 -> 58 | BG32: =10*5.8 -> 58 | BH32: 0 | BI32: =8*5.8 -> 46.4 | BJ32: 112 | BK32: 31941 | BL32: 1.41 | BM32: 94.58 | BN32: 19.8 | BO32: =+SUM(Tabla_master_rend[[#This Row],[B_altas]:[B_lab]])/Tabla_master_rend[[#This Row],[Kg_SalidaSecadero]] -> 0.0085908394 | BP32: =+(Tabla_master_rend[[#This Row],[Kg_mer_env_real]]+Tabla_master_rend[[#This Row],[kg_mer_lab_real]])/Tabla_master_rend[[#This Row],[Kg_SalidaSecadero]] -> 0.0035809774 | BQ32: =+Tabla_master_rend[[#This Row],[Merma_TOT]]/Tabla_master_rend[[#This Row],[Kg_Queso_Blan]] -> 0.018262813 | BR32: =+Tabla_master_rend[[#This Row],[kg_mer_lab_real]]+Tabla_master_rend[[#This Row],[Kg_mer_env_real]]+Tabla_master_rend[[#This Row],[Kg_rebaba]]+Tabla_master_rend[[#This Row],[L_Agua]]+Tabla_master_rend[[#This Row],[Kg_Desmoldeo]]+Tabla_master_rend[[#This Row],[Kg_Llenadora]]+Tabla_master_rend[[#This Row],[Kg_Finos]] -> 592.03 | BT32: =IF(+Tabla_master_rend[[#This Row],[Kg_Env_Total]]=0,0,Tabla_master_rend[[#This Row],[Kg_Env_Total]]-Tabla_master_rend[[#This Row],[Kg_SalidaSecadero]]) -> 0 | BU32: =+Tabla_master_rend[[#This Row],[Diferencia_Env_vs_Sec_kg]]/Tabla_master_rend[[#This Row],[Kg_SalidaSecadero]] -> 0 | BV32: =IFERROR(Tabla_master_rend[[#This Row],[Litros_Leche_Total]]*SUMIFS(tbl_PrecioLeche[PMV_eur_L],tbl_PrecioLeche[AñoMes],TEXT(Tabla_master_rend[[#This Row],[Fecha]],"yyyy-mm"),tbl_PrecioLeche[Tipo_Leche],Tabla_master_rend[[#This Row],[Tipo_Leche]]),"") -> 0 | BW32: =+(Tabla_master_rend[[#This Row],[Coste_Leche_€]]-Tabla_master_rend[[#This Row],[Kg_MG_Nata]]*$CO$3)/Tabla_master_rend[[#This Row],[Kg_Queso_Blan]] -> -0.22932242 | BX32: =SUM(Tabla_master_rend[[#This Row],[Kg_Finos]:[Kg_Desmoldeo]])+Tabla_master_rend[[#This Row],[L_Agua]]+SUM(Tabla_master_rend[[#This Row],[B_altas]:[B_lab]]) -> 750.64 | BY32: =+BX32-Tabla_master_rend[[#This Row],[Merma_TOT]] -> 158.61 | BZ32: =+BY32/BX32 -> 0.21129969 | CA32: =+Tabla_master_rend[[#This Row],[Kg_Queso_Blan]]*$CA$1 -> 210.71206 | CB32: =+Tabla_master_rend[[#This Row],[Kg_Queso_Blan]]*($CB$1-$CA$1) -> 113.46034 | CC32: =+(Tabla_master_rend[[#This Row],[Kg_Queso_Blan]]-CA32-CB32)*$CC$1 -> 336.97721 | CD32: =+CA32+CB32+CC32 -> 661.14961 | CE32: =+CD32/Tabla_master_rend[[#This Row],[Kg_Queso_Blan]] -> 0.020395 | CF32: =+Tabla_master_rend[[#This Row],[Merma_TOT]]/Tabla_master_rend[[#This Row],[Kg_Queso_Blan]] -> 0.018262813 | CG32: =CD32-Tabla_master_rend[[#This Row],[Merma_TOT]] -> 69.11961 | CH32: {=-BR32 * IFERROR(INDEX('Precio Leche_EBITDA_Ventas'!$BD$87:$BD$110,MATCH(1,('Precio Leche_EBITDA_Ventas'!$AZ$87:$AZ$110=YEAR(A32))*('Precio Leche_EBITDA_Ventas'!$BB$87:$BB$110=C32),0)),1.3)} -> -2072.105 | CI32: =+CG32*$CM$2 -> 89.855493
A33: 45727 | B33: 3 | C33: =+UPPER(TEXT(Tabla_master_rend[[#This Row],[Fecha]],"MMM")) -> MAR | D33: =+UPPER(TEXT(Tabla_master_rend[[#This Row],[Fecha]],"ddd")) -> MA | E33: 110325126 | F33: VACA | G33: GOUDA_F | H33: 17 | I33: =+Tabla_master_rend[[#This Row],[L_Leche_ent]]+Tabla_master_rend[[#This Row],[L_desn_ext]]+Tabla_master_rend[[#This Row],[L_cabra]]+Tabla_master_rend[[#This Row],[L_oveja]] -> 271762 | J33: 271762 | K33: 0.0381 | L33: 0.0336 | M33: =0.93*K33+0.74*L33+0.048 -> 0.108297 | N33: NO | O33: 0 | P33: 0 | Q33: 0 | R33: 3290 | T33: 224230 | U33: =+Tabla_master_rend[[#This Row],[L_suero Total]]/Tabla_master_rend[[#This Row],[Litros_Leche_Total]] -> 0.82509696 | V33: 0.0018 | W33: 0.0088 | X33: 124695 | Y33: 40442 | Z33: =IF(Tabla_master_rend[[#This Row],[L_suero para con]]=0,0,+Tabla_master_rend[[#This Row],[L_suero para con]]/Tabla_master_rend[[#This Row],[L_suero_con]]) -> 3.0833045 | AA33: =+Tabla_master_rend[[#This Row],[L_suero Total]]-Tabla_master_rend[[#This Row],[L_suero para con]] -> 99535 | AI33: =+Tabla_master_rend[[#This Row],[Kg_Finos]]+Tabla_master_rend[[#This Row],[Kg_Llenadora]]+Tabla_master_rend[[#This Row],[Kg_Desmoldeo]]+Tabla_master_rend[[#This Row],[L_Agua]]+Tabla_master_rend[[#This Row],[Kg_SalidaSecadero]] -> 31068.02 | AJ33: =+Tabla_master_rend[[#This Row],[Litros_Leche_Total]]/Tabla_master_rend[[#This Row],[Kg_Queso_Blan]] -> 8.7473228 | AK33: =+Tabla_master_rend[[#This Row],[Litros_Leche_Total]]/(Tabla_master_rend[[#This Row],[Kg_Queso_Blan]]-Tabla_master_rend[[#This Row],[Merma_TOT]]) -> 8.9199039 | AL33: =VLOOKUP(G33,REND_TARGET[#All],8,FALSE) -> 9.354943 | AM33: =(I33*1.03*Tabla_master_rend[[#This Row],[%MG_Leche]])+(I33*1.03*Tabla_master_rend[[#This Row],[%MP_Leche]]) -> 20069.895 | AN33: 0.2916 | AO33: 0.2378 | AP33: 0.5785 | AQ33: =+Tabla_master_rend[[#This Row],[Kg_Queso_Blan]]*Tabla_master_rend[[#This Row],[ES_QUESO]]/(Tabla_master_rend[[#This Row],[Kg_Solidos_leche]]) -> 0.89551286 | AR33: =R33*0.4 -> 1316 | AS33: =+(Tabla_master_rend[[#This Row],[Kg_Queso_Blan]]*Tabla_master_rend[[#This Row],[%MG_QUESO]]+(Tabla_master_rend[[#This Row],[Kg_MG_Nata]]))/(Tabla_master_rend[[#This Row],[Litros_Leche_Total]]*1.03*Tabla_master_rend[[#This Row],[%MG_Leche]]) -> 0.97287125 | AT33: =+Tabla_master_rend[[#This Row],[Kg_Queso_Blan]]*Tabla_master_rend[[#This Row],[%PT_QUESO]]/(Tabla_master_rend[[#This Row],[Litros_Leche_Total]]*1.03*Tabla_master_rend[[#This Row],[%MP_Leche]]) -> 0.78552533 | AU33: =AR33*$CO$3 -> 9870 | AV33: 56.32 | AW33: 62.7 | AX33: 13 | AY33: =SUM(Tabla_master_rend[[#This Row],[Kg_Finos]:[Kg_Desmoldeo]]) -> 132.02 | AZ33: =+(Tabla_master_rend[[#This Row],[Kg_Finos]]+Tabla_master_rend[[#This Row],[Kg_Llenadora]]+Tabla_master_rend[[#This Row],[Kg_Desmoldeo]])/(Tabla_master_rend[[#This Row],[Kg_Queso_Blan]]) -> 0.0042493857 | BA33: 325 | BB33: =+Tabla_master_rend[[#This Row],[L_Agua]]/(Tabla_master_rend[[#This Row],[L_Agua]]+Tabla_master_rend[[#This Row],[Kg_SalidaSecadero]]) -> 0.01050556 | BC33: 4304 | BD33: 4258 | BE33: 30652 | BF33: =17*6.2 -> 105.4 | BG33: =8*6.2 -> 49.6 | BH33: =5*6.2 -> 31 | BI33: =15*6.2 -> 93 | BJ33: 110 | BK33: 30611 | BL33: 7.02 | BM33: 105.11 | BN33: 31.95 | BO33: =+SUM(Tabla_master_rend[[#This Row],[B_altas]:[B_lab]])/Tabla_master_rend[[#This Row],[Kg_SalidaSecadero]] -> 0.01270785 | BP33: =+(Tabla_master_rend[[#This Row],[Kg_mer_env_real]]+Tabla_master_rend[[#This Row],[kg_mer_lab_real]])/Tabla_master_rend[[#This Row],[Kg_SalidaSecadero]] -> 0.0044774754 | BQ33: =+Tabla_master_rend[[#This Row],[Merma_TOT]]/Tabla_master_rend[[#This Row],[Kg_Queso_Blan]] -> 0.01934787 | BR33: =+Tabla_master_rend[[#This Row],[kg_mer_lab_real]]+Tabla_master_rend[[#This Row],[Kg_mer_env_real]]+Tabla_master_rend[[#This Row],[Kg_rebaba]]+Tabla_master_rend[[#This Row],[L_Agua]]+Tabla_master_rend[[#This Row],[Kg_Desmoldeo]]+Tabla_master_rend[[#This Row],[Kg_Llenadora]]+Tabla_master_rend[[#This Row],[Kg_Finos]] -> 601.1 | BT33: =IF(+Tabla_master_rend[[#This Row],[Kg_Env_Total]]=0,0,Tabla_master_rend[[#This Row],[Kg_Env_Total]]-Tabla_master_rend[[#This Row],[Kg_SalidaSecadero]]) -> 0 | BU33: =+Tabla_master_rend[[#This Row],[Diferencia_Env_vs_Sec_kg]]/Tabla_master_rend[[#This Row],[Kg_SalidaSecadero]] -> 0 | BV33: =IFERROR(Tabla_master_rend[[#This Row],[Litros_Leche_Total]]*SUMIFS(tbl_PrecioLeche[PMV_eur_L],tbl_PrecioLeche[AñoMes],TEXT(Tabla_master_rend[[#This Row],[Fecha]],"yyyy-mm"),tbl_PrecioLeche[Tipo_Leche],Tabla_master_rend[[#This Row],[Tipo_Leche]]),"") -> 0 | BW33: =+(Tabla_master_rend[[#This Row],[Coste_Leche_€]]-Tabla_master_rend[[#This Row],[Kg_MG_Nata]]*$CO$3)/Tabla_master_rend[[#This Row],[Kg_Queso_Blan]] -> -0.31769002 | BX33: =SUM(Tabla_master_rend[[#This Row],[Kg_Finos]:[Kg_Desmoldeo]])+Tabla_master_rend[[#This Row],[L_Agua]]+SUM(Tabla_master_rend[[#This Row],[B_altas]:[B_lab]]) -> 846.02 | BY33: =+BX33-Tabla_master_rend[[#This Row],[Merma_TOT]] -> 244.92 | BZ33: =+BY33/BX33 -> 0.2894967 | CA33: =+Tabla_master_rend[[#This Row],[Kg_Queso_Blan]]*$CA$1 -> 201.94213 | CB33: =+Tabla_master_rend[[#This Row],[Kg_Queso_Blan]]*($CB$1-$CA$1) -> 108.73807 | CC33: =+(Tabla_master_rend[[#This Row],[Kg_Queso_Blan]]-CA33-CB33)*$CC$1 -> 322.95207 | CD33: =+CA33+CB33+CC33 -> 633.63227 | CE33: =+CD33/Tabla_master_rend[[#This Row],[Kg_Queso_Blan]] -> 0.020395 | CF33: =+Tabla_master_rend[[#This Row],[Merma_TOT]]/Tabla_master_rend[[#This Row],[Kg_Queso_Blan]] -> 0.01934787 | CG33: =CD33-Tabla_master_rend[[#This Row],[Merma_TOT]] -> 32.532268 | CH33: {=-BR33 * IFERROR(INDEX('Precio Leche_EBITDA_Ventas'!$BD$87:$BD$110,MATCH(1,('Precio Leche_EBITDA_Ventas'!$AZ$87:$AZ$110=YEAR(A33))*('Precio Leche_EBITDA_Ventas'!$BB$87:$BB$110=C33),0)),1.3)} -> -2103.85 | CI33: =+CG33*$CM$2 -> 42.291948
A34: 45729 | B34: 3 | C34: =+UPPER(TEXT(Tabla_master_rend[[#This Row],[Fecha]],"MMM")) -> MAR | D34: =+UPPER(TEXT(Tabla_master_rend[[#This Row],[Fecha]],"ddd")) -> JU | E34: 130325026 | F34: VACA | G34: GOUDA | H34: 18 | I34: =+Tabla_master_rend[[#This Row],[L_Leche_ent]]+Tabla_master_rend[[#This Row],[L_desn_ext]]+Tabla_master_rend[[#This Row],[L_cabra]]+Tabla_master_rend[[#This Row],[L_oveja]] -> 266346 | J34: 266346 | K34: 0.0382 | L34: 0.0335 | M34: =0.93*K34+0.74*L34+0.048 -> 0.108316 | N34: SI | O34: 0 | P34: 0 | Q34: 0 | R34: 2629 | T34: 237870 | U34: =+Tabla_master_rend[[#This Row],[L_suero Total]]/Tabla_master_rend[[#This Row],[Litros_Leche_Total]] -> 0.89308644 | V34: 0.0025 | W34: 0.0096 | X34: 237928 | Y34: 82283 | Z34: =IF(Tabla_master_rend[[#This Row],[L_suero para con]]=0,0,+Tabla_master_rend[[#This Row],[L_suero para con]]/Tabla_master_rend[[#This Row],[L_suero_con]]) -> 2.8915815 | AA34: =+Tabla_master_rend[[#This Row],[L_suero Total]]-Tabla_master_rend[[#This Row],[L_suero para con]] -> -58 | AI34: =+Tabla_master_rend[[#This Row],[Kg_Finos]]+Tabla_master_rend[[#This Row],[Kg_Llenadora]]+Tabla_master_rend[[#This Row],[Kg_Desmoldeo]]+Tabla_master_rend[[#This Row],[L_Agua]]+Tabla_master_rend[[#This Row],[Kg_SalidaSecadero]] -> 33231.32 | AJ34: =+Tabla_master_rend[[#This Row],[Litros_Leche_Total]]/Tabla_master_rend[[#This Row],[Kg_Queso_Blan]] -> 8.0149088 | AK34: =+Tabla_master_rend[[#This Row],[Litros_Leche_Total]]/(Tabla_master_rend[[#This Row],[Kg_Queso_Blan]]-Tabla_master_rend[[#This Row],[Merma_TOT]]) -> 8.3812848 | AL34: =VLOOKUP(G34,REND_TARGET[#All],8,FALSE) -> 8.494317 | AM34: =(I34*1.03*Tabla_master_rend[[#This Row],[%MG_Leche]])+(I34*1.03*Tabla_master_rend[[#This Row],[%MP_Leche]]) -> 19669.918 | AN34: 0.2872 | AO34: 0.2329 | AP34: 0.571 | AQ34: =+Tabla_master_rend[[#This Row],[Kg_Queso_Blan]]*Tabla_master_rend[[#This Row],[ES_QUESO]]/(Tabla_master_rend[[#This Row],[Kg_Solidos_leche]]) -> 0.96467526 | AR34: =R34*0.4 -> 1051.6 | AS34: =+(Tabla_master_rend[[#This Row],[Kg_Queso_Blan]]*Tabla_master_rend[[#This Row],[%MG_QUESO]]+(Tabla_master_rend[[#This Row],[Kg_MG_Nata]]))/(Tabla_master_rend[[#This Row],[Litros_Leche_Total]]*1.03*Tabla_master_rend[[#This Row],[%MG_Leche]]) -> 1.0110677 | AT34: =+Tabla_master_rend[[#This Row],[Kg_Queso_Blan]]*Tabla_master_rend[[#This Row],[%PT_QUESO]]/(Tabla_master_rend[[#This Row],[Litros_Leche_Total]]*1.03*Tabla_master_rend[[#This Row],[%MP_Leche]]) -> 0.84214887 | AU34: =AR34*$CO$3 -> 7887 | AV34: 83.82 | AW34: 296 | AX34: 31.5 | AY34: =SUM(Tabla_master_rend[[#This Row],[Kg_Finos]:[Kg_Desmoldeo]]) -> 411.32 | AZ34: =+(Tabla_master_rend[[#This Row],[Kg_Finos]]+Tabla_master_rend[[#This Row],[Kg_Llenadora]]+Tabla_master_rend[[#This Row],[Kg_Desmoldeo]])/(Tabla_master_rend[[#This Row],[Kg_Queso_Blan]]) -> 0.01237748 | BA34: 825 | BB34: =+Tabla_master_rend[[#This Row],[L_Agua]]/(Tabla_master_rend[[#This Row],[L_Agua]]+Tabla_master_rend[[#This Row],[Kg_SalidaSecadero]]) -> 0.025137112 | BC34: 4660 | BD34: 4595 | BE34: 32420 | BF34: =3*6.2 -> 18.6 | BG34: =4*6.2 -> 24.8 | BH34: =3*6.2 -> 18.6 | BI34: =40*6.2 -> 248 | BJ34: 108 | BK34: 31995 | BL34: 2.86 | BM34: 189.57 | BN34: 23.91 | BO34: =+SUM(Tabla_master_rend[[#This Row],[B_altas]:[B_lab]])/Tabla_master_rend[[#This Row],[Kg_SalidaSecadero]] -> 0.013064541 | BP34: =+(Tabla_master_rend[[#This Row],[Kg_mer_env_real]]+Tabla_master_rend[[#This Row],[kg_mer_lab_real]])/Tabla_master_rend[[#This Row],[Kg_SalidaSecadero]] -> 0.0066722925 | BQ34: =+Tabla_master_rend[[#This Row],[Merma_TOT]]/Tabla_master_rend[[#This Row],[Kg_Queso_Blan]] -> 0.043713581 | BR34: =+Tabla_master_rend[[#This Row],[kg_mer_lab_real]]+Tabla_master_rend[[#This Row],[Kg_mer_env_real]]+Tabla_master_rend[[#This Row],[Kg_rebaba]]+Tabla_master_rend[[#This Row],[L_Agua]]+Tabla_master_rend[[#This Row],[Kg_Desmoldeo]]+Tabla_master_rend[[#This Row],[Kg_Llenadora]]+Tabla_master_rend[[#This Row],[Kg_Finos]] -> 1452.66 | BT34: =IF(+Tabla_master_rend[[#This Row],[Kg_Env_Total]]=0,0,Tabla_master_rend[[#This Row],[Kg_Env_Total]]-Tabla_master_rend[[#This Row],[Kg_SalidaSecadero]]) -> 0 | BU34: =+Tabla_master_rend[[#This Row],[Diferencia_Env_vs_Sec_kg]]/Tabla_master_rend[[#This Row],[Kg_SalidaSecadero]] -> 0 | BV34: =IFERROR(Tabla_master_rend[[#This Row],[Litros_Leche_Total]]*SUMIFS(tbl_PrecioLeche[PMV_eur_L],tbl_PrecioLeche[AñoMes],TEXT(Tabla_master_rend[[#This Row],[Fecha]],"yyyy-mm"),tbl_PrecioLeche[Tipo_Leche],Tabla_master_rend[[#This Row],[Tipo_Leche]]),"") -> 0 | BW34: =+(Tabla_master_rend[[#This Row],[Coste_Leche_€]]-Tabla_master_rend[[#This Row],[Kg_MG_Nata]]*$CO$3)/Tabla_master_rend[[#This Row],[Kg_Queso_Blan]] -> -0.23733634 | BX34: =SUM(Tabla_master_rend[[#This Row],[Kg_Finos]:[Kg_Desmoldeo]])+Tabla_master_rend[[#This Row],[L_Agua]]+SUM(Tabla_master_rend[[#This Row],[B_altas]:[B_lab]]) -> 1654.32 | BY34: =+BX34-Tabla_master_rend[[#This Row],[Merma_TOT]] -> 201.66 | BZ34: =+BY34/BX34 -> 0.12189903 | CA34: =+Tabla_master_rend[[#This Row],[Kg_Queso_Blan]]*$CA$1 -> 216.00358 | CB34: =+Tabla_master_rend[[#This Row],[Kg_Queso_Blan]]*($CB$1-$CA$1) -> 116.30962 | CC34: =+(Tabla_master_rend[[#This Row],[Kg_Queso_Blan]]-CA34-CB34)*$CC$1 -> 345.43957 | CD34: =+CA34+CB34+CC34 -> 677.75277 | CE34: =+CD34/Tabla_master_rend[[#This Row],[Kg_Queso_Blan]] -> 0.020395 | CF34: =+Tabla_master_rend[[#This Row],[Merma_TOT]]/Tabla_master_rend[[#This Row],[Kg_Queso_Blan]] -> 0.043713581 | CG34: =CD34-Tabla_master_rend[[#This Row],[Merma_TOT]] -> -774.90723 | CH34: {=-BR34 * IFERROR(INDEX('Precio Leche_EBITDA_Ventas'!$BD$87:$BD$110,MATCH(1,('Precio Leche_EBITDA_Ventas'!$AZ$87:$AZ$110=YEAR(A34))*('Precio Leche_EBITDA_Ventas'!$BB$87:$BB$110=C34),0)),1.3)} -> -5084.31 | CI34: =+CG34*$CM$2 -> -1007.3794
